Workbook

Sheet Client-Mas-Names
A1: =IFERROR(__xludf.DUMMYFUNCTION("IMPORTRANGE(""1nXhG9zoD3F4ppV4_PoNIKqbOYdLgnLJyE2LlTlfnbOk"", ""Clients!C3:C"")"),"Client") -> Client | B1: =IFERROR(__xludf.DUMMYFUNCTION("IMPORTRANGE(""1nXhG9zoD3F4ppV4_PoNIKqbOYdLgnLJyE2LlTlfnbOk"", ""Clients!E3:E"")"),"Billing Name") -> Billing Name
A2: =IFERROR(__xludf.DUMMYFUNCTION("""COMPUTED_VALUE"""),"Office Monthly Meeting") -> Office Monthly Meeting
A3: =IFERROR(__xludf.DUMMYFUNCTION("""COMPUTED_VALUE"""),"Office (R&D,Testing)") -> Office (R&D,Testing)
A4: =IFERROR(__xludf.DUMMYFUNCTION("""COMPUTED_VALUE"""),"Vinod Lunia-SB Colony") -> Vinod Lunia-SB Colony
A5: =IFERROR(__xludf.DUMMYFUNCTION("""COMPUTED_VALUE"""),"Alagappan - Central Studio Road") -> Alagappan - Central Studio Road
A6: =IFERROR(__xludf.DUMMYFUNCTION("""COMPUTED_VALUE"""),"Samanth Bajaj-Tirupur") -> Samanth Bajaj-Tirupur
A7: =IFERROR(__xludf.DUMMYFUNCTION("""COMPUTED_VALUE"""),"Raja-Ganapathy") -> Raja-Ganapathy
A8: =IFERROR(__xludf.DUMMYFUNCTION("""COMPUTED_VALUE"""),"Manimaran - Namakkal") -> Manimaran - Namakkal
A9: =IFERROR(__xludf.DUMMYFUNCTION("""COMPUTED_VALUE"""),"Ponnusamy - Namakkal") -> Ponnusamy - Namakkal
A10: =IFERROR(__xludf.DUMMYFUNCTION("""COMPUTED_VALUE"""),"Selvakumar-Karur") -> Selvakumar-Karur
A11: =IFERROR(__xludf.DUMMYFUNCTION("""COMPUTED_VALUE"""),"Prabhuram-S B Colony") -> Prabhuram-S B Colony
A12: =IFERROR(__xludf.DUMMYFUNCTION("""COMPUTED_VALUE"""),"Raman - Ramanathapuram") -> Raman - Ramanathapuram
A13: =IFERROR(__xludf.DUMMYFUNCTION("""COMPUTED_VALUE"""),"Saranya Rajkumar-Hopes") -> Saranya Rajkumar-Hopes
A14: =IFERROR(__xludf.DUMMYFUNCTION("""COMPUTED_VALUE"""),"Dhanalakshmi - Lakshmi Mills") -> Dhanalakshmi - Lakshmi Mills
A15: =IFERROR(__xludf.DUMMYFUNCTION("""COMPUTED_VALUE"""),"Dhanakottiram - Gobi") -> Dhanakottiram - Gobi
A16: =IFERROR(__xludf.DUMMYFUNCTION("""COMPUTED_VALUE"""),"Dr.Kumaresh-Gobi") -> Dr.Kumaresh-Gobi
A17: =IFERROR(__xludf.DUMMYFUNCTION("""COMPUTED_VALUE"""),"Jai Elangovan-Coonor") -> Jai Elangovan-Coonor
A18: =IFERROR(__xludf.DUMMYFUNCTION("""COMPUTED_VALUE"""),"Dr. Prabhu-CBE") -> Dr. Prabhu-CBE
A19: =IFERROR(__xludf.DUMMYFUNCTION("""COMPUTED_VALUE"""),"Abirami-Sangagiri") -> Abirami-Sangagiri
A20: =IFERROR(__xludf.DUMMYFUNCTION("""COMPUTED_VALUE"""),"Bipin-Tirupur") -> Bipin-Tirupur
A21: =IFERROR(__xludf.DUMMYFUNCTION("""COMPUTED_VALUE"""),"Sarayu - Tirupur") -> Sarayu - Tirupur
A22: =IFERROR(__xludf.DUMMYFUNCTION("""COMPUTED_VALUE"""),"Arumugam-PSG Hospital") -> Arumugam-PSG Hospital
A23: =IFERROR(__xludf.DUMMYFUNCTION("""COMPUTED_VALUE"""),"Sumanth Ramamoorthy-ELGI") -> Sumanth Ramamoorthy-ELGI
A24: =IFERROR(__xludf.DUMMYFUNCTION("""COMPUTED_VALUE"""),"Nirmal - Salem") -> Nirmal - Salem
A25: =IFERROR(__xludf.DUMMYFUNCTION("""COMPUTED_VALUE"""),"Jayakumar-Chinthamanipudur") -> Jayakumar-Chinthamanipudur
A26: =IFERROR(__xludf.DUMMYFUNCTION("""COMPUTED_VALUE"""),"Dr.Arun-KMCH") -> Dr.Arun-KMCH
A27: =IFERROR(__xludf.DUMMYFUNCTION("""COMPUTED_VALUE"""),"Joseph Kurian (Ashik)-Cbe") -> Joseph Kurian (Ashik)-Cbe
A28: =IFERROR(__xludf.DUMMYFUNCTION("""COMPUTED_VALUE"""),"Dr.Thiyagararjan - Ram Nagar") -> Dr.Thiyagararjan - Ram Nagar
A29: =IFERROR(__xludf.DUMMYFUNCTION("""COMPUTED_VALUE"""),"Selvaraj - Salem") -> Selvaraj - Salem
A30: =IFERROR(__xludf.DUMMYFUNCTION("""COMPUTED_VALUE"""),"Arun-Mettupalayam") -> Arun-Mettupalayam
A31: =IFERROR(__xludf.DUMMYFUNCTION("""COMPUTED_VALUE"""),"Nandhakumar - V'Koil") -> Nandhakumar - V'Koil
A32: =IFERROR(__xludf.DUMMYFUNCTION("""COMPUTED_VALUE"""),"Anoop Shroff - S B Colony") -> Anoop Shroff - S B Colony
A33: =IFERROR(__xludf.DUMMYFUNCTION("""COMPUTED_VALUE"""),"Krishnaveni - Tirupur") -> Krishnaveni - Tirupur
A34: =IFERROR(__xludf.DUMMYFUNCTION("""COMPUTED_VALUE"""),"Subburaj-Vadavali") -> Subburaj-Vadavali
A35: =IFERROR(__xludf.DUMMYFUNCTION("""COMPUTED_VALUE"""),"Selvaraj-Vadavali") -> Selvaraj-Vadavali
A36: =IFERROR(__xludf.DUMMYFUNCTION("""COMPUTED_VALUE"""),"Ramamorthy-Karamadai") -> Ramamorthy-Karamadai
A37: =IFERROR(__xludf.DUMMYFUNCTION("""COMPUTED_VALUE"""),"L N House - Race Course") -> L N House - Race Course
A38: =IFERROR(__xludf.DUMMYFUNCTION("""COMPUTED_VALUE"""),"Suresh (CVS) - Pollachi") -> Suresh (CVS) - Pollachi
A39: =IFERROR(__xludf.DUMMYFUNCTION("""COMPUTED_VALUE"""),"Mr. Prabhakaran") -> Mr. Prabhakaran
A40: =IFERROR(__xludf.DUMMYFUNCTION("""COMPUTED_VALUE"""),"Dinesh Anand-Vadavalli") -> Dinesh Anand-Vadavalli
A41: =IFERROR(__xludf.DUMMYFUNCTION("""COMPUTED_VALUE"""),"Pradeep (Warp)-S B Colony") -> Pradeep (Warp)-S B Colony
A42: =IFERROR(__xludf.DUMMYFUNCTION("""COMPUTED_VALUE"""),"Prism School - Dindugal") -> Prism School - Dindugal
A43: =IFERROR(__xludf.DUMMYFUNCTION("""COMPUTED_VALUE"""),"Thangavel - Pallipalayam") -> Thangavel - Pallipalayam
A44: =IFERROR(__xludf.DUMMYFUNCTION("""COMPUTED_VALUE"""),"Soundarajan-Chinthamanipudur") -> Soundarajan-Chinthamanipudur
A45: =IFERROR(__xludf.DUMMYFUNCTION("""COMPUTED_VALUE"""),"Mr.Nambi - G V Residency ") -> Mr.Nambi - G V Residency
A46: =IFERROR(__xludf.DUMMYFUNCTION("""COMPUTED_VALUE"""),"Emarald Factory - Rakipalayam") -> Emarald Factory - Rakipalayam
A47: =IFERROR(__xludf.DUMMYFUNCTION("""COMPUTED_VALUE"""),"Colonel Baskar-S B Colony") -> Colonel Baskar-S B Colony
A48: =IFERROR(__xludf.DUMMYFUNCTION("""COMPUTED_VALUE"""),"Saha-Vellakinar Pirivu") -> Saha-Vellakinar Pirivu | B48: =IFERROR(__xludf.DUMMYFUNCTION("""COMPUTED_VALUE"""),"Mrs.Kamala Saha") -> Mrs.Kamala Saha
A49: =IFERROR(__xludf.DUMMYFUNCTION("""COMPUTED_VALUE"""),"Arjunan (MLA) - Selvapuram") -> Arjunan (MLA) - Selvapuram
A50: =IFERROR(__xludf.DUMMYFUNCTION("""COMPUTED_VALUE"""),"Sri Nithin") -> Sri Nithin
A51: =IFERROR(__xludf.DUMMYFUNCTION("""COMPUTED_VALUE"""),"Srinivasan-S B Colony") -> Srinivasan-S B Colony | B51: =IFERROR(__xludf.DUMMYFUNCTION("""COMPUTED_VALUE"""),"Chambak Srinivasan") -> Chambak Srinivasan
A52: =IFERROR(__xludf.DUMMYFUNCTION("""COMPUTED_VALUE"""),"Vikram (CS Academy) - Race course") -> Vikram (CS Academy) - Race course
A53: =IFERROR(__xludf.DUMMYFUNCTION("""COMPUTED_VALUE"""),"Isola -Tirupur") -> Isola -Tirupur
A54: =IFERROR(__xludf.DUMMYFUNCTION("""COMPUTED_VALUE"""),"Shanmugam - Chennai") -> Shanmugam - Chennai
A55: =IFERROR(__xludf.DUMMYFUNCTION("""COMPUTED_VALUE"""),"Priya - Gandhi Park") -> Priya - Gandhi Park
A56: =IFERROR(__xludf.DUMMYFUNCTION("""COMPUTED_VALUE"""),"Col.Sridhar (Covai Property) - Trichy Road") -> Col.Sridhar (Covai Property) - Trichy Road
A57: =IFERROR(__xludf.DUMMYFUNCTION("""COMPUTED_VALUE"""),"MSK Anand-Tirupur") -> MSK Anand-Tirupur
A58: =IFERROR(__xludf.DUMMYFUNCTION("""COMPUTED_VALUE"""),"Dr.Balavenkatasubramanian") -> Dr.Balavenkatasubramanian
A59: =IFERROR(__xludf.DUMMYFUNCTION("""COMPUTED_VALUE"""),"Pradeepkumar-Tindivanam") -> Pradeepkumar-Tindivanam
A60: =IFERROR(__xludf.DUMMYFUNCTION("""COMPUTED_VALUE"""),"Aravind (S&A) - Vadamadurai") -> Aravind (S&A) - Vadamadurai
A61: =IFERROR(__xludf.DUMMYFUNCTION("""COMPUTED_VALUE"""),"Pankaj - Tirupur") -> Pankaj - Tirupur
A62: =IFERROR(__xludf.DUMMYFUNCTION("""COMPUTED_VALUE"""),"Diya Enterprises-NSR Road") -> Diya Enterprises-NSR Road
A63: =IFERROR(__xludf.DUMMYFUNCTION("""COMPUTED_VALUE"""),"Velu-Tirupur") -> Velu-Tirupur
A64: =IFERROR(__xludf.DUMMYFUNCTION("""COMPUTED_VALUE"""),"P.S.Vinaykumar") -> P.S.Vinaykumar
A65: =IFERROR(__xludf.DUMMYFUNCTION("""COMPUTED_VALUE"""),"Mr.Amit Mohato - Pricol Apartments") -> Mr.Amit Mohato - Pricol Apartments | B65: =IFERROR(__xludf.DUMMYFUNCTION("""COMPUTED_VALUE"""),"Mr.Amit") -> Mr.Amit
A66: =IFERROR(__xludf.DUMMYFUNCTION("""COMPUTED_VALUE"""),"Rajesh-R.S. Puram") -> Rajesh-R.S. Puram
A67: =IFERROR(__xludf.DUMMYFUNCTION("""COMPUTED_VALUE"""),"Ramani Hondai - Salem") -> Ramani Hondai - Salem
A68: =IFERROR(__xludf.DUMMYFUNCTION("""COMPUTED_VALUE"""),"SKM Buildres P.Ltd") -> SKM Buildres P.Ltd
A69: =IFERROR(__xludf.DUMMYFUNCTION("""COMPUTED_VALUE"""),"Dr.Ranganathan") -> Dr.Ranganathan
A70: =IFERROR(__xludf.DUMMYFUNCTION("""COMPUTED_VALUE"""),"Nishanth Chandren - Chennai") -> Nishanth Chandren - Chennai | B70: =IFERROR(__xludf.DUMMYFUNCTION("""COMPUTED_VALUE"""),"Wintlet ") -> Wintlet
A71: =IFERROR(__xludf.DUMMYFUNCTION("""COMPUTED_VALUE"""),"Senthilkumar (P P Associates)") -> Senthilkumar (P P Associates)
A72: =IFERROR(__xludf.DUMMYFUNCTION("""COMPUTED_VALUE"""),"Apex-Vedapatti") -> Apex-Vedapatti
A73: =IFERROR(__xludf.DUMMYFUNCTION("""COMPUTED_VALUE"""),"Mr.Ethiraj-Saravanampatty") -> Mr.Ethiraj-Saravanampatty
A74: =IFERROR(__xludf.DUMMYFUNCTION("""COMPUTED_VALUE"""),"Ramani Sankar - Ketti") -> Ramani Sankar - Ketti
A75: =IFERROR(__xludf.DUMMYFUNCTION("""COMPUTED_VALUE"""),"Arun-Palakkad") -> Arun-Palakkad | B75: =IFERROR(__xludf.DUMMYFUNCTION("""COMPUTED_VALUE"""),"Balaji Fuels") -> Balaji Fuels
A76: =IFERROR(__xludf.DUMMYFUNCTION("""COMPUTED_VALUE"""),"Srinivas - Race Course") -> Srinivas - Race Course
A77: =IFERROR(__xludf.DUMMYFUNCTION("""COMPUTED_VALUE"""),"Lavanya Shankar - S B Colony") -> Lavanya Shankar - S B Colony
A78: =IFERROR(__xludf.DUMMYFUNCTION("""COMPUTED_VALUE"""),"Diamond City") -> Diamond City
A79: =IFERROR(__xludf.DUMMYFUNCTION("""COMPUTED_VALUE"""),"Gopalakrishnan-TVS Nagar") -> Gopalakrishnan-TVS Nagar
A80: =IFERROR(__xludf.DUMMYFUNCTION("""COMPUTED_VALUE"""),"Anandhakrishnan-Tuticorin") -> Anandhakrishnan-Tuticorin | B80: =IFERROR(__xludf.DUMMYFUNCTION("""COMPUTED_VALUE"""),"Divya Impex") -> Divya Impex
A81: =IFERROR(__xludf.DUMMYFUNCTION("""COMPUTED_VALUE"""),"Senthilanand - Tuticorin") -> Senthilanand - Tuticorin
A82: =IFERROR(__xludf.DUMMYFUNCTION("""COMPUTED_VALUE"""),"Arun - Tuticorin") -> Arun - Tuticorin
A83: =IFERROR(__xludf.DUMMYFUNCTION("""COMPUTED_VALUE"""),"Suresh Ramadass - Vedapatti") -> Suresh Ramadass - Vedapatti
A84: =IFERROR(__xludf.DUMMYFUNCTION("""COMPUTED_VALUE"""),"Mrs.Dinesh Nair (Foundation One)") -> Mrs.Dinesh Nair (Foundation One)
A85: =IFERROR(__xludf.DUMMYFUNCTION("""COMPUTED_VALUE"""),"Krishnamoorthy -vadavalli") -> Krishnamoorthy -vadavalli
A86: =IFERROR(__xludf.DUMMYFUNCTION("""COMPUTED_VALUE"""),"Jagadeesh Kannan - Puliyakullam") -> Jagadeesh Kannan - Puliyakullam
A87: =IFERROR(__xludf.DUMMYFUNCTION("""COMPUTED_VALUE"""),"Mr.Ranjith - Vadavalli") -> Mr.Ranjith - Vadavalli
A88: =IFERROR(__xludf.DUMMYFUNCTION("""COMPUTED_VALUE"""),"Dhanam Automobiles ") -> Dhanam Automobiles
A89: =IFERROR(__xludf.DUMMYFUNCTION("""COMPUTED_VALUE"""),"Vijayanand-SB Colony") -> Vijayanand-SB Colony
A90: =IFERROR(__xludf.DUMMYFUNCTION("""COMPUTED_VALUE"""),"Anandh-Kovilmedu") -> Anandh-Kovilmedu
A91: =IFERROR(__xludf.DUMMYFUNCTION("""COMPUTED_VALUE"""),"Sankar & Associates") -> Sankar & Associates
A92: =IFERROR(__xludf.DUMMYFUNCTION("""COMPUTED_VALUE"""),"Ramalingam (Auditor)") -> Ramalingam (Auditor)
A93: =IFERROR(__xludf.DUMMYFUNCTION("""COMPUTED_VALUE"""),"Arun - Kovaiputhur") -> Arun - Kovaiputhur
A94: =IFERROR(__xludf.DUMMYFUNCTION("""COMPUTED_VALUE"""),"Mr.Mahender Mandradiar") -> Mr.Mahender Mandradiar
A95: =IFERROR(__xludf.DUMMYFUNCTION("""COMPUTED_VALUE"""),"Mr.Ashvinkumar") -> Mr.Ashvinkumar
A96: =IFERROR(__xludf.DUMMYFUNCTION("""COMPUTED_VALUE"""),"BKS House (Sudha Madam Mother Home)") -> BKS House (Sudha Madam Mother Home)
A97: =IFERROR(__xludf.DUMMYFUNCTION("""COMPUTED_VALUE"""),"Mrs.Kalavathy - Vadavalli") -> Mrs.Kalavathy - Vadavalli
A98: =IFERROR(__xludf.DUMMYFUNCTION("""COMPUTED_VALUE"""),"Mohit Jain (Palak)") -> Mohit Jain (Palak)
A99: =IFERROR(__xludf.DUMMYFUNCTION("""COMPUTED_VALUE"""),"Vairavan ") -> Vairavan
A100: =IFERROR(__xludf.DUMMYFUNCTION("""COMPUTED_VALUE"""),"Mr.Vimal Kannan - Kambam") -> Mr.Vimal Kannan - Kambam
...

Sheet BOM Overview
I1: Customer approval pending | J1: Inka side pending | K1: Inka side pending | L1: Inka side pending | M1: Inka side pending | O1: Ok | Q1: Inka service pending | R1: Inka service pending | S1: Inka service pending | U1: Ok
C2: Client Name | D2: Vijayalakshmi - Palladam | E2: Estimate BOM | F2: Addl./Subtract | G2: Total | H2: Zoho Bom | I2: Awaiting order request | J2: To order material | K2: Ordered | L2: Recd (To test/config) | M2: Configured - ready for install | N2: Inka Side Pending | O2: Delivered | P2: Provision only - Matl Not reqd | Q2: Failed - Picked up from site | R2: Failed - Need to service | S2: Sent for service | T2: Inka Service Pending | U2: Replaced/Serviced | V2: Returned - Not reqd
H3: (From DCs in Zoho)
A4: camera | B4: Brand | C4: Product | D4: Model No
B5: WBOX | C5: {=unique('Apex-Vedapatti'!C17:C88)} -> #REF! | D5: 12312as | E5: =countif('Apex-Vedapatti '!C$18:C$106,C5) -> 0
E6: =countif('Apex-Vedapatti '!C$18:C$106,C6) -> 0
E7: =countif('Apex-Vedapatti '!C$18:C$106,C7) -> 0 | I7: 1
E8: =countif('Apex-Vedapatti '!C$18:C$106,C8) -> 0
E9: =countif('Apex-Vedapatti '!C$18:C$106,C9) -> 0
E10: =countif('Apex-Vedapatti '!C$18:C$106,C10) -> 0
E11: =countif('Apex-Vedapatti '!C$18:C$106,C11) -> 0 | I11: API for pulling DCs
E12: =countif('Apex-Vedapatti '!C$18:C$106,C12) -> 0 | I12: https://books.zoho.com/api/v3/deliverychallans?organization_id=65760XXX7
E13: =countif('Apex-Vedapatti '!C$18:C$106,C13) -> 0
E14: =countif('Apex-Vedapatti '!C$18:C$106,C14) -> 0
E15: =countif('Apex-Vedapatti '!C$18:C$106,C15) -> 0 | I15: 3 | L15: 2 | M15: 1 | N15: 3
E16: =countif('Apex-Vedapatti '!C$18:C$106,C16) -> 0
E17: =countif('Apex-Vedapatti '!C$18:C$106,C17) -> 0
E18: =countif('Apex-Vedapatti '!C$18:C$106,C18) -> 0
E19: =countif('Apex-Vedapatti '!C$18:C$106,C19) -> 0
E20: =countif('Apex-Vedapatti '!C$18:C$106,C20) -> 0
E21: =countif('Apex-Vedapatti '!C$18:C$106,C21) -> 0
E22: =countif('Apex-Vedapatti '!C$18:C$106,C22) -> 0
E23: =countif('Apex-Vedapatti '!C$18:C$106,C23) -> 0
E24: =countif('Apex-Vedapatti '!C$18:C$106,C24) -> 0
E25: =countif('Apex-Vedapatti '!C$18:C$106,C25) -> 0
E26: =countif('Apex-Vedapatti '!C$18:C$106,C26) -> 0
E27: =countif('Apex-Vedapatti '!C$18:C$106,C27) -> 0

Sheet ClientProjects List
B1: Sheet No. | C1: Client Name | D1: Site | E1: Eng. in Charge of BOM | F1: Link | G1: G-Drive Link (Drawings & BOM) | H1: Site Status | I1: Site Status | J1: Provisions | K1: BOM | L1: Remarks | M1: Stage 1- Visit Counts needed | N1: Stage 2 - Visit Counts needed | O1: Visited count Stage 1 | P1: Visited count stage 2 | Q1: % work completed | R1: As on
A2: Vijalakshmi - Palladam | C2: Vijayalakshmi | D2: Palladam | E2: Sakthi | F2: Vijayalakshmi | G2: https://drive.google.com/open?id=13cvRfsalE__mU8atlx5vs60QfmFuhd6g | L2: Except SS all materials ready
A3: Dr.Karthik-Mettupalayam | B3: 49 | C3: Karthik | D3: Mettupalayam | E3: Sakthi | F3: Dr. Karthik
A4: Suresh Prabhagaran-salem | B4: 81 | C4: Suresh | D4: Salem | F4: Suresh Prabhagaran
A5: Karthikeyan-Tirupur | B5: 105 | C5: Karthikeyan | D5: Tirupur | E5: Sakthi | F5: Karthikeyan
A6: Shan Vembutty | B6: 107 | C6: Sudarshan | D6: Chettipalayam | E6: Asok | F6: Sudarshan
A7: Vanji-NavIndia | B7: 121 | C7: Vanji | D7: Nav India | E7: Asok | F7: Vanji | R7: 13.3.2024
B8: 135 | C8: Srinivasan | D8: Tirupur | E8: Sakthi | F8: Srinivasan
A9: Ar. Mohanraj | B9: 136 | C9: Mohanraj | D9: Coimbatore | E9: Sakthi | F9: Ar. Mohanraj
A10: Prabhu-Palladam | B10: 142 | C10: Prabhu | D10: Palladam | E10: Asok | F10: Prabhu | R10: 18.2.2024
A11: Vijayabharathi-Palani | B11: 144 | C11: Vijayabharathi | D11: Palani | E11: Pistis | F11: Vijayabharathi
A12: Ar.Sathiya | B12: 146 | C12: Sathiya | D12: Saravanampatti | E12: Asok | F12: Madblack
A13: ALC | B13: 147 | C13: Arthanari | D13: Salem | E13: Asok | F13: ALC
A14: Prabhu-Tirupur | B14: 148 | C14: Prabhu | D14: Tirupur | E14: Asok | F14: Prabhu
A15: Dhanraj | B15: 149 | C15: Dhanraj | D15: Puliayampatti | E15: Asok | F15: Dhanraj | R15: 4.4.2024
A16: SPP Silk House-Mr Karthikeyan | B16: 152 | C16: SPP Silk House | D16: Cheran Nagar | E16: Asok | F16: SPP Silks | G16: FF - 4 Rooms - Dimming, Mobile app Additional need zmote for tata sky
A17: Chandrasekar | B17: 155 | C17: Chandrasekar | D17: Tindivanam | E17: Pistis | F17: Chandrasekar
A18: Gopalakrishnan | B18: 158 | C18: Gopalakrishnan | D18: Tirupur | E18: Sakthi | F18: Gopalakrishnan
A19: Arun Vijay | B19: 159 | C19: Arun Vijay | D19: Krishnagiri | E19: Asok | F19: Arun Vijay
A20: Punita | B20: 162 | C20: Punita | D20: Kalapatti | E20: Asok | F20: Punita | G20: Door sensor -5 Nos.
A21: Venba Residence | B21: 164 | C21: Venba | D21: Coimbatore | E21: Asok | F21: Venba | G21: Biometric pending
A22: Singaram | B22: 165 | C22: Singaram | D22: Saibaba colony | E22: Sakthi | F22: Singaram | G22: Balance payment to receive
A23: Sumanth Ramamoorthy-ELGI | B23: 192 | C23: Sumanth | D23: Race Course | E23: Asok
A24: Aarthi Residence | B24: 166 | C24: Vignesh | D24: kalapatti | E24: Asok | F24: Vignesh
A25: Manikandan-Vedasanthur | B25: 172 | C25: Manikandan | D25: Vedasanthur | E25: Asok | F25: Manikandan
A26: Shivakumar, Kothagiri | B26: 173 | C26: Shivakumar | D26: Kothagiri | E26: Asok | F26: Shivakumar
A27: Dinesh | B27: 176 | C27: Dinesh | D27: Sathyamangalam | F27: Dinesh
A28: Thirumoorthy | B28: 179 | C28: Thirumoorthy | D28: Karur | E28: Asok | F28: Thirumoorthy | G28: temporarily installed 4 cameras
A29: Karpagavalli, Namakkal | B29: 184 | C29: Karpavalli | D29: Namakkal | E29: Kumaraguru | F29: Karpagavalli
A30: Studio Mello | B30: 187 | C30: Studio Mello | D30: Salem | E30: Sakthi | F30: Studio Mello
A31: Janani (JCA Residence) | B31: 188 | C31: Janani | D31: Tirupur | E31: Sakthi | F31: Janani (JCA Residence)
A32: Aarthi Harish | B32: 190 | C32: Aarthi Harish | D32: Ganapathy | E32: Asok | F32: Aarthi Harish
A33: Senthil-Asian Pavers | B33: 193 | C33: Senthil | D33: Saravanampatti | E33: Asok | F33: Senthil
A34: Dhanabal | B34: 194 | C34: Dhanabal | D34: Gounder mills | E34: Sakthi | F34: Dhanabal
A35: Raja | B35: 195 | C35: Raja | D35: Tirupur | E35: Sakthi | F35: Raja
A36: Chandramohan | B36: 196 | C36: Chandramohan | D36: Tirupur | E36: Kumaraguru | F36: Chandramohan
A37: Gunasekar-kalapatti | B37: 198 | C37: Gunasekar | D37: Kalapatti | E37: Sakthi | F37: Gunasekar
A38: Abhishek - Abinitha | B38: 199 | C38: Abhinitha | E38: Asok | F38: Abhishek
A39: Renjith Calicut | B39: 204 | C39: Renjith | D39: Calicut | E39: Asok | F39: Renjith
A40: Pooja Summit | B40: 205 | C40: Pooja | D40: Vallukuparai | E40: Asok | F40: Pooja summit
A41: Duraiswamy | B41: 207 | C41: Duraiswamy | E41: Kumaraguru | F41: Duraiswamy
A42: Erode villa-Mrs.Vinothini | B42: 208 | C42: Vinothini | D42: Erode | E42: Sakthi | F42: Erode Villa
A43: Manohar | B43: 209 | C43: Manohar | D43: Peelamedu | E43: Kumaraguru | F43: Manohar
A44: Mrs. Priyadarshini | B44: 212 | C44: Priyadarshini | D44: Kovilpalayam | E44: Sakthi | F44: Priyadarshini
A45: Mahesh NSN Palayam | B45: 213 | C45: Mahesh | D45: NSN Palayam | E45: Asok | F45: Mahesh
A46: Codissia | B46: 214 | C46: Codissia | D46: Sulur | E46: Asok | F46: Codissia
A47: Prem Kumaran | B47: 215 | C47: Premkumaran | D47: Sitra | E47: Sakthi | F47: Premkumaran
A48: Prakash | B48: 216 | C48: Prakash | D48: Ganapathy | E48: Asok | F48: Prakash
A49: Rajesh | B49: 218 | C49: Dr.Rajesh | D49: Sitra | E49: Asok | F49: Dr.Rajesh
A50: Raja Vellakovil Farm House | B50: 219 | C50: Vellakovil farm house | D50: Vellakovil | E50: Kumaraguru | F50: Raja
A51: Sambath | B51: 220 | D51: Nehru Nagar | E51: Kumaraguru | F51: Sambath
A52: Raghukumaran | B52: 221 | E52: Asok | F52: Raghukumaran
A53: Vinoth -Ponyarajapuram | B53: 222 | C53: Vinoth | D53: Ponyarajapuram | F53: Vinoth Ponyarajapuram
A54: Arrow Hospital | B54: 223 | C54: Arrow | D54: Vadavalli | E54: Kumaraguru | F54: Arrow Hospital
A55: Mohan Atrium House | B55: 225 | C55: Atrium Houe | F55: Mohan Atrium House
A56: Balakrishnan - Pollachi | C56: Balakrishnan | D56: Pollachi | F56: Balakrishnan | H56: Materials to be ordered
A57: Race Course Apartment (Vengateswaran) | B57: 226 | C57: Vengatewaran | D57: Race course | E57: Kumaraguru | F57: Race Course Apartment
A58: Prabhakaran | B58: 228 | C58: Prabhakaran | D58: Ottanchattiram | E58: Azhagar | F58: Prabhakaran
A59: Christopher | B59: 229 | C59: Stalwart | D59: Coimbatore | E59: Asok & Kumaraguru | F59: Christopher
A60: Prithivi | B60: 232 | C60: Prithivi | D60: Coimbatore | E60: Asok | F60: Prithivi
A61: Shruthinth | B61: 231 | C61: Shruthinith | D61: Coimbatore | E61: Kumaraguru | F61: Shruthinith
A62: Chandrika Vittel | B62: 234 | C62: Chandrika Vittel | D62: Saibaba Colony | E62: Sakthi
A63: Kavitha | B63: 230 | C63: Kavitha | D63: Bangalore | E63: Kumaraguru | F63: Kavitha
A64: Anugraha Residence | B64: 233 | C64: Anugraha | D64: Edyarpalayam | E64: Satheesh | F64: Anugraha
A68: Senthil Prabhu | C68: Senthil Prabhu | D68: Cbe | F68: SenthilPrabhu | G68: https://drive.google.com/open?id=1bYOi2XgCzYV7jVF_TB73HyIHas4YTYBy | H68: Payment to be recd
C69: Madan Shankar | D69: Gold Wins | F69: Madan Sankar | G69: https://drive.google.com/open?id=1_OGkRK1NIL1Dc1jQwi_jNh5SszQrxBN6 | H69: Yet to Start
A70: Inka Smart Home | C70: Office | D70: SB Colony | F70: Office
A71: Office Monthly Meeting | C71: Dhanalakshmi | D71: Lakshmi Mills | F71: Dhanalakshmi | G71: https://drive.google.com/open?id=1QlF2_2BPXkVT8TNjnNdkPRGWi8s4TKLv | H71: Cable checklist to be done
A72: Krishnaveni - Tirupur | C72: Krishnaveni | D72: Tirupur | F72: Krishnaveni | G72: https://drive.google.com/drive/folders/13K9gjYPXcLEsXn0fA2BkSyhD5pbNLKX5 | H72: Cable checklist to be done
A73: Bipin-Tirupur | C73: B House | D73: Tirupur | F73: B House | G73: https://drive.google.com/drive/folders/1qHRcia6tdR5LhEx4H-rBLLO2O4_hQANE
A74: Selvakumar - Vadavalli | C74: Selvakumar | D74: Vadavalli | F74: Selvakumar | H74: Cabling check list done | I74: FF Cabling pending
A75: Saravanan Madurai | B75: 51 | C75: Saravanan | D75: Madurai | F75: Saravanan | H75: Prework to be done
A76: Thamarai Residence | B76: 53 | C76: Thamarai | D76: Thanjavur | F76: Thamarai | H76: to order materials
A77: ASMI Villa | B77: 45 | C77: ASMI Villa | D77: Kayalpattinam | F77: ASMI Villa | H77: Cabling work undergoing
A78: Hayagreevas - Palladam | B78: 124 | C78: Hariharan | D78: Kalapatti | F78: Hariharan | H78: Cancelled
A79: Maya Villas-Mr. Faizal | B79: 54 | C79: Maya | D79: Anaikatti | F79: Maya Resorts | H79: Piping checking
A80: Gopal Patel | B80: 78 | C80: Gopal Patel | D80: Pollachi | F80: Gopal Patel | H80: Piping checking Completed
A81: Gokul,Madurai | B81: 88 | C81: Gokul | D81: Madurai | E81: Pistis | F81: Gokul | H81: Cable check list to be done
A82: Anitha Manaria | B82: 116 | C82: Anita Manaria | E82: Pistis | F82: Anita
A83: Balakrishnan - Pollachi | C83: Balakrishnan | D83: Pollachi | F83: Balakrishnan | H83: Materials to be ordered
A84: Naveen - Pollachi | C84: Naveen | D84: Pollachi | F84: Naveen | H84: Installed one door sensor
A85: Sasikala Ganeshan | B85: 89 | C85: Sasikala | D85: Palladam | F85: Sasikala | H85: Automation quotation given to client
A86: Narayan-Vedapatti | B86: 92 | C86: Narayanan | D86: Vedapatti | E86: Sakthi | F86: Narayanan | H86: Cable check list to be done
A87: Ram Ganesh | C87: Ramganesh | D87: Gandhipuram | F87: Ramganesh | G87: https://drive.google.com/drive/folders/11lNl221sCVb3yOhhB5T5N8QCVRz6nfDM | H87: Camera & VDP Completed
A88: Swarnalatha-Pollachi | B88: 75 | C88: Latha | D88: Pollachi | E88: Sakthi | F88: Latha | H88: Cable check list done
A89: Saran Salem | B89: 71 | C89: Saran | D89: Salem | F89: Saran | H89: Sent sales order-Material payment to be recd
A90: Elangovan-Karur | B90: 76 | C90: Elango | D90: Karur | F90: elango
A91: Rajkumar | B91: 127 | C91: Rajkumar | D91: Dharapuram | E91: Asok | F91: Rajkumar
A92: JC Group | B92: 145 | C92: JC Group | D92: Thadagam Road | E92: Pistis | F92: JC Group | R92: 27.10.2023
A93: Ram-Peelamedu | B93: 102 | C93: Ram | D93: Peelamedu | E93: Pistis | F93: Ram
A94: Urban Constorium | B94: 189 | C94: Udhayanad | D94: Near Airport | E94: Sakthi | F94: Urban Constorium
A96: YET to CONFIRM
A97: Selva | C97: Selva | D97: Karur | F97: Selva,Karur
A98: Palanisamy | C98: Palanisamy | D98: Erode | F98: Palanisamy | H98: Yet to start
A99: Ramamoorthy | C99: Ramamoorthy | D99: Karamadai
A100: Jawahar | C100: Jawahar | D100: Namakkal | F100: Jawahar | H100: Yet to start
A101: Dr. Radhika | C101: Radhika | D101: Coimbatore | F101: Dr.Radhika | H101: Yet to start
A102: Senthil, Tirupur office
A103: Balaji Chetty | B103: 134 | C103: Balaji | D103: RS Puram | E103: Sakthi | F103: Balaji | H103: 1st site visit done by Sakthi
A107: COMPLETED PROJECTS | C107: Completed Projects | I107: Service Warranty upto | J107: Camera | K107: Automation | L107: Security Systems
...

Sheet Anugraha Residence
B1: Client Name | C1: Anugraha Residence | F1: Overall site status | J1: Count | K1: % | M1: Material status | N1: Count | O1: % | Q1: Visti No. | R1: IR No. | S1: Date
B2: Site | C2: Edyarpalayam | F2: Yet to start | M2: Awaiting order request | Q2: 1 | S2: 21.2.2026 | T2: 1st site visit | U2: Satheesh & Tharun
B3: Location | F3: Position marked - I | M3: To order material | Q3: 2 | S3: 23.2.2026 | T3: Site meeting | U3: Satheesh
B4: GPS Coordinates | F4: Piping done - C | M4: Ordered
B5: Architect | F5: Wiring done - C | M5: Recd (To test/config)
B6: Site Supervisor | F6: Wiring - Checked Ok - I | M6: Configured - ready for install
B7: Electrician | F7: Wiring rework reqd - C | M7: Delivered
B8: Electrical Contractor | F8: Provision not provided - C | M8: Provision only - Matl Not reqd
B9: Billing contact | F9: Position to be changed - C | M9: Failed - Picked up from site
B10: Carpenter | F10: Installed - working | M10: Failed - Need to service
B11: Civil Supervisor | F11: Installed - To activate - I | M11: Sent for service
B12: G-Drive Link | F12: Installed - Not working - IC | M12: Replaced/Serviced
B13: Mail id | F13: Door Ready - C | M13: Returned - Not reqd
B14: Site Engineer | F14: Door Not Ready - I
B15: Brand | C15: Product | D15: Serial No. | E15: Model No | F15: Sale Price | G15: Installation charge | H15: Location | I15: Drawing Ref No. | J15: Site status | K15: <--Date | L15: Prop/Addl | M15: Material | N15: <-- Date | O15: Client | P15: Inka | Q15: Comments | R15: SR Nos (If multiple - add all) | S15: DC

Sheet Kavitha
B1: Client Name | C1: Mrs. Kavitha | F1: Overall site status | J1: Count | K1: % | M1: Material status | N1: Count | O1: % | Q1: Visti No. | R1: IR No. | S1: Date
B2: Site | C2: Bangalore | F2: Yet to start | M2: Awaiting order request | Q2: 1 | S2: 15.2.2026 | T2: 1st site visit | U2: Kumaraguru
B3: Location | C3: https://www.google.com/maps?q=13.0039654,77.7405749&z=17&hl=en | F3: Position marked - I | M3: To order material | Q3: 2
B4: GPS Coordinates | F4: Piping done - C | M4: Ordered
B5: Architect | F5: Wiring done - C | M5: Recd (To test/config)
B6: Site Supervisor | F6: Wiring - Checked Ok - I | M6: Configured - ready for install
B7: Electrician | C7: Vnktsa Elctr New | E7: 91770 92700 | F7: Wiring rework reqd - C | M7: Delivered
B8: Electrical Contractor | F8: Provision not provided - C | M8: Provision only - Matl Not reqd
B9: Billing contact | F9: Position to be changed - C | M9: Failed - Picked up from site
B10: Carpenter | F10: Installed - working | M10: Failed - Need to service
B11: Civil Supervisor | F11: Installed - To activate - I | M11: Sent for service
B12: G-Drive Link | F12: Installed - Not working - IC | M12: Replaced/Serviced
B13: Mail id | F13: Door Ready - C | M13: Returned - Not reqd
B14: Site Engineer | F14: Door Not Ready - I
B15: Brand | C15: Product | D15: Serial No. | E15: Model No | F15: Sale Price | G15: Installation charge | H15: Location | I15: Drawing Ref No. | J15: Site status | K15: <--Date | L15: Prop/Addl | M15: Material | N15: <-- Date | O15: Client | P15: Inka | Q15: Comments | R15: SR Nos (If multiple - add all) | S15: DC
A16: Camera | B16: Prama Hikivision | C16: 4 MP Bullet IP Camera Colour - Prama Hikvision | E16: PT-NC140D3LIU- D1 | F16: 3950 | G16: 56890 | J16: Yet to start | K16: 15.2.2026 | L16: Prop | Q16: 1st site visit
B17: Prama Hikivision | C17: 4 MP Bullet IP Camera Colour - Prama Hikvision | E17: PT-NC140D3LIU- D1 | F17: 3950 | J17: Yet to start | K17: 15.2.2026 | L17: Prop | Q17: 1st site visit
B18: Prama Hikivision | C18: 4 MP Bullet IP Camera Colour - Prama Hikvision | E18: PT-NC140D3LIU- D1 | F18: 3950 | J18: Yet to start | K18: 15.2.2026 | L18: Prop | Q18: 1st site visit
B19: Prama Hikivision | C19: 4 MP Bullet IP Camera Colour - Prama Hikvision | E19: PT-NC140D3LIU- D1 | F19: 3950 | J19: Yet to start | K19: 15.2.2026 | L19: Prop | Q19: 1st site visit
B20: Prama Hikivision | C20: 4 MP Bullet IP Camera Colour - Prama Hikvision | E20: PT-NC140D3LIU- D1 | F20: 3950 | J20: Yet to start | K20: 15.2.2026 | L20: Prop | Q20: 1st site visit
B21: Prama Hikivision | C21: 4 MP Bullet IP Camera Colour - Prama Hikvision | E21: PT-NC140D3LIU- D1 | F21: 3950 | J21: Yet to start | K21: 15.2.2026 | L21: Prop | Q21: 1st site visit
B22: Prama Hikivision | C22: 4 MP Bullet IP Camera Colour - Prama Hikvision | E22: PT-NC140D3LIU- D1 | F22: 3950 | J22: Yet to start | K22: 15.2.2026 | L22: Prop | Q22: 1st site visit
B23: Prama Hikivision | C23: 4 MP Bullet IP Camera Colour - Prama Hikvision | E23: PT-NC140D3LIU- D1 | F23: 3950 | J23: Yet to start | K23: 15.2.2026 | L23: Prop | Q23: 1st site visit
B24: Prama Hikivision | C24: 4 MP Bullet IP Camera Colour - Prama Hikvision | E24: PT-NC140D3LIU- D1 | F24: 3950 | J24: Yet to start | K24: 15.2.2026 | L24: Prop | Q24: 1st site visit
B25: Prama Hikivision | C25: 4 MP Bullet IP Camera Colour - Prama Hikvision | E25: PT-NC140D3LIU- D1 | F25: 3950 | J25: Yet to start | K25: 15.2.2026 | L25: Prop | Q25: 1st site visit
B26: Prama Hikivision | C26: 4 MP Bullet IP Camera Colour - Prama Hikvision | E26: PT-NC140D3LIU- D1 | F26: 3950 | J26: Yet to start | K26: 15.2.2026 | L26: Prop | Q26: 1st site visit
B27: Hikvision | C27: 16 channel NVR (K2) - Hikvision | E27: DS-7616NI-K2 | F27: 15900 | J27: Yet to start | K27: 15.2.2026 | L27: Prop | Q27: 1st site visit
B28: Toshiba | C28: 4 TB Hard Disk - Toshiba | E28: AVHDDS300 | F28: 8160 | J28: Yet to start | K28: 15.2.2026 | L28: Prop | Q28: 1st site visit
... B30: TP Link | C30: 8 Port POE Switch (Gigabit) 2 Uplink SFP - TP Link | E30: TL-SG2210P | F30: 7990 | J30: Yet to start | K30: 15.2.2026 | L30: Prop | Q30: 1st site visit
C31: Camera Accessories | F31: 2500 | J31: Yet to start | K31: 15.2.2026 | L31: Prop
Q32: 1st site visit
A33: Security system | B33: Hikvision | C33: Hikvision - Control Panel Hybrid | E33: DS-PHA64-LP(B) | F33: 29500 | J33: Yet to start | K33: 15.2.2026 | L33: Prop | Q33: 1st site visit
B34: Hikvision | C34: Hikvision - GSM module | E34: DS-PM2-S | F34: 9773 | J34: Yet to start | K34: 15.2.2026 | L34: Prop | Q34: 1st site visit
B35: Hikvision | C35: Hikvision IP Module | E35: IP Module | F35: 8450 | J35: Yet to start | K35: 15.2.2026 | L35: Prop | Q35: 1st site visit
B36: Hikvision | C36: Hikvision - Wired LCD Keypad | E36: DS-PICI-LRT-HWB | F36: 7237 | J36: Yet to start | K36: 15.2.2026 | L36: Prop | Q36: 1st site visit
B37: Hikvision | C37: Hikvision Door Sensor | E37: DS-PD1-MC-WWS(H) | F37: 450 | J37: Yet to start | K37: 15.2.2026 | L37: Prop | Q37: 1st site visit
B38: Hikvision | C38: Hikvision Door Sensor | E38: DS-PD1-MC-WWS(H) | F38: 450 | J38: Yet to start | K38: 15.2.2026 | L38: Prop | Q38: 1st site visit
B39: Hikvision | C39: Hikvision Door Sensor | E39: DS-PD1-MC-WWS(H) | F39: 450 | J39: Yet to start | K39: 15.2.2026 | L39: Prop | Q39: 1st site visit
B40: Hikvision | C40: Hikvision Door Sensor | E40: DS-PD1-MC-WWS(H) | F40: 450 | J40: Yet to start | K40: 15.2.2026 | L40: Prop | Q40: 1st site visit
B41: Hikvision | C41: Hikvision Door Sensor | E41: DS-PD1-MC-WWS(H) | F41: 450 | J41: Yet to start | K41: 15.2.2026 | L41: Prop | Q41: 1st site visit
B42: Hikvision | C42: Hikvision Door Sensor | E42: DS-PD1-MC-WWS(H) | F42: 450 | J42: Yet to start | K42: 15.2.2026 | L42: Prop | Q42: 1st site visit
B43: Hikvision | C43: Hikvision Door Sensor | E43: DS-PD1-MC-WWS(H) | F43: 450 | J43: Yet to start | K43: 15.2.2026 | L43: Prop | Q43: 1st site visit
B44: DSC | C44: Glass Break Detector Wired (Digital) | E44: LC-105-DGB | F44: 3267 | J44: Yet to start | K44: 15.2.2026 | L44: Prop | Q44: 1st site visit
B45: DSC | C45: Glass Break Detector Wired (Digital) | E45: LC-105-DGB | F45: 3267 | J45: Yet to start | K45: 15.2.2026 | L45: Prop | Q45: 1st site visit
... B55: Hikivision | C55: Hikvision - Wired Siren | E55: DS 109 | F55: 1434 | J55: Yet to start | K55: 15.2.2026 | L55: Prop | Q55: 1st site visit
C56: Battery Backup | E56: 12V-7amp | F56: 2240 | J56: Yet to start | K56: 15.2.2026 | L56: Prop | Q56: 1st site visit
A58: Video Door Phone Calling System | B58: Hikvision | C58: VDP Outdoor Camera - Hikvision | E58: DS-KD8003-IME1/Surface | F58: 11600 | J58: Yet to start | K58: 15.2.2026 | L58: Prop | Q58: 1st site visit
B59: Hikvision | C59: VDP Indoor Monitor - Hikvision | E59: DS-KH6320-WTE1 | F59: 10480 | J59: Yet to start | K59: 15.2.2026 | L59: Prop | Q59: 1st site visit
A61: Wifi Access Point - TP Link | B61: TP Link | C61: Access Point EAP 265 - TP Link | E61: EAP 265 | F61: 8250 | J61: Yet to start | K61: 15.2.2026 | L61: Prop | Q61: 1st site visit
B62: TP Link | C62: Access Point EAP 265 - TP Link | E62: EAP 265 | F62: 8250 | J62: Yet to start | K62: 15.2.2026 | L62: Prop | Q62: 1st site visit
B63: TP Link | C63: Access Point EAP 265 - TP Link | E63: EAP 265 | F63: 8250 | J63: Yet to start | K63: 15.2.2026 | L63: Prop | Q63: 1st site visit
B64: TP Link | C64: Access Point EAP 265 - TP Link | E64: EAP 265 | F64: 8250 | J64: Yet to start | K64: 15.2.2026 | L64: Prop | Q64: 1st site visit
B65: TP Link | C65: Access Point EAP 265 - TP Link | E65: EAP 265 | F65: 8250 | J65: Yet to start | K65: 15.2.2026 | L65: Prop | Q65: 1st site visit
B66: TP Link | C66: Access Point EAP 265 - TP Link | E66: EAP 265 | F66: 8250 | J66: Yet to start | K66: 15.2.2026 | L66: Prop | Q66: 1st site visit
B67: TP Link | C67: Access Point EAP 265 - TP Link | E67: EAP 265 | F67: 8250 | J67: Yet to start | K67: 15.2.2026 | L67: Prop | Q67: 1st site visit
B68: TP Link | C68: Access Point EAP 265 - TP Link | E68: EAP 265 | F68: 8250 | J68: Yet to start | K68: 15.2.2026 | L68: Prop | Q68: 1st site visit
B69: Hikvision | C69: 4 Port POE Switch - Hikvision | E69: DS-3E0105P-E/M | F69: 3750 | J69: Yet to start | K69: 15.2.2026 | L69: Prop | Q69: 1st site visit
A71: Automation | B71: Eglu | C71: In-Wall Switch 3S - Eg | E71: EGIW04R | F71: 10370 | J71: Yet to start | K71: 15.2.2026 | L71: Prop | Q71: 1st site visit
B72: Eglu | C72: In-Wall Switch 3S - Eg | E72: EGIW04R | F72: 10370 | J72: Yet to start | K72: 15.2.2026 | L72: Prop | Q72: 1st site visit
B73: Eglu | C73: In-Wall Switch 3S - Eg | E73: EGIW04R | F73: 10370 | J73: Yet to start | K73: 15.2.2026 | L73: Prop | Q73: 1st site visit
B74: Eglu | C74: In-Wall Switch 3S - Eg | E74: EGIW04R | F74: 10370 | J74: Yet to start | K74: 15.2.2026 | L74: Prop | Q74: 1st site visit
B75: Eglu | C75: In-Wall Switch 3S - Eg | E75: EGIW04R | F75: 10370 | J75: Yet to start | K75: 15.2.2026 | L75: Prop | Q75: 1st site visit
B76: Eglu | C76: In-Wall Switch 3S - Eg | E76: EGIW04R | F76: 10370 | J76: Yet to start | K76: 15.2.2026 | L76: Prop | Q76: 1st site visit
B77: Eglu | C77: IR & Av Control E | E77: EIR | F77: 7503 | J77: Yet to start | K77: 15.2.2026 | L77: Prop | Q77: 1st site visit
B78: Eglu | C78: Automation Hub | E78: EGLU | F78: 34000 | J78: Yet to start | K78: 15.2.2026 | L78: Prop | Q78: 1st site visit

Sheet Chandrika Vittel
B1: Client Name | C1: Mrs.Chandrika Vittel | F1: Overall site status | J1: Count | K1: % | M1: Material status | N1: Count | O1: % | Q1: Visti No. | R1: IR No. | S1: Date
B2: Site | C2: Saibaba Colony | F2: Yet to start | M2: Awaiting order request | Q2: 1 | R2: IR No.53 | S2: 8.12.2025 | T2: 1st site visit | U2: Sakthi
B3: Location | F3: Position marked - I | M3: To order material | Q3: 2
B4: GPS Coordinates | F4: Piping done - C | M4: Ordered
B5: Architect | F5: Wiring done - C | M5: Recd (To test/config)
B6: Site Supervisor | F6: Wiring - Checked Ok - I | M6: Configured - ready for install
B7: Electrician | F7: Wiring rework reqd - C | M7: Delivered
B8: Electrical Contractor | F8: Provision not provided - C | M8: Provision only - Matl Not reqd
B9: Billing contact | F9: Position to be changed - C | M9: Failed - Picked up from site
B10: Carpenter | F10: Installed - working | M10: Failed - Need to service
B11: Civil Supervisor | F11: Installed - To activate - I | M11: Sent for service
B12: G-Drive Link | F12: Installed - Not working - IC | M12: Replaced/Serviced
B13: Mail id | F13: Door Ready - C | M13: Returned - Not reqd
B14: Site Engineer | F14: Door Not Ready - I
B15: Brand | C15: Product | D15: Serial No. | E15: Model No | F15: Sale Price | G15: Installation charge | H15: Location | I15: Drawing Ref No. | J15: Site status | K15: <--Date | L15: Prop/Addl | M15: Material | N15: <-- Date | O15: Client | P15: Inka | Q15: Comments | R15: SR Nos (If multiple - add all) | S15: DC
A16: Camera | B16: CP Plus | C16: 4 Mp Bullet IP Camera Colour/InbuiltMic -CP PLUS | E16: CP-UNC-TA41PL3C-D-LQ-0360 | F16: 4860 | G16: 11000 | L16: Prop
B17: CP Plus | C17: 4 Mp Bullet IP Camera Colour/InbuiltMic -CP PLUS | E17: CP-UNC-TA41PL3C-D-LQ-0360 | F17: 4860 | L17: Prop
B18: CP Plus | C18: 4 Mp Bullet IP Camera Colour/InbuiltMic -CP PLUS | E18: CP-UNC-TA41PL3C-D-LQ-0360 | F18: 4860 | L18: Prop
B19: CP Plus | C19: 4 Mp Bullet IP Camera Colour/InbuiltMic -CP PLUS | E19: CP-UNC-TA41PL3C-D-LQ-0360 | F19: 4860 | L19: Prop
B20: CP Plus | C20: 4 Mp Bullet IP Camera Colour/InbuiltMic -CP PLUS | E20: CP-UNC-TA41PL3C-D-LQ-0360 | F20: 4860 | L20: Prop
B21: CP Plus | C21: 4 Mp Bullet IP Camera Colour/InbuiltMic -CP PLUS | E21: CP-UNC-TA41PL3C-D-LQ-0360 | F21: 4860 | L21: Prop
B22: CP Plus | C22: 4 Mp Bullet IP Camera Colour/InbuiltMic -CP PLUS | E22: CP-UNC-TA41PL3C-D-LQ-0360 | F22: 4860 | L22: Prop
B23: CP Plus | C23: 4 Mp Bullet IP Camera Colour/InbuiltMic -CP PLUS | E23: CP-UNC-TA41PL3C-D-LQ-0360 | F23: 4860 | L23: Prop
B24: CP Plus | C24: 4 MP DOME CAMERA -CP PLUS | E24: CP-UNC-DA41L3C-D-LQ-60 | F24: 4450 | L24: Prop
B25: CP Plus | C25: 16 Channel NVR (2 Sata) - CP Plus | E25: CP-UNR-4K2162/V2 | F25: 20450 | L25: Prop
B26: TP Link | C26: 16 Port POE Gigabit Switch (TL-SG1218MPE) - TP Link | E26: TL-SG1218MPE | F26: 17500 | L26: Prop
B27: WBOX | C27: 8 TB Hard Disk - WD | E27: NIL | F27: 17980 | L27: Prop
C28: Camera Accessories | F28: 2500 | L28: Prop

Sheet Prithivi
B1: Client Name | C1: Mr.Prithivi | F1: Overall site status | J1: Count | K1: % | M1: Material status | N1: Count | O1: % | Q1: Visti No. | R1: IR No. | S1: Date
B2: Site | C2: Coimbatore | F2: Yet to start | M2: Awaiting order request | Q2: 1 | R2: IR No.1448 | S2: 1.12.2025 | T2: 1st site visit | U2: Asok & Kumaraguru
B3: Location | F3: Position marked - I | M3: To order material | Q3: 2
B4: GPS Coordinates | F4: Piping done - C | M4: Ordered
B5: Architect | F5: Wiring done - C | M5: Recd (To test/config)
B6: Site Supervisor | F6: Wiring - Checked Ok - I | M6: Configured - ready for install
B7: Electrician | F7: Wiring rework reqd - C | M7: Delivered
B8: Electrical Contractor | F8: Provision not provided - C | M8: Provision only - Matl Not reqd
B9: Billing contact | F9: Position to be changed - C | M9: Failed - Picked up from site
B10: Carpenter | F10: Installed - working | M10: Failed - Need to service
B11: Civil Supervisor | F11: Installed - To activate - I | M11: Sent for service
B12: G-Drive Link | F12: Installed - Not working - IC | M12: Replaced/Serviced
B13: Mail id | F13: Door Ready - C | M13: Returned - Not reqd
B14: Site Engineer | F14: Door Not Ready - I
B15: Brand | C15: Product | D15: Product | E15: Model No | F15: Sale Price | G15: Installation charge | H15: Location | I15: Drawing Ref No. | J15: Site status | K15: <--Date | L15: Prop/Addl | M15: Material | N15: <-- Date | O15: Client | P15: Inka | Q15: Comments | R15: SR Nos (If multiple - add all) | S15: DC
A16: Automation | B16: KNX | C16: KNX Power Supply 640mA

Sheet Shruthinith
B1: Client Name | C1: Mr.Shruthinith | E1: 9363600603 | F1: Overall site status | J1: Count | K1: % | M1: Material status | N1: Count | O1: % | Q1: Visti No. | R1: IR No. | S1: Date
B2: Site | C2: Coimbatore | F2: Yet to start | M2: Awaiting order request | Q2: 1 | R2: IR No.1473 | S2: 30.1.2026 | T2: 1st site visit | U2: Kumaraguru
B3: Location | F3: Position marked - I | M3: To order material | Q3: 2
B4: GPS Coordinates | F4: Piping done - C | M4: Ordered
B5: Architect | F5: Wiring done - C | M5: Recd (To test/config)
B6: Site Supervisor | F6: Wiring - Checked Ok - I | M6: Configured - ready for install
B7: Electrician | C7: Mr.Shanmugam | E7: 9566955892 | F7: Wiring rework reqd - C | M7: Delivered
B8: Electrical Contractor | F8: Provision not provided - C | M8: Provision only - Matl Not reqd
B9: Billing contact | F9: Position to be changed - C | M9: Failed - Picked up from site
B10: Carpenter | F10: Installed - working | M10: Failed - Need to service
B11: Civil Supervisor | F11: Installed - To activate - I | M11: Sent for service
B12: G-Drive Link | F12: Installed - Not working - IC | M12: Replaced/Serviced
B13: Mail id | F13: Door Ready - C | M13: Returned - Not reqd
B14: Site Engineer | F14: Door Not Ready - I
B15: Brand | C15: Product | D15: Serial No. | E15: Model No | F15: Sale Price | G15: Installation charge | H15: Location | I15: Drawing Ref No. | J15: Site status | K15: <--Date | L15: Prop/Addl | M15: Material | N15: <-- Date | O15: Client | P15: Inka | Q15: Comments | R15: SR Nos (If multiple - add all) | S15: DC
A16: Camera | B16: Hikvision | C16: 4 MP Bullet IP Camera (3043GO-I) - Hikvision | E16: DS - 2CD1043G0-I - 4mm | F16: 6450 | G16: 11401 | L16: Prop
B17: Hikvision | C17: 4 MP Bullet IP Camera (3043GO-I) - Hikvision | E17: DS - 2CD1043G0-I - 4mm | F17: 6450 | L17: Prop
B18: Hikvision | C18: 4 MP Bullet IP Camera (3043GO-I) - Hikvision | E18: DS - 2CD1043G0-I - 4mm | F18: 6450 | L18: Prop
B19: Hikvision | C19: 4 MP Bullet IP Camera (3043GO-I) - Hikvision | E19: DS - 2CD1043G0-I - 4mm | F19: 6450 | L19: Prop
B20: Hikvision | C20: 4 MP Bullet IP Camera (3043GO-I) - Hikvision | E20: DS - 2CD1043G0-I - 4mm | F20: 6450 | L20: Prop
B21: Hikvision | C21: 4 MP Bullet IP Camera (3043GO-I) - Hikvision | E21: DS - 2CD1043G0-I - 4mm | F21: 6450 | L21: Prop
B22: Hikvision | C22: 4 MP Bullet IP Camera (3043GO-I) - Hikvision | E22: DS - 2CD1043G0-I - 4mm | F22: 6450 | L22: Prop
B23: Hikvision | C23: 4 MP Bullet IP Camera (3043GO-I) - Hikvision | E23: DS - 2CD1043G0-I - 4mm | F23: 6450 | L23: Prop
B24: Hikvision | C24: 4 MP Bullet IP Camera (3043GO-I) - Hikvision | E24: DS - 2CD1043G0-I - 4mm | F24: 6450 | L24: Prop
B25: Hikvision | C25: 4 MP Bullet IP Camera (3043GO-I) - Hikvision | E25: DS - 2CD1043G0-I - 4mm | F25: 6450 | L25: Prop
B26: Hikvision | C26: 4 MP Bullet IP Camera (3043GO-I) - Hikvision | E26: DS - 2CD1043G0-I - 4mm | F26: 6450 | L26: Prop
B27: Hikvision | C27: 4 MP Bullet IP Camera (3043GO-I) - Hikvision | E27: DS - 2CD1043G0-I - 4mm | F27: 6450 | L27: Prop
B28: Hikvision | C28: 4 MP Bullet IP Camera (3043GO-I) - Hikvision | E28: DS - 2CD1043G0-I - 4mm | F28: 6450 | L28: Prop
B29: Hikvision | C29: 16 channel NVR (K2) - Hikvision | E29: DS-7616NI-K2 | F29: 15900
B30: TP Link | C30: 8 Port POE Switch (Gigabit) 2 Uplink SFP - TP Link | E30: TL-SG2210P | F30: 8250
B31: TP Link | C31: 8 Port POE Switch (Gigabit) 2 Uplink SFP - TP Link | E31: TL-SG2210P | F31: 8250
B32: Toshiba | C32: 4 TB Hard Disk - Toshiba | E32: AVHDDS300 | F32: 8160
C33: Camera Accessories | F33: 2500
A35: Wifi | B35: TP Link | C35: Access Point EAP245 - TP Link | E35: EAP245 | F35: 8250 | G35: 4125
B36: TP Link | C36: Access Point EAP245 - TP Link | E36: EAP245 | F36: 8250
B37: TP Link | C37: Access Point EAP245 - TP Link | E37: EAP245 | F37: 8250
B38: TP Link | C38: Access Point EAP245 - TP Link | E38: EAP245 | F38: 8250
B39: TP Link | C39: Access Point EAP245 - TP Link | E39: EAP245 | F39: 8250
A41: Video Door Phone System - Hikvision | B41: Hikvision | C41: VDP Outdoor Camera - Hikvision | E41: DS-KD8003-IME1/Surface | F41: 11600 | G41: 2603
B42: Hikvision | C42: VDP Indoor Monitor - Hikvision | E42: DS-KH6320-WTE1 | F42: 10480
B43: TP Link | C43: 4 port POE Gigabit Switch - TP Link | E43: TL-SF1008PG | F43: 3950
A45: Security Alarm System - DSC TYCO | B45: DSC | C45: DSC Hybrid - Control Panel | E45: HS2032NKCE | F45: 21450 | G45: 7126
B46: DSC | C46: DSC - LCD Keypad Kit | E46: HS2LCDS | F46: 5900
B47: DSC | C47: DSC - Power Supply (220V CE Transformer) | E47: 220-16.5V TRF | F47: 2808
B48: DSC | C48: Door Sensor (Mag) - Wired | E48: SEC-MSC | F48: 450
B49: DSC | C49: Door Sensor (Mag) - Wired | E49: SEC-MSC | F49: 450
B50: DSC | C50: Door Sensor (Mag) - Wired | E50: SEC-MSC | F50: 450
B51: DSC | C51: Door Sensor (Mag) - Wired | E51: SEC-MSC | F51: 450
B52: DSC | C52: Door Sensor (Mag) - Wired | E52: SEC-MSC | F52: 450
B53: DSC | C53: DSC - Wired Vibration/Shock Sensor | E53: SS-102 | F53: 3800
B54: DSC | C54: DSC - Wired Vibration/Shock Sensor | E54: SS-102 | F54: 3800
B55: DSC | C55: DSC - Wired Vibration/Shock Sensor | E55: SS-102 | F55: 3800
B56: DSC | C56: DSC - Wired Vibration/Shock Sensor | E56: SS-102 | F56: 3800
B57: DSC | C57: DSC - Wired Vibration/Shock Sensor | E57: SS-102 | F57: 3800
C58: Digital PIR Pet Immune Motion Detector with Wall Mount Bracket | E58: LC200 | F58: 2564
C59: Digital PIR Pet Immune Motion Detector with Wall Mount Bracket | E59: LC200 | F59: 2564
C60: Digital PIR Pet Immune Motion Detector with Wall Mount Bracket | E60: LC200 | F60: 2564
B61: DSC | C61: DSC - IP Module | E61: TL280E | F61: 9000
C62: Siren 15W | E62: SD15W | F62: 1400
C63: Battery Backup | E63: 12V-7amp | F63: 1760

Sheet Christopher
B1: Client Name | C1: Mr.Christopher | E1: 9994588885 | F1: Overall site status | J1: Count | K1: % | M1: Material status | N1: Count | O1: % | Q1: Visti No. | R1: IR No. | S1: Date
B2: Site | C2: Coimbatore | F2: Yet to start | M2: Awaiting order request | Q2: 1 | R2: IR No.1448 | S2: 1.12.2025 | T2: 1st site visit | U2: Asok & Kumaraguru
B3: Location | F3: Position marked - I | M3: To order material | Q3: 2
B4: GPS Coordinates | F4: Piping done - C | M4: Ordered
B5: Architect | F5: Wiring done - C | M5: Recd (To test/config)
B6: Site Supervisor | C6: Mr.Sarathi (Dreamstyle interiors) | E6: 9600099600 | F6: Wiring - Checked Ok - I | M6: Configured - ready for install
B7: Electrician | C7: Mr.Mansoor | E7: 8344572588 | F7: Wiring rework reqd - C | M7: Delivered
B8: Electrical Contractor | F8: Provision not provided - C | M8: Provision only - Matl Not reqd
B9: Billing contact | F9: Position to be changed - C | M9: Failed - Picked up from site
B10: Carpenter | F10: Installed - working | M10: Failed - Need to service
B11: Civil Supervisor | F11: Installed - To activate - I | M11: Sent for service
B12: G-Drive Link | F12: Installed - Not working - IC | M12: Replaced/Serviced
B13: Mail id | F13: Door Ready - C | M13: Returned - Not reqd
B14: Site Engineer | F14: Door Not Ready - I
B15: Brand | C15: Product | D15: Serial No. | E15: Model No | F15: Sale Price | G15: Installation charge | H15: Location | I15: Drawing Ref No. | J15: Site status | K15: <--Date | L15: Prop/Addl | M15: Material | N15: <-- Date | O15: Client | P15: Inka | Q15: Comments | R15: SR Nos (If multiple - add all) | S15: DC
A16: Camera | B16: Prama Hikvision | C16: 4 MP Bullet IP Camera Colour - Prama Hikvision | E16: PT-NC140D3LIU- D1 | F16: 4750 | G16: 10461 | J16: Yet to start | K16: 1.12.2025 | L16: Prop | M16: Awaiting order request | R16: 1448
B17: Prama Hikvision | C17: 4 MP Bullet IP Camera Colour - Prama Hikvision | E17: PT-NC140D3LIU- D1 | F17: 4750 | J17: Yet to start | K17: 1.12.2025 | L17: Prop | M17: Awaiting order request | R17: 1448
B18: Prama Hikvision | C18: 4 MP Bullet IP Camera Colour - Prama Hikvision | E18: PT-NC140D3LIU- D1 | F18: 4750 | J18: Yet to start | K18: 1.12.2025 | L18: Prop | M18: Awaiting order request | R18: 1448
B19: Prama Hikvision | C19: 4 MP Bullet IP Camera Colour - Prama Hikvision | E19: PT-NC140D3LIU- D1 | F19: 4750 | J19: Yet to start | K19: 1.12.2025 | L19: Prop | M19: Awaiting order request | R19: 1448
B20: Prama Hikvision | C20: 4 MP Bullet IP Camera Colour - Prama Hikvision | E20: PT-NC140D3LIU- D1 | F20: 4750 | J20: Yet to start | K20: 1.12.2025 | L20: Prop | M20: Awaiting order request | R20: 1448
B21: Prama Hikvision | C21: 4 MP Bullet IP Camera Colour - Prama Hikvision | E21: PT-NC140D3LIU- D1 | F21: 4750 | J21: Yet to start | K21: 1.12.2025 | L21: Prop | M21: Awaiting order request | R21: 1448
B22: Prama Hikvision | C22: 4 MP Bullet IP Camera Colour - Prama Hikvision | E22: PT-NC140D3LIU- D1 | F22: 4750 | J22: Yet to start | K22: 1.12.2025 | L22: Prop | M22: Awaiting order request | R22: 1448
B23: Prama Hikvision | C23: 4 MP Bullet IP Camera Colour - Prama Hikvision | E23: PT-NC140D3LIU- D1 | F23: 4750 | J23: Yet to start | K23: 1.12.2025 | L23: Prop | M23: Awaiting order request | R23: 1448
B24: Prama Hikvision | C24: 4 MP Bullet IP Camera Colour - Prama Hikvision | E24: PT-NC140D3LIU- D1 | F24: 4750 | J24: Yet to start | K24: 1.12.2025 | L24: Prop | M24: Awaiting order request | R24: 1448
B25: Prama Hikvision | C25: 4 MP Bullet IP Camera Colour - Prama Hikvision | E25: PT-NC140D3LIU- D1 | F25: 4750 | J25: Yet to start | K25: 1.12.2025 | L25: Prop | M25: Awaiting order request | R25: 1448
B26: Prama Hikvision | C26: 4 MP Bullet IP Camera Colour - Prama Hikvision | E26: PT-NC140D3LIU- D1 | F26: 4750 | J26: Yet to start | K26: 1.12.2025 | L26: Prop | M26: Awaiting order request | R26: 1448
B27: Prama Hikvision | C27: 4 MP Bullet IP Camera Colour - Prama Hikvision | E27: PT-NC140D3LIU- D1 | F27: 4750 | J27: Yet to start | K27: 1.12.2025 | L27: Prop | M27: Awaiting order request | R27: 1448
B28: Prama Hikvision | C28: 4 MP Bullet IP Camera Colour - Prama Hikvision | E28: PT-NC140D3LIU- D1 | F28: 4750 | J28: Yet to start | K28: 1.12.2025 | L28: Prop | M28: Awaiting order request | R28: 1448
... B32: TP Link | C32: 8 Port POE Switch (Gigabit) 2 Uplink SFP - TP Link | E32: TL-SG2210P | F32: 8250 | J32: Yet to start | K32: 1.12.2025 | L32: Prop | M32: Awaiting order request | R32: 1448
C33: Camera Accessories | F33: 2500 | J33: Yet to start | K33: 1.12.2025 | L33: Prop | M33: Awaiting order request | R33: 1448
A35: Security Alarm System - DSC TYCO | B35: DSC | C35: DSC Hybrid - Control Panel | E35: HS2032NKCE | F35: 22450 | G35: 9196 | J35: Yet to start | K35: 1.12.2025 | L35: Prop | M35: Awaiting order request | R35: 1448
B36: DSC | C36: DSC - LCD Keypad Kit | E36: HS2LCDS | F36: 5900 | J36: Yet to start | K36: 1.12.2025 | L36: Prop | M36: Awaiting order request | R36: 1448
B37: DSC | C37: DSC - Power Supply (220V CE Transformer) | E37: 220-16.5V TRF | F37: 2808 | J37: Yet to start | K37: 1.12.2025 | L37: Prop | M37: Awaiting order request | R37: 1448
B38: Securico | C38: Door Sensor (Mag) - Wired | E38: SEC-MSC | F38: 450 | J38: Yet to start | K38: 1.12.2025 | L38: Prop | M38: Awaiting order request | R38: 1448
B39: Securico | C39: Door Sensor (Mag) - Wired | E39: SEC-MSC | F39: 450 | J39: Yet to start | K39: 1.12.2025 | L39: Prop | M39: Awaiting order request | R39: 1448
B40: Securico | C40: Door Sensor (Mag) - Wired | E40: SEC-MSC | F40: 450 | J40: Yet to start | K40: 1.12.2025 | L40: Prop | M40: Awaiting order request | R40: 1448
B41: Securico | C41: Door Sensor (Mag) - Wired | E41: SEC-MSC | F41: 450 | J41: Yet to start | K41: 1.12.2025 | L41: Prop | M41: Awaiting order request | R41: 1448
B42: Securico | C42: Door Sensor (Mag) - Wired | E42: SEC-MSC | F42: 450 | J42: Yet to start | K42: 1.12.2025 | L42: Prop | M42: Awaiting order request | R42: 1448
B43: Securico | C43: Door Sensor (Mag) - Wired | E43: SEC-MSC | F43: 450 | J43: Yet to start | K43: 1.12.2025 | L43: Prop | M43: Awaiting order request | R43: 1448
B44: Securico | C44: Door Sensor (Mag) - Wired | E44: SEC-MSC | F44: 450 | J44: Yet to start | K44: 1.12.2025 | L44: Prop | M44: Awaiting order request | R44: 1448
B45: Securico | C45: Door Sensor (Mag) - Wired | E45: SEC-MSC | F45: 450 | J45: Yet to start | K45: 1.12.2025 | L45: Prop | M45: Awaiting order request | R45: 1448
B46: Securico | C46: Door Sensor (Mag) - Wired | E46: SEC-MSC | F46: 450 | J46: Yet to start | K46: 1.12.2025 | L46: Prop | M46: Awaiting order request | R46: 1448
B47: Securico | C47: Door Sensor (Mag) - Wired | E47: SEC-MSC | F47: 450 | J47: Yet to start | K47: 1.12.2025 | L47: Prop | M47: Awaiting order request | R47: 1448
... B62: DSC | C62: DSC - Wired Vibration/Shock Sensor | E62: SS-102 | F62: 4100 | J62: Yet to start | K62: 1.12.2025 | L62: Prop | M62: Awaiting order request | R62: 1448
C63: Siren 15W | E63: SD15W | F63: 1400 | J63: Yet to start | K63: 1.12.2025 | L63: Prop | M63: Awaiting order request | R63: 1448
C64: Battery Backup | E64: 12V-7amp | F64: 1760 | J64: Yet to start | K64: 1.12.2025 | L64: Prop | M64: Awaiting order request | R64: 1448
A66: Automation | B66: KNX | C66: KNX Power Supply 640mA | E66: 24V | F66: 28900 | G66: 74393 | J66: Yet to start | K66: 1.12.2025 | L66: Prop | M66: Awaiting order request | R66: 1448
B67: Schneider | C67: Schneider IP Interface | E67: MTN6502-0105 | F67: 57123 | J67: Yet to start | K67: 1.12.2025 | L67: Prop | M67: Awaiting order request | R67: 1448
B68: Lumi | C68: Lumi 12 Channel KNX Actuator with manual On-Off | E68: 20A * 12 | F68: 39500 | J68: Yet to start | K68: 1.12.2025 | L68: Prop | M68: Awaiting order request | R68: 1448
B69: Lumi | C69: Lumi 12 Channel KNX Actuator with manual On-Off | E69: 20A * 12 | F69: 39500 | J69: Yet to start | K69: 1.12.2025 | L69: Prop | M69: Awaiting order request | R69: 1448
B70: Lumi | C70: Lumi 12 Channel KNX Actuator with manual On-Off | E70: 20A * 12 | F70: 39500 | J70: Yet to start | K70: 1.12.2025 | L70: Prop | M70: Awaiting order request | R70: 1448
B71: Lumi | C71: Lumi 12 Channel KNX Actuator with manual On-Off | E71: 20A * 12 | F71: 39500 | J71: Yet to start | K71: 1.12.2025 | L71: Prop | M71: Awaiting order request | R71: 1448
B72: Lumi | C72: Lumi 12 Channel KNX Actuator with manual On-Off | E72: 20A * 12 | F72: 39500 | J72: Yet to start | K72: 1.12.2025 | L72: Prop | M72: Awaiting order request | R72: 1448
B73: Lumi | C73: Lumi 12 Channel KNX Actuator with manual On-Off | E73: 20A * 12 | F73: 39500 | J73: Yet to start | K73: 1.12.2025 | L73: Prop | M73: Awaiting order request | R73: 1448
B74: Lumi | C74: Lumi 12 Channel KNX Actuator with manual On-Off | E74: 20A * 12 | F74: 39500 | J74: Yet to start | K74: 1.12.2025 | L74: Prop | M74: Awaiting order request | R74: 1448
B75: Lumi | C75: Lumi 12 Channel KNX Actuator with manual On-Off | E75: 20A * 12 | F75: 39500 | J75: Yet to start | K75: 1.12.2025 | L75: Prop | M75: Awaiting order request | R75: 1448
B76: Lumi | C76: Lumi 12 Channel KNX Actuator with manual On-Off | E76: 20A * 12 | F76: 39500 | J76: Yet to start | K76: 1.12.2025 | L76: Prop | M76: Awaiting order request | R76: 1448
B77: Lumi | C77: Lumi 6 Button KNX Tactile Keypads | E77: LUMIKNX6T | F77: 14250 | J77: Yet to start | K77: 1.12.2025 | L77: Prop | M77: Awaiting order request | R77: 1448
B78: Lumi | C78: Lumi 6 Button KNX Tactile Keypads | E78: LUMIKNX6T | F78: 14250 | J78: Yet to start | K78: 1.12.2025 | L78: Prop | M78: Awaiting order request | R78: 1448
... B95: Sensinova | C95: Basic Motion HF Microwave Sensor - Ceiling mount | E95: SN-MW700C | F95: 1978 | J95: Yet to start | K95: 1.12.2025 | L95: Prop | M95: Awaiting order request | R95: 1448
B96: Lumi | C96: Lumi Home Pro Gateway | F96: 79700 | J96: Yet to start | K96: 1.12.2025 | L96: Prop | M96: Awaiting order request | R96: 1448
A98: Wifi | B98: TP Link | C98: Access Point EAP245 - TP Link | E98: EAP245 | F98: 8400 | G98: 7560 | J98: Yet to start | K98: 1.12.2025 | L98: Prop | M98: Awaiting order request | R98: 1448
B99: TP Link | C99: Access Point EAP245 - TP Link | E99: EAP245 | F99: 8400 | J99: Yet to start | K99: 1.12.2025 | L99: Prop | M99: Awaiting order request | R99: 1448
B100: TP Link | C100: Access Point EAP245 - TP Link | E100: EAP245 | F100: 8400 | J100: Yet to start | K100: 1.12.2025 | L100: Prop | M100: Awaiting order request | R100: 1448
B101: TP Link | C101: Access Point EAP245 - TP Link | E101: EAP245 | F101: 8400 | J101: Yet to start | K101: 1.12.2025 | L101: Prop | M101: Awaiting order request | R101: 1448
B102: TP Link | C102: Access Point EAP245 - TP Link | E102: EAP245 | F102: 8400 | J102: Yet to start | K102: 1.12.2025 | L102: Prop | M102: Awaiting order request | R102: 1448
B103: TP Link | C103: Access Point EAP245 - TP Link | E103: EAP245 | F103: 8400 | J103: Yet to start | K103: 1.12.2025 | L103: Prop | M103: Awaiting order request | R103: 1448
B104: TP Link | C104: Access Point EAP245 - TP Link | E104: EAP245 | F104: 8400 | J104: Yet to start | K104: 1.12.2025 | L104: Prop | M104: Awaiting order request | R104: 1448
B105: TP Link | C105: Access Point EAP245 - TP Link | E105: EAP245 | F105: 8400 | J105: Yet to start | K105: 1.12.2025 | L105: Prop | M105: Awaiting order request | R105: 1448
B106: TP Link | C106: Access Point EAP245 - TP Link | E106: EAP245 | F106: 8400 | J106: Yet to start | K106: 1.12.2025 | L106: Prop | M106: Awaiting order request | R106: 1448
A108: Video Door Phone System - Hikvision | B108: Hikvision | C108: VDP Outdoor Camera - Hikvision | E108: DS-KD8003-IME1/Surface | F108: 11600 | G108: 4304 | J108: Yet to start | K108: 1.12.2025 | L108: Prop | M108: Awaiting order request | R108: 1448
B109: Hikvision | C109: VDP Indoor Monitor - Hikvision | E109: DS-KH6320-WTE1 | F109: 10480 | J109: Yet to start | K109: 1.12.2025 | L109: Prop | M109: Awaiting order request | R109: 1448
B110: Hikvision | C110: VDP Indoor Monitor - Hikvision | E110: DS-KH6320-WTE1 | F110: 10480 | J110: Yet to start | K110: 1.12.2025 | L110: Prop | M110: Awaiting order request | R110: 1448
B111: Hikvision | C111: VDP Indoor Monitor - Hikvision | E111: DS-KH6320-WTE1 | F111: 10480 | J111: Yet to start | K111: 1.12.2025 | L111: Prop | M111: Awaiting order request | R111: 1448
A113: Networking | B113: Matrix | C113: IPBX with 4 CO and 2 Single Line & 50 IP | E113: NENXIP50 | F113: 21800 | G113: 4880 | J113: Yet to start | K113: 1.12.2025 | L113: Prop | M113: Awaiting order request | R113: 1448
B114: Matrix | C114: IP Phone (SIP One Touch) - R51P | E114: OTP-AP-R51P | F114: 3150 | J114: Yet to start | K114: 1.12.2025 | L114: Prop | M114: Awaiting order request | R114: 1448
B115: Matrix | C115: IP Phone (SIP One Touch) - R51P | E115: OTP-AP-R51P | F115: 3150 | J115: Yet to start | K115: 1.12.2025 | L115: Prop | M115: Awaiting order request | R115: 1448
B116: Matrix | C116: IP Phone (SIP One Touch) - R51P | E116: OTP-AP-R51P | F116: 3150 | J116: Yet to start | K116: 1.12.2025 | L116: Prop | M116: Awaiting order request | R116: 1448
B117: Matrix | C117: IP Phone (SIP One Touch) - R51P | E117: OTP-AP-R51P | F117: 3150 | J117: Yet to start | K117: 1.12.2025 | L117: Prop | M117: Awaiting order request | R117: 1448
B118: Matrix | C118: IP Phone (SIP One Touch) - R51P | E118: OTP-AP-R51P | F118: 3150 | J118: Yet to start | K118: 1.12.2025 | L118: Prop | M118: Awaiting order request | R118: 1448
B119: Matrix | C119: IP Phone (SIP One Touch) - R51P | E119: OTP-AP-R51P | F119: 3150 | J119: Yet to start | K119: 1.12.2025 | L119: Prop | M119: Awaiting order request | R119: 1448
B120: TP Link | C120: 8 Port POE Switch (Gigabit) 2 Uplink SFP - TP Link | E120: TL-SG2210P | F120: 8100 | J120: Yet to start | K120: 1.12.2025 | L120: Prop | M120: Awaiting order request | R120: 1448

Sheet Prabhakaran
B1: Client Name | C1: Mr.Prabhakaran | E1: 9894605424 | F1: Overall site status | J1: Count | K1: % | M1: Material status | N1: Count | O1: % | Q1: Visti No. | R1: IR No. | S1: Date
B2: Site | C2: Ottanchaittram | F2: Yet to start | M2: Awaiting order request | Q2: 1 | R2: IR No.174 | S2: 8.11.2025 | T2: 1st site visit | U2: Azhagar
B3: Location | F3: Position marked - I | M3: To order material | Q3: 2
B4: GPS Coordinates | F4: Piping done - C | M4: Ordered
B5: Architect | F5: Wiring done - C | M5: Recd (To test/config)
B6: Site Supervisor | F6: Wiring - Checked Ok - I | M6: Configured - ready for install
B7: Electrician | C7: Mr.Jodheeswaran | E7: 8661867089 | F7: Wiring rework reqd - C | M7: Delivered
B8: Electrical Contractor | F8: Provision not provided - C | M8: Provision only - Matl Not reqd
B9: Billing contact | F9: Position to be changed - C | M9: Failed - Picked up from site
B10: Carpenter | F10: Installed - working | M10: Failed - Need to service
B11: Civil Supervisor | F11: Installed - To activate - I | M11: Sent for service
B12: G-Drive Link | F12: Installed - Not working - IC | M12: Replaced/Serviced
B13: Mail id | F13: Door Ready - C | M13: Returned - Not reqd
B14: Site Engineer | F14: Door Not Ready - I
B15: Brand | C15: Product | D15: Serial No. | E15: Model No | F15: Sale Price | G15: Installation charge | H15: Location | I15: Drawing Ref No. | J15: Site status | K15: <--Date | L15: Prop/Addl | M15: Material | N15: <-- Date | O15: Client | P15: Inka | Q15: Comments | R15: SR Nos (If multiple - add all) | S15: DC
A16: Camera | B16: CP Plus | C16: 4 MP Bullet IP Camera - CP Plus | E16: CP-UNC-TA41L3C- | F16: 4860 | G16: 13436 | J16: Position marked - I | L16: Prop | M16: Awaiting order request
B17: CP Plus | C17: 4 MP Bullet IP Camera - CP Plus | E17: CP-UNC-TA41L3C- | F17: 4860 | J17: Position marked - I | L17: Prop | M17: Awaiting order request
B18: CP Plus | C18: 4 MP Bullet IP Camera - CP Plus | E18: CP-UNC-TA41L3C- | F18: 4860 | J18: Position marked - I | L18: Prop | M18: Awaiting order request
B19: CP Plus | C19: 4 MP Bullet IP Camera - CP Plus | E19: CP-UNC-TA41L3C- | F19: 4860 | J19: Position marked - I | L19: Prop | M19: Awaiting order request
B20: CP Plus | C20: 4 MP Bullet IP Camera - CP Plus | E20: CP-UNC-TA41L3C- | F20: 4860 | J20: Position marked - I | L20: Prop | M20: Awaiting order request
B21: CP Plus | C21: 4 MP Bullet IP Camera - CP Plus | E21: CP-UNC-TA41L3C- | F21: 4860 | J21: Position marked - I | L21: Prop | M21: Awaiting order request
B22: CP Plus | C22: 4 MP Bullet IP Camera - CP Plus | E22: CP-UNC-TA41L3C- | F22: 4860 | J22: Position marked - I | L22: Prop | M22: Awaiting order request
B23: CP Plus | C23: 4 MP Bullet IP Camera - CP Plus | E23: CP-UNC-TA41L3C- | F23: 4860 | J23: Position marked - I | L23: Prop | M23: Awaiting order request
B24: CP Plus | C24: 4 MP Bullet IP Camera - CP Plus | E24: CP-UNC-TA41L3C- | F24: 4860 | J24: Position marked - I | L24: Prop | M24: Awaiting order request
B25: CP Plus | C25: 4 MP Dome IP Camera - CP Plus | E25: CP-UNC-DA41PL3C | F25: 4050 | J25: Position marked - I | L25: Prop | M25: Awaiting order request
B26: CP Plus | C26: 16 Channel NVR - CP Plus | E26: CP-UNR4K- 4162-V2 | F26: 15500 | J26: Position marked - I | L26: Prop | M26: Awaiting order request
B27: TP Link | C27: 16 Port POE Gigabit Switch (TL-SG1218MPE) - TP Link | E27: TL-SG1218MPE | F27: 15625 | J27: Position marked - I | L27: Prop | M27: Awaiting order request
B28: Toshiba | C28: 4 TB Hard Disk - Toshiba | E28: AVHDDS300 | F28: 8160 | J28: Position marked - I | L28: Prop | M28: Awaiting order request
C29: Camera Accessories | F29: 2500
A31: Security Alarm System - DSC TYCO | B31: DSC TYCO | C31: DSC Hybrid - Control Panel | E31: HS2032NKCE | F31: 22450 | G31: 17905 | J31: Position marked - I | L31: Prop | M31: Awaiting order request
B32: DSC TYCO | C32: DSC - LCD Keypad Kit | E32: HS2LCDS | F32: 5900 | J32: Position marked - I | L32: Prop | M32: Awaiting order request
B33: DSC TYCO | C33: DSC - Power Supply (220V CE Transformer) | E33: 220-16.5V TRF | F33: 2808 | J33: Position marked - I | L33: Prop | M33: Awaiting order request
B34: Securico | C34: Door Sensor (Mag) - Wired | E34: SEC-MSC | F34: 450 | J34: Position marked - I | L34: Prop | M34: Awaiting order request
B35: Securico | C35: Door Sensor (Mag) - Wired | E35: SEC-MSC | F35: 450 | J35: Position marked - I | L35: Prop | M35: Awaiting order request
B36: Securico | C36: Door Sensor (Mag) - Wired | E36: SEC-MSC | F36: 450 | J36: Position marked - I | L36: Prop | M36: Awaiting order request
B37: DSC TYCO | C37: DSC - Wired Vibration/Shock Sensor | E37: SS-102 | F37: 4100 | J37: Position marked - I | L37: Prop | M37: Awaiting order request
B38: DSC TYCO | C38: DSC - Wired Vibration/Shock Sensor | E38: SS-102 | F38: 4100 | J38: Position marked - I | L38: Prop | M38: Awaiting order request
B39: DSC TYCO | C39: DSC - Wired Vibration/Shock Sensor | E39: SS-102 | F39: 4100 | J39: Position marked - I | L39: Prop | M39: Awaiting order request
B40: DSC TYCO | C40: DSC - Wired Vibration/Shock Sensor | E40: SS-102 | F40: 4100 | J40: Position marked - I | L40: Prop | M40: Awaiting order request
B41: DSC TYCO | C41: DSC - Wired Vibration/Shock Sensor | E41: SS-102 | F41: 4100 | J41: Position marked - I | L41: Prop | M41: Awaiting order request
B42: DSC TYCO | C42: DSC - Wired Vibration/Shock Sensor | E42: SS-102 | F42: 4100 | J42: Position marked - I | L42: Prop | M42: Awaiting order request
B43: DSC TYCO | C43: DSC - Wired Vibration/Shock Sensor | E43: SS-102 | F43: 4100 | J43: Position marked - I | L43: Prop | M43: Awaiting order request
... B55: DSC TYCO | C55: DSC - IP Module | E55: TL280E | F55: 9900 | J55: Position marked - I | L55: Prop | M55: Awaiting order request
C56: Siren 15W | E56: SD15W | F56: 1400 | J56: Position marked - I | L56: Prop | M56: Awaiting order request
C57: Battery Backup | E57: 12V-7amp | F57: 1760 | J57: Position marked - I | L57: Prop | M57: Awaiting order request
A59: Automation | B59: Eglu | C59: In-Wall Switch 3S - Eg | E59: EGIW04R | F59: 9200 | G59: 14760 | J59: Position marked - I | L59: Prop | M59: Awaiting order request
B60: Eglu | C60: In-Wall Switch 3S - Eg | E60: EGIW04R | F60: 9200 | J60: Position marked - I | L60: Prop | M60: Awaiting order request
B61: Eglu | C61: In-Wall Switch 3S - Eg | E61: EGIW04R | F61: 9200 | J61: Position marked - I | L61: Prop | M61: Awaiting order request
B62: Eglu | C62: In-Wall Switch 3S - Eg | E62: EGIW04R | F62: 9200 | J62: Position marked - I | L62: Prop | M62: Awaiting order request
B63: Eglu | C63: In-Wall Switch 3S - Eg | E63: EGIW04R | F63: 9200 | J63: Position marked - I | L63: Prop | M63: Awaiting order request
B64: Eglu | C64: In-Wall Switch 3S - Eg | E64: EGIW04R | F64: 9200 | J64: Position marked - I | L64: Prop | M64: Awaiting order request
B65: Eglu | C65: In-Wall Switch 3S - Eg | E65: EGIW04R | F65: 9200 | J65: Position marked - I | L65: Prop | M65: Awaiting order request
B66: Eglu | C66: Automation Hub | E66: HUB PLUS | F66: 34000 | J66: Position marked - I | L66: Prop | M66: Awaiting order request
A68: VDP | B68: Hikvision | C68: VDP Outdoor Camera - Hikvision | E68: DS-KD8003-IME1/Surface | F68: 11600 | G68: 4884 | J68: Position marked - I | L68: Prop | M68: Awaiting order request
B69: Hikvision | C69: VDP Indoor Monitor - Hikvision | E69: DS-KH6320-WTE1 | F69: 10480 | J69: Position marked - I | L69: Prop | M69: Awaiting order request
B70: Hikvision | C70: VDP Indoor Monitor - Hikvision | E70: DS-KH6320-WTE1 | F70: 10480 | J70: Position marked - I | L70: Prop | M70: Awaiting order request
A72: WIFI Access Point - TP Link | B72: TP Link | C72: Access Point EAP245 - TP Link | E72: EAP245 | F72: 8850 | G72: 7653 | J72: Position marked - I | L72: Prop | M72: Awaiting order request
B73: TP Link | C73: Access Point EAP245 - TP Link | E73: EAP245 | F73: 8850 | J73: Position marked - I | L73: Prop | M73: Awaiting order request
B74: TP Link | C74: Access Point EAP245 - TP Link | E74: EAP245 | F74: 8850 | J74: Position marked - I | L74: Prop | M74: Awaiting order request
B75: TP Link | C75: Access Point EAP245 - TP Link | E75: EAP245 | F75: 8850 | J75: Position marked - I | L75: Prop | M75: Awaiting order request
B76: TP Link | C76: 16 Port POE Gigabit Switch (TLSG1218MPE) - TP Link | E76: TLSG1218MPE | F76: 15625 | J76: Position marked - I | L76: Prop | M76: Awaiting order request
A78: Gate Automation | B78: Autozone | C78: Sliding Gate Operator 600 Kg 24V AC KIT | E78: AZSL100A/KIT | F78: 38950 | G78: 7103 | J78: Position marked - I | L78: Prop | M78: Awaiting order request
C79: Gate Rack | E79: AZ 9mm | F79: 1952 | J79: Position marked - I | L79: Prop | M79: Awaiting order request
C80: Gate Rack | E80: AZ 9mm | F80: 1952 | J80: Position marked - I | L80: Prop | M80: Awaiting order request
C81: Gate Rack | E81: AZ 9mm | F81: 1952 | J81: Position marked - I | L81: Prop | M81: Awaiting order request
C82: Gate Rack | E82: AZ 9mm | F82: 1952 | J82: Position marked - I | L82: Prop | M82: Awaiting order request
C85: Cat 6 Cable - Netfox 2 coil x305 m(yellow and blue) 2 boxes | M85: Delivered | N85: 10.11.2025 | S85: 180

Sheet Karunanidhi Construction
B1: Client Name | C1: Karunanidhi Construction | D1: Mrs. Thrisha | E1: 9003105327 | F1: Overall site status | J1: Count | K1: % | M1: Material status | N1: Count | O1: % | Q1: Visti No. | R1: IR No. | S1: Date
B2: Site | C2: SB Colony | F2: Yet to start | M2: Awaiting order request | Q2: 1 | S2: 7.11.2025 | T2: 1st site visit | U2: Kumaraguru
B3: Location | F3: Position marked - I | M3: To order material | Q3: 2 | S3: 10.11.2025 | T3: installation | U3: sakthi & Kumaraguru
B4: GPS Coordinates | F4: Piping done - C | M4: Ordered
B5: Architect | F5: Wiring done - C | M5: Recd (To test/config)
B6: Site Supervisor | C6: Mr. Boobesh viswanathan | E6: 8526903777 | F6: Wiring - Checked Ok - I | M6: Configured - ready for install
B7: Electrician | F7: Wiring rework reqd - C | M7: Delivered
B8: Electrical Contractor | F8: Provision not provided - C | M8: Provision only - Matl Not reqd
B9: Billing contact | F9: Position to be changed - C | M9: Failed - Picked up from site
B10: Carpenter | F10: Installed - working | M10: Failed - Need to service
B11: Civil Supervisor | F11: Installed - To activate - I | M11: Sent for service
B12: G-Drive Link | F12: Installed - Not working - IC | M12: Replaced/Serviced
B13: Mail id | F13: Door Ready - C | M13: Returned - Not reqd
B14: Site Engineer | F14: Door Not Ready - I
B15: Brand | C15: Product | D15: Serial No. | E15: Model No | F15: Sale Price | G15: Installation charge | H15: Location | I15: Drawing Ref No. | J15: Site status | K15: <--Date | L15: Prop/Addl | M15: Material | N15: <-- Date | O15: Client | P15: Inka | Q15: Comments | R15: SR Nos (If multiple - add all) | S15: DC
A16: Camera | B16: CP Plus | C16: 4 MP Bullet IP Camera - CP Plus | E16: CP-UNC-TB41L3-MDS | F16: 4860 | G16: 4074 | J16: Installed - working | K16: 45941 | L16: Prop | M16: Delivered | N16: 5.11.2025 | S16: 177
B17: CP Plus | C17: 4 MP Bullet IP Camera - CP Plus | E17: CP-UNC-TB41L3-MDS | F17: 4860 | J17: Installed - working | K17: 45941 | L17: Prop | M17: Delivered | N17: 5.11.2025 | S17: 177
B18: CP Plus | C18: 4 MP Bullet IP Camera - CP Plus | E18: CP-UNC-TB41L3-MDS | F18: 4860 | J18: Installed - working | K18: 45941 | L18: Prop | M18: Delivered | N18: 5.11.2025 | S18: 177
B19: CP Plus | C19: 4 MP Bullet IP Camera - CP Plus | E19: CP-UNC-TB41L3-MDS | F19: 4860 | J19: Installed - working | K19: 45941 | L19: Prop | M19: Delivered | N19: 5.11.2025 | S19: 177
B20: TP Link | C20: 8 Port POE Switch (Gigabit) 2 Uplink SFP - TP Link | E20: TL-SG2210P | F20: 7990 | J20: Installed - working | K20: 45941 | L20: Prop | M20: Delivered | N20: 5.11.2025 | S20: 177
B21: CP Plus | C21: 4 Channal NVR - CP Plus / 1 Sata | E21: CP-UNR-104F1 | F21: 4250 | J21: Installed - working | K21: 45941 | L21: Prop | M21: Delivered | N21: 5.11.2025 | S21: 177
B22: Toshiba | C22: 4 TB Hard Disk - Toshiba | E22: AVHDDS300 | F22: 8160 | J22: Installed - working | K22: 45941 | L22: Prop | M22: Delivered | N22: 5.11.2025 | S22: 177
C23: Camera Accessories | F23: 900 | J23: Installed - working | K23: 45941 | L23: Prop | M23: Delivered | N23: 5.11.2025 | S23: 177
B24: CP Plus | C24: 2U RACK-CP PLUS | E24: RK4535VW-2U | J24: Installed - working | K24: 45941 | L24: Addl | M24: Delivered | N24: 5.11.2025 | S24: 177
C25: 3 Module Plate (4x4G Wood Sheet) | E25: 4X4 G | J25: Installed - working | K25: 45941 | L25: Addl | M25: Delivered | N25: 5.11.2025 | S25: 177
C26: 3 Module Plate (4x4G Wood Sheet) | E26: 4X4 G | J26: Installed - working | K26: 45941 | L26: Addl | M26: Delivered | N26: 5.11.2025 | S26: 177
C27: 3 Module Plate (4x4G Wood Sheet) | E27: 4X4 G | J27: Installed - working | K27: 45941 | L27: Addl | M27: Delivered | N27: 5.11.2025 | S27: 177
C28: 3 Module Plate (4x4G Wood Sheet) | E28: 4X4 G | J28: Installed - working | K28: 45941 | L28: Addl | M28: Delivered | N28: 5.11.2025 | S28: 177

Sheet Race Course Apartment
B1: Client Name | C1: Race Course Apartment - Mr. Vengateswaran | F1: Overall site status | J1: Count | K1: % | M1: Material status | N1: Count | O1: % | Q1: Visti No. | R1: IR No. | S1: Date
B2: Site | C2: Race Course | F2: Yet to start | M2: Awaiting order request | Q2: 1 | S2: 14.10.2025 | T2: 1st site visit | U2: Kumaraguru
B3: Location | F3: Position marked - I | M3: To order material | Q3: 2 | S3: 15.10.2025 | T3: installation | U3: sakthi & Kumaraguru
B4: GPS Coordinates | F4: Piping done - C | M4: Ordered
B5: Architect | C5: Ar. Neeraj Sivakumar | E5: 7904076275 | F5: Wiring done - C | M5: Recd (To test/config)
B6: Site Supervisor | F6: Wiring - Checked Ok - I | M6: Configured - ready for install
B7: Electrician | F7: Wiring rework reqd - C | M7: Delivered
B8: Electrical Contractor | F8: Provision not provided - C | M8: Provision only - Matl Not reqd
B9: Billing contact | F9: Position to be changed - C | M9: Failed - Picked up from site
B10: Carpenter | F10: Installed - working | M10: Failed - Need to service
B11: Civil Supervisor | F11: Installed - To activate - I | M11: Sent for service
B12: G-Drive Link | F12: Installed - Not working - IC | M12: Replaced/Serviced
B13: Mail id | F13: Door Ready - C | M13: Returned - Not reqd
B14: Site Engineer | F14: Door Not Ready - I
B15: Brand | C15: Product | D15: Serial No. | E15: Model No | F15: Sale Price | G15: Installation charge | H15: Location | I15: Drawing Ref No. | J15: Site status | K15: <--Date | L15: Prop/Addl | M15: Material | N15: <-- Date | O15: Client | P15: Inka | Q15: Comments | R15: SR Nos (If multiple - add all) | S15: DC
A16: Camera | B16: CP Plus | C16: 4 MP WIFI WIRELESS CAMERA -CP PLUS | D16: 240101320003932 | E16: CP-V41A | F16: 2600 | G16: 3500 | J16: Installed - working | K16: 7.11.2025 | L16: Prop | M16: Delivered | S16: 178
B17: Sandisk | C17: Memory Card 256GB - Sandisk | E17: 256 GB | F17: 2190 | J17: Installed - working | K17: 7.11.2025 | L17: Prop | M17: Delivered | S17: 178
A19: VDP | B19: Hikvision | C19: VDP Indoor Monitor- Hikvision | D19: WIRELESS-Q41041931 | E19: DS-KH6320-WTE1 | F19: 14500 | J19: Installed - working | K19: 7.11.2025 | L19: Prop | M19: Delivered | S19: 178
C20: VDP Outdoor Camera - Hikvision | D20: WIRELESS-GC3153630 | E20: DS-KD6113 | J20: Installed - working | K20: 7.11.2025 | L20: Prop | M20: Delivered | S20: 178
C21: Camera Accessories | F21: 1000
A23: Wifi | B23: TP Link | C23: Access Point EAP245 - TP Link | D23: 224B152004485 | E23: EAP245 | F23: 8250 | G23: 1500 | L23: Addl | M23: Delivered | N23: 11.11.2025 | S23: 182
C24: Cat 6 Cable - Netfox-7mts | F24: 294 | L24: Addl | M24: Delivered | N24: 11.11.2025 | S24: 182

Sheet Mohan Atirum House
B1: Client Name | C1: Mohan Atrium House | D1: Mr. Naveen | F1: Overall site status | J1: Count | K1: % | M1: Material status | N1: Count | O1: % | Q1: Visti No. | R1: IR No. | S1: Date
B2: Site | C2: Sulur | F2: Yet to start | M2: Awaiting order request | Q2: 1 | R2: IR No.206 | S2: 3.7.2025 | T2: 1st site visit | U2: Sakthi
B3: Location | F3: Position marked - I | M3: To order material | Q3: 2 | R3: IR No.231 | S3: 10.7.2025 | T3: Site meeting | U3: Sakthi
B4: GPS Coordinates | F4: Piping done - C | M4: Ordered | Q4: 3 | R4: IR No.236 | S4: 21.7.2025 | T4: Site meeting | U4: Sakthi
B5: Architect | F5: Wiring done - C | M5: Recd (To test/config) | Q5: 4 | R5: IR No.1446 | S5: 25.7.2025 | T5: Piping checking | U5: Sakthi
B6: Site Supervisor | F6: Wiring - Checked Ok - I | M6: Configured - ready for install
B7: Electrician | F7: Wiring rework reqd - C | M7: Delivered
B8: Electrical Contractor | F8: Provision not provided - C | M8: Provision only - Matl Not reqd
B9: Billing contact | F9: Position to be changed - C | M9: Failed - Picked up from site
B10: Carpenter | F10: Installed - working | M10: Failed - Need to service
B11: Civil Supervisor | F11: Installed - To activate - I | M11: Sent for service
B12: G-Drive Link | F12: Installed - Not working - IC | M12: Replaced/Serviced
B13: Mail id | F13: Door Ready - C | M13: Returned - Not reqd
B14: Site Engineer | F14: Door Not Ready - I
B15: Brand | C15: Product | D15: Serial No. | E15: Model No | F15: Sale Price | G15: Installation charge | H15: Location | I15: Drawing Ref No. | J15: Site status | K15: <--Date | L15: Prop/Addl | M15: Material | N15: <-- Date | O15: Client | P15: Inka | Q15: Comments | R15: SR Nos (If multiple - add all) | S15: DC
A16: Camera | B16: Prama | C16: 4 Mp Bullet IP Camera Colour/InbuiltMic - Prama | E16: PT-NC140D3LIU(D2) | F16: 4840 | G16: 12037 | L16: Prop
B17: Prama | C17: 4 Mp Bullet IP Camera Colour/InbuiltMic - Prama | E17: PT-NC140D3LIU(D2) | F17: 4840 | L17: Prop
B18: Prama | C18: 4 Mp Bullet IP Camera Colour/InbuiltMic - Prama | E18: PT-NC140D3LIU(D2) | F18: 4840 | L18: Prop
B19: Prama | C19: 4 Mp Bullet IP Camera Colour/InbuiltMic - Prama | E19: PT-NC140D3LIU(D2) | F19: 4840 | L19: Prop
B20: Prama | C20: 4 Mp Bullet IP Camera Colour/InbuiltMic - Prama | E20: PT-NC140D3LIU(D2) | F20: 4840 | L20: Prop
B21: Prama | C21: 4 Mp Bullet IP Camera Colour/InbuiltMic - Prama | E21: PT-NC140D3LIU(D2) | F21: 4840 | L21: Prop
B22: Prama | C22: 4 Mp Bullet IP Camera Colour/InbuiltMic - Prama | E22: PT-NC140D3LIU(D2) | F22: 4840 | L22: Prop
B23: Prama | C23: 4 Mp Bullet IP Camera Colour/InbuiltMic - Prama | E23: PT-NC140D3LIU(D2) | F23: 4840 | L23: Prop
B24: Prama | C24: 4 Mp Bullet IP Camera Colour/InbuiltMic - Prama | E24: PT-NC140D3LIU(D2) | F24: 4840 | L24: Prop
B25: Prama | C25: 4 Mp Bullet IP Camera Colour/InbuiltMic - Prama | E25: PT-NC140D3LIU(D2) | F25: 4840 | L25: Prop
B26: Prama | C26: 4 Mp Bullet IP Camera Colour/InbuiltMic - Prama | E26: PT-NC140D3LIU(D2) | F26: 4840 | L26: Prop
B27: Prama | C27: 4 Mp Bullet IP Camera Colour/InbuiltMic - Prama | E27: PT-NC140D3LIU(D2) | F27: 4840 | L27: Prop
B28: Prama Hikvision | C28: 16 Channel NVR (K2) - Prama Hikvision | E28: PT-NRAS2A16-K2 | F28: 14500 | L28: Prop
... B31: Netfox | C31: Cat 6 Jack - Netfox-35 nos. | E31: RJ-45 | F31: 25 | L31: Prop
C32: Camera Accessories | F32: 2050 | L32: Prop
L33: Prop
A34: Security Alarm System - DSC TYCO | B34: DSC | C34: DSC Hybrid - Control Panel | E34: HS2032NKCE | F34: 24450 | G34: 22989
B35: DSC | C35: DSC - LCD Keypad Kit | E35: HS2LCDS | F35: 6300 | L35: Prop
B36: DSC | C36: DSC - Power Supply (220V CE Transformer) | E36: 220-16.5V TRF | F36: 2808 | L36: Prop
B37: Securico | C37: Door Sensor (Mag) - Wired | E37: SEC-MSC | F37: 450 | L37: Prop
B38: Securico | C38: Door Sensor (Mag) - Wired | E38: SEC-MSC | F38: 450 | L38: Prop
B39: Securico | C39: Door Sensor (Mag) - Wired | E39: SEC-MSC | F39: 450 | L39: Prop
B40: Securico | C40: Door Sensor (Mag) - Wired | E40: SEC-MSC | F40: 450 | L40: Prop
B41: Securico | C41: Door Sensor (Mag) - Wired | E41: SEC-MSC | F41: 450 | L41: Prop
B42: Securico | C42: Door Sensor (Mag) - Wired | E42: SEC-MSC | F42: 450 | L42: Prop
B43: Securico | C43: Door Sensor (Mag) - Wired | E43: SEC-MSC | F43: 450 | L43: Prop
B44: Securico | C44: Door Sensor (Mag) - Wired | E44: SEC-MSC | F44: 450 | L44: Prop
B45: Securico | C45: Door Sensor (Mag) - Wired | E45: SEC-MSC | F45: 450 | L45: Prop
B46: Securico | C46: Door Sensor (Mag) - Wired | E46: SEC-MSC | F46: 450 | L46: Prop
... B90: DSC | C90: DSC - IP Module | E90: TL280E | F90: 9780 | L90: Prop
C91: Siren 15W | E91: SD15W | F91: 1400 | L91: Prop
C92: Battery Backup | E92: 12V-7amp | F92: 1760 | L92: Prop
C93: Accessories | F93: 1050 | L93: Prop
A95: Vedio Door Phone - Hikvision | B95: Hikvision | C95: VDP Outdoor Camera - Hikvision | E95: DS-KD8003-IME1/Surface | F95: 10600 | G95: 2308 | L95: Prop
B96: Hikvision | C96: VDP Indoor Monitor - Hikvision | E96: DS-KH6320-WTE1 | F96: 9480 | L96: Prop
L97: Prop
A98: Wifi Access Point - TP Link | B98: TP Link | C98: Access Point EAP245 - TP Link | E98: EAP245 | F98: 8250 | L98: Prop
B99: TP Link | C99: Access Point EAP245 - TP Link | E99: EAP245 | F99: 8250 | L99: Prop
B100: TP Link | C100: Access Point EAP245 - TP Link | E100: EAP245 | F100: 8250 | L100: Prop
B101: TP Link | C101: Access Point EAP245 - TP Link | E101: EAP245 | F101: 8250 | L101: Prop
B102: TP Link | C102: Access Point EAP245 - TP Link | E102: EAP245 | F102: 8250 | L102: Prop
B103: TP Link | C103: Access Point EAP245 - TP Link | E103: EAP245 | F103: 8250 | L103: Prop
B104: TP Link | C104: Access Point EAP245 - TP Link | E104: EAP245 | F104: 8250 | L104: Prop
B105: TP Link | C105: 8 Port Switch (Gigabit) - TP Link | E105: TL-SG2008D | F105: 8450 | L105: Prop
A107: Automation | B107: Neon | C107: Neon 8 Switch 1 Fan Touch Panel | E107: NS-SIB080Y100 | F107: 24500 | G107: 14700 | L107: Prop
B108: Neon | C108: Neon 8 Switch 1 Fan Touch Panel | E108: NS-SIB080Y100 | F108: 24500 | L108: Prop
B109: Neon | C109: Neon 8 Switch 1 Fan Touch Panel | E109: NS-SIB080Y100 | F109: 24500 | L109: Prop
B110: Neon | C110: Neon 8 Switch 1 Fan Touch Panel | E110: NS-SIB080Y100 | F110: 24500 | L110: Prop
B111: Neon | C111: Neon 8 Switch 1 Fan Touch Panel | E111: NS-SIB080Y100 | F111: 24500 | L111: Prop
B112: Neon | C112: Neon 8 Switch 1 Fan Touch Panel | E112: NS-SIB080Y100 | F112: 24500 | L112: Prop

Sheet NavBalu Associates
B1: Client Name | C1: NavBalu Associates | D1: Mr. Naveen | E1: 8015161702 | F1: Overall site status | J1: Count | K1: % | M1: Material status | N1: Count | O1: % | Q1: Visti No. | R1: IR No. | S1: Date
B2: Site | C2: 100 ft road | F2: Yet to start | M2: Awaiting order request | Q2: 1 | S2: 14.10.2025 | T2: 1st site visit | U2: Kumaraguru
B3: Location | C3: https://maps.app.goo.gl/fsNtNaE3TBK9fQcZ6?g_st=awb | F3: Position marked - I | M3: To order material | Q3: 2 | S3: 15.10.2025 | T3: installation | U3: sakthi & Kumaraguru
B4: GPS Coordinates | F4: Piping done - C | M4: Ordered
B5: Architect | F5: Wiring done - C | M5: Recd (To test/config)
B6: Site Supervisor | F6: Wiring - Checked Ok - I | M6: Configured - ready for install
B7: Electrician | F7: Wiring rework reqd - C | M7: Delivered
B8: Electrical Contractor | F8: Provision not provided - C | M8: Provision only - Matl Not reqd
B9: Billing contact | F9: Position to be changed - C | M9: Failed - Picked up from site
B10: Carpenter | F10: Installed - working | M10: Failed - Need to service
B11: Civil Supervisor | F11: Installed - To activate - I | M11: Sent for service
B12: G-Drive Link | F12: Installed - Not working - IC | M12: Replaced/Serviced
B13: Mail id | F13: Door Ready - C | M13: Returned - Not reqd
B14: Site Engineer | F14: Door Not Ready - I
B15: Brand | C15: Product | D15: Serial No. | E15: Model No | F15: Sale Price | G15: Installation charge | H15: Location | I15: Drawing Ref No. | J15: Site status | K15: <--Date | L15: Prop/Addl | M15: Material | N15: <-- Date | O15: Client | P15: Inka | Q15: Comments | R15: SR Nos (If multiple - add all) | S15: DC
A16: Security system | B16: Hikvision | C16: Hikvision - Control Panel AX Pro | E16: DS-PWA64 - AX Pro | F16: 27450 | G16: 7090 | H16: MD Room | J16: Completed | K16: 15.10.2025 | L16: Prop | M16: Delivered | N16: 15.10.2025 | S16: 169
B17: Hikvision | C17: Hikvision - Wireless Dual Sensor (Door/Vibration) | D17: Q36721906 | E17: PDMCK-EG2-WB | F17: 4750 | H17: MD room inside | J17: Completed | K17: 15.10.2025 | L17: Prop | M17: Delivered | N17: 15.10.2025 | S17: 169
B18: Hikvision | C18: Hikvision - Wireless Dual Sensor (Door/Vibration) | D18: Q36721882 | E18: PDMCK-EG2-WB | F18: 4750 | H18: MD room outside | J18: Completed | K18: 15.10.2025 | L18: Prop | M18: Delivered | N18: 15.10.2025 | S18: 169
B19: Hikvision | C19: Hikvision - Wireless Dual Sensor (Door/Vibration) | D19: Q41058404 | E19: PDMCK-EG2-WB | F19: 4750 | H19: Work space window 1 | J19: Completed | K19: 15.10.2025 | L19: Prop | M19: Delivered | N19: 15.10.2025 | S19: 169
B20: Hikvision | C20: Wireless Magnetic Door Sensor - Hikvision | D20: Q39151332 | E20: DS-PD1-MC-WWS | F20: 2950 | H20: Front entrance door | J20: Completed | K20: 15.10.2025 | L20: Prop | M20: Delivered | N20: 15.10.2025 | S20: 169
B21: Hikvision | C21: Wireless Magnetic Door Sensor - Hikvision | D21: Q39151335 | E21: DS-PD1-MC-WWS | F21: 2950 | H21: Back Exit door | J21: Completed | K21: 15.10.2025 | L21: Prop | M21: Delivered | N21: 15.10.2025 | S21: 169
B22: Hikvision | C22: Wireless Magnetic Door Sensor - Hikvision | D22: Q39151361 | E22: DS-PD1-MC-WWS | F22: 2950 | H22: Work space window 2 | J22: Completed | K22: 15.10.2025 | L22: Prop | M22: Delivered | N22: 15.10.2025 | S22: 169
B23: Hikvision | C23: Wireless Magnetic Door Sensor - Hikvision | D23: Q39151362 | E23: DS-PD1-MC-WWS | F23: 2950 | H23: Work space window 3 | J23: Completed | K23: 15.10.2025 | L23: Prop | M23: Delivered | N23: 15.10.2025 | S23: 169
B24: Hikvision | C24: Wireless Magnetic Door Sensor - Hikvision | D24: Q39151387 | E24: DS-PD1-MC-WWS | F24: 2950 | H24: Work space window entry | J24: Completed | K24: 15.10.2025 | L24: Prop | M24: Delivered | N24: 15.10.2025 | S24: 169
B25: Hikvision | C25: Wireless Magnetic Door Sensor - Hikvision | D25: Q39151364 | E25: DS-PD1-MC-WWS | F25: 2950 | H25: Work space window exit | J25: Completed | K25: 15.10.2025 | L25: Prop | M25: Delivered | N25: 15.10.2025 | S25: 169
B26: Hikvision | C26: Key fob (Wireless ) | D26: Q31168017 | E26: WS4939 | F26: 2200 | J26: Completed | K26: 15.10.2025 | L26: Prop | M26: Delivered | N26: 15.10.2025 | S26: 169
B27: Hikvision | C27: Key fob (Wireless ) | D27: Q31167996 | E27: WS4939 | F27: 2200 | J27: Completed | K27: 15.10.2025 | L27: Prop | M27: Delivered | N27: 15.10.2025 | S27: 169
B28: Hikvision | C28: Wireless Siren - Hikvision | D28: Q40780281 | E28: Wireless Siren | F28: 7100 | H28: Car parking | J28: Completed | K28: 15.10.2025 | L28: Prop | M28: Delivered | N28: 15.10.2025 | S28: 169

Sheet Arrow Hospital
B1: Client Name | C1: Arrow Hospital | D1: Mr.Haseeb | E1: 9443020343 | F1: Overall site status | J1: Count | K1: % | M1: Material status | N1: Count | O1: % | Q1: Visti No. | R1: IR No. | S1: Date
B2: Site | C2: Vadavalli | E2: 9688748946 | F2: Yet to start | M2: Awaiting order request
B3: Location | E3: 9840706220 | F3: Position marked - I | M3: To order material
B4: GPS Coordinates | F4: Piping done - C | M4: Ordered
B5: Architect | F5: Wiring done - C | M5: Recd (To test/config)
B6: Site Supervisor | F6: Wiring - Checked Ok - I | M6: Configured - ready for install
B7: Electrician | F7: Wiring rework reqd - C | M7: Delivered
B8: Electrical Contractor | F8: Provision not provided - C | M8: Provision only - Matl Not reqd
B9: Billing contact | F9: Position to be changed - C | M9: Failed - Picked up from site
B10: Carpenter | F10: Installed - working | M10: Failed - Need to service
B11: Civil Supervisor | F11: Installed - To activate - I | M11: Sent for service
B12: G-Drive Link | F12: Installed - Not working - IC | M12: Replaced/Serviced
B13: Mail id | F13: Door Ready - C | M13: Returned - Not reqd
B14: Site Engineer | F14: Door Not Ready - I
B16: Brand | C16: Product | D16: Serial No. | E16: Model No | F16: Sale Price | G16: Installation charge | H16: Location | I16: Drawing Ref No. | J16: Site status | K16: <--Date | L16: Prop/Addl | M16: Material | N16: <-- Date | O16: Client | P16: Inka | Q16: Comments | R16: SR Nos (If multiple - add all) | S16: DC
A17: Camera | B17: Prama Hivision | C17: 4 MP Bullet IP Camera | E17: PT-NC140D3-IUF(D) | F17: 4250 | G17: 42500 | J17: Yet to start | L17: Prop | M17: Awaiting order request | Q17: 1st site visit done
B18: Prama Hivision | C18: 4 MP Bullet IP Camera | E18: PT-NC140D3-IUF(D) | F18: 4250 | J18: Yet to start | L18: Prop | M18: Awaiting order request | Q18: 1st site visit done
B19: Prama Hivision | C19: 4 MP Bullet IP Camera | E19: PT-NC140D3-IUF(D) | F19: 4250 | J19: Yet to start | L19: Prop | M19: Awaiting order request | Q19: 1st site visit done
B20: Prama Hivision | C20: 4 MP Bullet IP Camera | E20: PT-NC140D3-IUF(D) | F20: 4250 | J20: Yet to start | L20: Prop | M20: Awaiting order request | Q20: 1st site visit done
B21: Prama Hivision | C21: 4 MP Bullet IP Camera | E21: PT-NC140D3-IUF(D) | F21: 4250 | J21: Yet to start | L21: Prop | M21: Awaiting order request | Q21: 1st site visit done
B22: Prama Hivision | C22: 4 MP Bullet IP Camera | E22: PT-NC140D3-IUF(D) | F22: 4250 | J22: Yet to start | L22: Prop | M22: Awaiting order request | Q22: 1st site visit done
B23: Prama Hivision | C23: 4 MP Bullet IP Camera | E23: PT-NC140D3-IUF(D) | F23: 4250 | J23: Yet to start | L23: Prop | M23: Awaiting order request | Q23: 1st site visit done
B24: Prama Hivision | C24: 4 MP Bullet IP Camera | E24: PT-NC140D3-IUF(D) | F24: 4250 | J24: Yet to start | L24: Prop | M24: Awaiting order request | Q24: 1st site visit done
B25: Prama Hivision | C25: 4 MP Bullet IP Camera | E25: PT-NC140D3-IUF(D) | F25: 4250 | J25: Yet to start | L25: Prop | M25: Awaiting order request | Q25: 1st site visit done
B26: Prama Hivision | C26: 4 MP Bullet IP Camera | E26: PT-NC140D3-IUF(D) | F26: 4250 | J26: Yet to start | L26: Prop | M26: Awaiting order request | Q26: 1st site visit done
B27: Prama Hivision | C27: 4 MP Dome IP Camera Colour/InbuiltMic - Prama | E27: PT-NC143D3LIU(D2) | F27: 4250 | J27: Yet to start | L27: Prop | M27: Awaiting order request | Q27: 1st site visit done
B28: Prama Hivision | C28: 4 MP Dome IP Camera Colour/InbuiltMic - Prama | E28: PT-NC143D3LIU(D2) | F28: 4250 | J28: Yet to start | L28: Prop | M28: Awaiting order request | Q28: 1st site visit done
B29: Prama Hivision | C29: 4 MP Dome IP Camera Colour/InbuiltMic - Prama | E29: PT-NC143D3LIU(D2) | F29: 4250 | J29: Yet to start | L29: Prop | M29: Awaiting order request | Q29: 1st site visit done
... B75: Toshiba | C75: 8 TB Hard Disk - Toshiba | E75: Nil | F75: 18450 | J75: Yet to start | L75: Prop | M75: Awaiting order request | Q75: 1st site visit done
C76: Camera Accessories | F76: 4500
A78: Networking | B78: Grandstream | C78: IPBX Gradstream UCM 6301 | E78: UCM6301 | F78: 36400 | G78: 13280 | J78: Yet to start | L78: Prop | M78: Awaiting order request | Q78: 1st site visit done
B79: TP Link | C79: 24 Port Switch (Gigabit) - TP Link | E79: SG3428D | F79: 15500 | J79: Yet to start | L79: Prop | M79: Awaiting order request | Q79: 1st site visit done
B80: Grandstream | C80: IP Phone (GRP2601) - Grand stream | E80: GRP2601 | F80: 69350
B81: Grandstream | C81: IP Phone GRP2615 | E81: GRP 2615 | F81: 11550
A83: Wifi | B83: TP Link | C83: Access Point EAP245 - TP Link | E83: EAP245 | F83: 8250 | G83: 26340 | J83: Yet to start | L83: Prop | M83: Awaiting order request | Q83: 1st site visit done
B84: TP Link | C84: Access Point EAP245 - TP Link | E84: EAP245 | F84: 8250 | J84: Yet to start | L84: Prop | M84: Awaiting order request | Q84: 1st site visit done
B85: TP Link | C85: Access Point EAP245 - TP Link | E85: EAP245 | F85: 8250 | J85: Yet to start | L85: Prop | M85: Awaiting order request | Q85: 1st site visit done
B86: TP Link | C86: Access Point EAP245 - TP Link | E86: EAP245 | F86: 8250 | J86: Yet to start | L86: Prop | M86: Awaiting order request | Q86: 1st site visit done
B87: TP Link | C87: Access Point EAP245 - TP Link | E87: EAP245 | F87: 8250 | J87: Yet to start | L87: Prop | M87: Awaiting order request | Q87: 1st site visit done
B88: TP Link | C88: Access Point EAP245 - TP Link | E88: EAP245 | F88: 8250 | J88: Yet to start | L88: Prop | M88: Awaiting order request | Q88: 1st site visit done
B89: TP Link | C89: Access Point EAP245 - TP Link | E89: EAP245 | F89: 8250 | J89: Yet to start | L89: Prop | M89: Awaiting order request | Q89: 1st site visit done
B90: TP Link | C90: Access Point EAP245 - TP Link | E90: EAP245 | F90: 8250 | J90: Yet to start | L90: Prop | M90: Awaiting order request | Q90: 1st site visit done
B91: TP Link | C91: Access Point EAP245 - TP Link | E91: EAP245 | F91: 8250 | J91: Yet to start | L91: Prop | M91: Awaiting order request | Q91: 1st site visit done
B92: TP Link | C92: Access Point EAP245 - TP Link | E92: EAP245 | F92: 8250 | J92: Yet to start | L92: Prop | M92: Awaiting order request | Q92: 1st site visit done
B93: TP Link | C93: Access Point EAP245 - TP Link | E93: EAP245 | F93: 8250 | J93: Yet to start | L93: Prop | M93: Awaiting order request | Q93: 1st site visit done
B94: TP Link | C94: Access Point EAP245 - TP Link | E94: EAP245 | F94: 8250 | J94: Yet to start | L94: Prop | M94: Awaiting order request | Q94: 1st site visit done
B95: TP Link | C95: Access Point EAP245 - TP Link | E95: EAP245 | F95: 8250 | J95: Yet to start | L95: Prop | M95: Awaiting order request | Q95: 1st site visit done
... B109: TP Link | C109: TP Link Omada Cloud Controller | E109: OC200 | F109: 16800 | J109: Yet to start | L109: Prop | M109: Awaiting order request | Q109: 1st site visit done
C110: 6 U Rack | E110: Nil | F110: 2550 | J110: Yet to start | L110: Prop | M110: Awaiting order request | Q110: 1st site visit done
C111: 6 U Rack | E111: Nil | F111: 2550 | J111: Yet to start | L111: Prop | M111: Awaiting order request | Q111: 1st site visit done
C112: 6 U Rack | E112: Nil | F112: 2550 | J112: Yet to start | L112: Prop | M112: Awaiting order request | Q112: 1st site visit done
C113: 6 U Rack | E113: Nil | F113: 2550 | J113: Yet to start | L113: Prop | M113: Awaiting order request | Q113: 1st site visit done
A115: Attendance | B115: Hikvision | C115: Hikvision - Finger Print & Face Recognition | E115: DS-K1T320MFWX | F115: 6400 | G115: 640 | J115: Yet to start | L115: Prop | M115: Awaiting order request | Q115: 1st site visit done

Sheet Raghukumaran
B1: Client Name | C1: Mr. Raghukumaran | E1: 9751739555 | F1: Overall site status | J1: Count | K1: % | M1: Material status | N1: Count | O1: % | Q1: Visti No. | R1: IR No. | S1: Date
B2: Site | F2: Yet to start | M2: Awaiting order request
B3: Location | F3: Position marked - I | M3: To order material
B4: GPS Coordinates | F4: Piping done - C | M4: Ordered
B5: Architect | C5: Manny Architects - Ar.Vimalraj | E5: 9080800564 | F5: Wiring done - C | M5: Recd (To test/config)
B6: Site Supervisor | F6: Wiring - Checked Ok - I | M6: Configured - ready for install
B7: Electrician | F7: Wiring rework reqd - C | M7: Delivered
B8: Electrical Contractor | F8: Provision not provided - C | M8: Provision only - Matl Not reqd
B9: Billing contact | F9: Position to be changed - C | M9: Failed - Picked up from site
B10: Carpenter | F10: Installed - working | M10: Failed - Need to service
B11: Civil Supervisor | F11: Installed - To activate - I | M11: Sent for service
B12: G-Drive Link | F12: Installed - Not working - IC | M12: Replaced/Serviced
B13: Mail id | F13: Door Ready - C | M13: Returned - Not reqd
B14: Site Engineer | C14: Mr. Gokulnathan | E14: 8110999947 | F14: Door Not Ready - I
B16: Brand | C16: Product | D16: Serial No. | E16: Model No | F16: Sale Price | G16: Installation charge | H16: Location | I16: Drawing Ref No. | J16: Site status | K16: <--Date | L16: Prop/Addl | M16: Material | N16: <-- Date | O16: Client | P16: Inka | Q16: Comments | R16: SR Nos (If multiple - add all) | S16: DC

Sheet Vinoth 

Sheet Sambath

Sheet vellakovil farm house
B1: Client Name | C1: Vellakovil farm house | F1: Overall site status | J1: Count | K1: % | M1: Material status | N1: Count | O1: % | Q1: Visti No. | R1: IR No. | S1: Date
B2: Site | C2: Vellakovil | F2: Yet to start | M2: Awaiting order request | Q2: 1 | R2: IR No.034 | S2: 14.7.2025 | T2: 1st site visit | U2: Asok
B3: Location | F3: Position marked - I | M3: To order material | Q3: 2 | R3: IR No. | S3: 11.2.2026 | T3: Prework & installation | U3: Kumaraguru & Sateesh
B4: GPS Coordinates | C4: https://www.google.com/maps/place/10%C2%B059'20.9%22N+77%C2%B045'13.1%22E/@10.9891337,77.7510691,888m/data=!3m2!1e3!4b1!4m4!3m3!8m2!3d10.9891337!4d77.753644?hl=en&entry=ttu&g_ep=EgoyMDI1MDgxOS4wIKXMDSoASAFQAw%3D%3D | F4: Piping done - C | M4: Ordered | Q4: 3 | R4: IR No. | S4: 14.2.2026 | T4: installation | U4: Asok & Satheesh
B5: Architect | F5: Wiring done - C | M5: Recd (To test/config) | Q5: 4 | R5: IR No.87 | S5: 19.2.2026 | T5: installation-Gate | U5: Asok
B6: Site Supervisor | C6: Mr. Deena Dhayalan | D6: 9715115549 | F6: Wiring - Checked Ok - I | M6: Configured - ready for install
B7: Electrician | F7: Wiring rework reqd - C | M7: Delivered
B8: Electrical Contractor | F8: Provision not provided - C | M8: Provision only - Matl Not reqd
B9: Billing contact | F9: Position to be changed - C | M9: Failed - Picked up from site
B10: Carpenter | F10: Installed - working | M10: Failed - Need to service
B11: Civil Supervisor | F11: Installed - To activate - I | M11: Sent for service
B12: G-Drive Link | F12: Installed - Not working - IC | M12: Replaced/Serviced
B13: Mail id | F13: Door Ready - C | M13: Returned - Not reqd
B14: Site Engineer | C14: Mr. Vignesh | D14: 9788123499 | F14: Door Not Ready - I
B16: Brand | C16: Product | D16: Serial No. | E16: Model No | F16: Sale Price | G16: Installation charge | H16: Location | I16: Drawing Ref No. | J16: Site status | K16: <--Date | L16: Prop/Addl | M16: Material | N16: <-- Date | O16: Client | P16: Inka | Q16: Comments | R16: SR Nos (If multiple - add all) | S16: DC
A17: Camera | B17: Parma Hikvision | C17: 4 Mp Bullet IP Camera Colour/InbuiltMic - Prama | D17: GK1872750 | E17: PT-NC140D3LIU(D2) | F17: 4740 | G17: 14900 | J17: Installed - working | K17: 11.2.2026 | L17: Prop | M17: Delivered | N17: 9.2.2026 | S17: 261
B18: Parma Hikvision | C18: 4 Mp Bullet IP Camera Colour/InbuiltMic - Prama | D18: GK1867074 | E18: PT-NC140D3LIU(D2) | F18: 4740 | J18: Installed - working | K18: 11.2.2026 | L18: Prop | M18: Delivered | N18: 9.2.2026 | S18: 261
B19: Parma Hikvision | C19: 4 Mp Bullet IP Camera Colour/InbuiltMic - Prama | D19: GK1869573 | E19: PT-NC140D3LIU(D2) | F19: 4740 | J19: Installed - working | K19: 11.2.2026 | L19: Prop | M19: Delivered | N19: 9.2.2026 | S19: 261
B20: Parma Hikvision | C20: 4 Mp Bullet IP Camera Colour/InbuiltMic - Prama | D20: GK1869449 | E20: PT-NC140D3LIU(D2) | F20: 4740 | J20: Installed - working | K20: 11.2.2026 | L20: Prop | M20: Delivered | N20: 9.2.2026 | S20: 261
B21: Parma Hikvision | C21: 4 Mp Bullet IP Camera Colour/InbuiltMic - Prama | D21: GK1872751 | E21: PT-NC140D3LIU(D2) | F21: 4740 | J21: Installed - working | K21: 11.2.2026 | L21: Prop | M21: Delivered | N21: 9.2.2026 | S21: 261
B22: Parma Hikvision | C22: 4 Mp Bullet IP Camera Colour/InbuiltMic - Prama | D22: GK1869556 | E22: PT-NC140D3LIU(D2) | F22: 4740 | J22: Installed - working | K22: 11.2.2026 | L22: Prop | M22: Delivered | N22: 9.2.2026 | S22: 261
B23: Parma Hikvision | C23: 4 Mp Bullet IP Camera Colour/InbuiltMic - Prama | D23: GK1869566 | E23: PT-NC140D3LIU(D2) | F23: 4740 | J23: Installed - working | K23: 11.2.2026 | L23: Prop | M23: Delivered | N23: 9.2.2026 | S23: 261
B24: Parma Hikvision | C24: 4 Mp Bullet IP Camera Colour/InbuiltMic - Prama | E24: PT-NC140D3LIU(D2) | F24: 4740 | J24: Provision only - Matl Not reqd | L24: Prop | M24: Returned
B25: Parma Hikvision | C25: 4 Mp Bullet IP Camera Colour/InbuiltMic - Prama | E25: PT-NC140D3LIU(D2) | F25: 4740 | J25: Provision only - Matl Not reqd | L25: Prop | M25: Returned
B26: Hikvision | C26: 4 MP Varifocal Camera -Hikvision | D26: GQ2141597 | E26: DS-2CD3641G2-LIZS | F26: 7260 | J26: Installed - working | K26: 14.2.2026 | L26: Prop | M26: Delivered | N26: 13.2.2026 | S26: 264
B27: Hikvision | C27: 4 MP Varifocal Camera -Hikvision | D27: GQ2141536 | E27: DS-2CD3641G2-LIZS | F27: 7260 | J27: Installed - working | K27: 14.2.2026 | L27: Prop | M27: Delivered | N27: 13.2.2026 | S27: 264
B28: Hikvision | C28: 4 MP Varifocal Camera -Hikvision | D28: GQ2141525 | E28: DS-2CD3641G2-LIZS | F28: 7260 | J28: Installed - working | K28: 14.2.2026 | L28: Prop | M28: Delivered | N28: 13.2.2026 | S28: 264
B29: Hikvision | C29: 16 channel NVR (K2) - Hikvision | D29: FX4299619 | E29: DS-7616NI-K2 | F29: 15600 | J29: Installed - working | K29: 11.2.2026 | L29: Prop | M29: Delivered | N29: 9.2.2026 | S29: 261
B30: TP Link | C30: 16 Port POE Gigabit Switch (TL-SG1218MPE) - TP Link | D30: 225A870000614 | E30: TL-SG1218MPE | F30: 15100 | J30: Installed - working | K30: 11.2.2026 | L30: Prop | M30: Delivered | N30: 9.2.2026 | S30: 261
B31: Toshiba | C31: 4 TB Hard Disk - Toshiba | D31: 75N3S0BSSRWL | E31: AVHDDS300 | F31: 8160 | J31: Installed - working | K31: 11.2.2026 | L31: Prop | M31: Delivered | N31: 10.2.2026 | S31: 262
C32: Camera Accessories | F32: 2500
A34: Security system | B34: Hikvision | C34: Hikvision - Control Panel AX Pro | D34: Q32572640 | E34: DS-PWA64 - AX Pro | F34: 32000 | G34: 10000 | J34: Installed - working | K34: 11.2.2026 | L34: Prop | M34: Delivered | N34: 9.2.2026 | S34: 261
B35: Hikvision | C35: PANIC SWITCH - HIKVISION | D35: Q33901108 | E35: PHDSPB2 | F35: 470 | J35: Installed - working | K35: 11.2.2026 | L35: Prop | M35: Delivered | N35: 9.2.2026 | S35: 261
B36: Hikvision | C36: Hikvision Wireless Keyfob | D36: Q32559380 | E36: PKF1-WB | F36: 1580 | J36: Installed - working | K36: 11.2.2026 | L36: Prop | M36: Delivered | N36: 9.2.2026 | S36: 261
B37: Hikvision | C37: Wireless Indoor Siren - Hikvision | D37: Q38312918 | E37: DS-PS1-I-WB | F37: 9500 | J37: Installed - working | K37: 11.2.2026 | L37: Prop | M37: Delivered | N37: 9.2.2026 | S37: 261
B38: Hikvision | C38: Wireless Outdoor Siren - Hikvision | D38: Q43136676 | E38: DS-PS1-E-WB | F38: 7350 | J38: Installed - working | K38: 11.2.2026 | L38: Prop | M38: Delivered | N38: 9.2.2026 | S38: 261
A40: Automation | B40: Autozone | C40: CAR CONTROL SMART TAG(GATE AUTOMATION) | E40: AZSTS18 | F40: 9980 | L40: Prop | M40: Provision only - Matl Not reqd
B41: Autozone | C41: CAR CONTROL SMART TAG(GATE AUTOMATION) | E41: AZSTS18 | F41: 9980 | L41: Prop | M41: Provision only - Matl Not reqd
B42: Autozone | C42: CAR CONTROL SMART TAG(GATE AUTOMATION) | E42: AZSTS18 | F42: 9980 | L42: Prop | M42: Provision only - Matl Not reqd
B43: Autozone | C43: SMART TAG EXTERNAL RECEIVER( CAR CONTROL) | E43: AZER141 | F43: 9850 | L43: Prop | M43: Provision only - Matl Not reqd
C44: WIFI-DIVICE APP CONTROL (GATE AUTOMATION) | F44: 3670 | L44: Prop | M44: Delivered | N44: 9.2.2026 | S44: 261
C45: Sliding Gate Operator CONTROL BOARD +BASE PLATE + SPRING LIMIT)+ 1 MTR RAC ( 9MM) - AZ -9MM-4 NOS+ BOLT-PHOTOCELL AZ -PC10A- 1 PAIR+ IND - TRANSMITTER - 2NOS (AZ-T23B) | E45: AZSL100A/KIT | F45: 44000 | G45: 9000 | J45: Installed - working | K45: 19.2.2026 | L45: Prop | M45: Delivered | N45: 9.2.2026 | R45: 87 | S45: 261
C46: Gate Rack | E46: AZ 9mm | F46: 1952 | J46: Installed - working | K46: 19.2.2026 | L46: Prop | M46: Delivered | N46: 9.2.2026 | R46: 87 | S46: 261
C47: Gate Rack | E47: AZ 9mm | F47: 1952 | J47: Installed - working | K47: 19.2.2026 | L47: Prop | M47: Delivered | N47: 9.2.2026 | R47: 87 | S47: 261
C48: Gate Rack | E48: AZ 9mm | F48: 1952 | J48: Installed - working | K48: 19.2.2026 | L48: Prop | M48: Delivered | N48: 9.2.2026 | R48: 87 | S48: 261
C49: Gate Rack | E49: AZ 9mm | F49: 1952 | J49: Installed - working | K49: 19.2.2026 | L49: Prop | M49: Delivered | N49: 9.2.2026 | R49: 87 | S49: 261
C51: PVC (Hensel) Box | L51: Addl | M51: Delivered | N51: 25.8.2025 | S51: 136
C52: PVC (Hensel) Box | L52: Addl | M52: Delivered | N52: 25.8.2025 | S52: 136
C53: PVC (Hensel) Box | L53: Addl | M53: Delivered | N53: 25.8.2025 | S53: 136
C54: PVC (Hensel) Box | L54: Addl | M54: Delivered | N54: 25.8.2025 | S54: 136
C55: PVC (Hensel) Box | L55: Addl | M55: Delivered | N55: 25.8.2025 | S55: 136
C56: PVC (Hensel) Box | L56: Addl | M56: Delivered | N56: 25.8.2025 | S56: 136
C57: PVC (Hensel) Box | L57: Addl | M57: Delivered | N57: 25.8.2025 | S57: 136
C58: PVC (Hensel) Box | L58: Addl | M58: Delivered | N58: 25.8.2025 | S58: 136
C59: PVC (Hensel) Box | L59: Addl | M59: Delivered | N59: 25.8.2025 | S59: 136
C60: Camera Stand Adjustable- 1 to 2 Feet | L60: Addl | M60: Delivered | N60: 13.2.2026 | S60: 264
C61: Access Point EAP245 - TP Link | D61: 2254908002696 | E61: EAP245 | L61: Addl | M61: Delivered | N61: 9.2.2026 | S61: 261
C62: Cat 6 Jack - Netfox - 40 Nos. | M62: Delivered | N62: 9.2.2026 | S62: 261
C63: GATE RACK | E63: AZ -9MM | J63: Installed - working | K63: 19.2.2026 | L63: Addl | M63: Delivered | N63: 18.2.2026 | S63: 270 | T63: 87

Sheet Rajesh
B1: Client Name | C1: Dr. Rajesh | F1: Overall site status | J1: Count | K1: % | M1: Material status | N1: Count | O1: % | Q1: Visti No. | R1: IR No. | S1: Date
B2: Site | C2: Sulur | F2: Yet to start | M2: Awaiting order request | Q2: 1 | R2: IR No.211 | S2: 26.6.2025 | T2: 1st site visit | U2: Asok
B3: Location | F3: Position marked - I | M3: To order material
B4: GPS Coordinates | F4: Piping done - C | M4: Ordered
B5: Architect | F5: Wiring done - C | M5: Recd (To test/config)
B6: Site Supervisor | F6: Wiring - Checked Ok - I | M6: Configured - ready for install
B7: Electrician | F7: Wiring rework reqd - C | M7: Delivered
B8: Electrical Contractor | F8: Provision not provided - C | M8: Provision only - Matl Not reqd
B9: Billing contact | F9: Position to be changed - C | M9: Failed - Picked up from site
B10: Carpenter | F10: Installed - working | M10: Failed - Need to service
B11: Civil Supervisor | F11: Installed - To activate - I | M11: Sent for service
B12: G-Drive Link | F12: Installed - Not working - IC | M12: Replaced/Serviced
B13: Mail id | F13: Door Ready - C | M13: Returned - Not reqd
B14: Site Engineer | F14: Door Not Ready - I
B16: Brand | C16: Product | D16: Serial No. | E16: Model No | F16: Sale Price | G16: Installation charge | H16: Location | I16: Drawing Ref No. | J16: Site status | K16: <--Date | L16: Prop/Addl | M16: Material | N16: <-- Date | O16: Client | P16: Inka | Q16: Comments | R16: SR Nos (If multiple - add all) | S16: DC

Sheet Eventide
B1: Client Name | C1: Eventide coffee shop | E1: 8903320007 | F1: Overall site status | J1: Count | K1: % | M1: Material status | N1: Count | O1: % | Q1: Visti No. | R1: IR No. | S1: Date
B2: Site | C2: Chennai | F2: Yet to start | M2: Awaiting order request | Q2: 1 | R2: IR No.27 | S2: 20.6.2025 | T2: 1st site visit | U2: Kumaraguru
B3: Location | F3: Position marked - I | M3: To order material | Q3: 2 | R3: IR No.33 | S3: 8.7.2025 | T3: cable checking | U3: Kumaraguru
B4: GPS Coordinates | F4: Piping done - C | M4: Ordered | Q4: 3 | S4: 30.7.2025 | T4: installation | U4: Azhagar & Kumaraguru
B5: Architect | C5: Mr.Adithya | F5: Wiring done - C | M5: Recd (To test/config) | Q5: 4 | S5: 8.8.2025 | T5: installation | U5: Kavi electrician +1
B6: Site Supervisor | F6: Wiring - Checked Ok - I | M6: Configured - ready for install | Q6: 5 | S6: 29.9.2025 | T6: service | U6: Kumaraguru
B7: Electrician | F7: Wiring rework reqd - C | M7: Delivered
B8: Electrical Contractor | F8: Provision not provided - C | M8: Provision only - Matl Not reqd
B9: Billing contact | F9: Position to be changed - C | M9: Failed - Picked up from site
B10: Carpenter | F10: Installed - working | M10: Failed - Need to service
B11: Civil Supervisor | F11: Installed - To activate - I | M11: Sent for service
B12: G-Drive Link | F12: Installed - Not working - IC | M12: Replaced/Serviced
B13: Mail id | F13: Door Ready - C | M13: Returned - Not reqd
B14: Site Engineer | D14: Mr.John,Manager | E14: 7094316593 | F14: Door Not Ready - I
B16: Brand | C16: Product | D16: Serial No. | E16: Model No | F16: Sale Price | G16: Installation charge | H16: Location | I16: Drawing Ref No. | J16: Site status | K16: <--Date | L16: Prop/Addl | M16: Material | N16: <-- Date | O16: Client | P16: Inka | Q16: Comments | R16: SR Nos (If multiple - add all) | S16: DC
A17: Camera | B17: CP Plus | C17: 4 mp wifi outdoor camera -cp plus | D17: 2503013202012607 | E17: cpz43a | F17: 4400 | G17: 25000 | J17: Installed - working | K17: 8.8.2025 | L17: Prop | M17: Delivered | N17: 24.7.2025 | S17: 109
B18: CP Plus | C18: 4 mp wifi outdoor camera -cp plus | D18: 2.5030132e+15 | E18: cpz43a | F18: 4400 | J18: Installed - working | K18: 8.8.2025 | L18: Prop | M18: Delivered | N18: 24.7.2025 | S18: 109
B19: CP Plus | C19: 4 mp wifi outdoor camera -cp plus | D19: 2503013202016966 | E19: cpz43a | F19: 4400 | J19: Installed - working | K19: 8.8.2025 | L19: Prop | M19: Delivered | N19: 24.7.2025 | S19: 109
B20: CP Plus | C20: 4 mp wifi outdoor camera -cp plus | D20: 2503013202012559 | E20: cpz43a | F20: 4400 | J20: Installed - working | K20: 8.8.2025 | L20: Prop | M20: Delivered | N20: 24.7.2025 | S20: 109
B21: CP Plus | C21: 4 mp wifi outdoor camera -cp plus | D21: 2503013202012658 | E21: cpz43a | F21: 4400 | J21: Installed - working | K21: 8.8.2025 | L21: Prop | M21: Delivered | N21: 24.7.2025 | S21: 109
B22: CP Plus | C22: 4 mp wifi outdoor camera -cp plus | D22: 2503013202015434 | E22: cpz43a | F22: 4400 | J22: Installed - working | K22: 8.8.2025 | L22: Prop | M22: Delivered | N22: 24.7.2025 | S22: 109
B23: Sandisk | C23: Memory Card 256GB - Sandisk | F23: 2350 | J23: Installed - working | K23: 8.8.2025 | L23: Prop | M23: Delivered | N23: 24.7.2025 | S23: 111
B24: Sandisk | C24: Memory Card 256GB - Sandisk | F24: 2350 | J24: Installed - working | K24: 8.8.2025 | L24: Prop | M24: Delivered | N24: 24.7.2025 | S24: 111
B25: Sandisk | C25: Memory Card 256GB - Sandisk | F25: 2350 | J25: Installed - working | K25: 8.8.2025 | L25: Prop | M25: Delivered | N25: 24.7.2025 | S25: 111
B26: Sandisk | C26: Memory Card 256GB - Sandisk | F26: 2350 | J26: Installed - working | K26: 8.8.2025 | L26: Prop | M26: Delivered | N26: 24.7.2025 | S26: 111
B27: Sandisk | C27: Memory Card 256GB - Sandisk | F27: 2350 | J27: Installed - working | K27: 8.8.2025 | L27: Prop | M27: Delivered | N27: 24.7.2025 | S27: 111
B28: Sandisk | C28: Memory Card 256GB - Sandisk | F28: 2350 | J28: Installed - working | K28: 8.8.2025 | L28: Prop | M28: Delivered | N28: 24.7.2025 | S28: 111
C29: PVC (Hensel) Box | F29: 154 | J29: Installed | K29: 8.8.2025 | L29: Prop | M29: Delivered | N29: 24.7.2025 | S29: 109
C30: PVC (Hensel) Box | F30: 154 | J30: Installed | K30: 8.8.2025 | L30: Prop | M30: Delivered | N30: 24.7.2025 | S30: 109
C31: PVC (Hensel) Box | F31: 154 | J31: Installed | K31: 8.8.2025 | L31: Prop | M31: Delivered | N31: 24.7.2025 | S31: 109
C32: PVC (Hensel) Box | F32: 154 | J32: Installed | K32: 8.8.2025 | L32: Prop | M32: Delivered | N32: 24.7.2025 | S32: 109
C33: PVC (Hensel) Box | F33: 154 | J33: Installed | K33: 8.8.2025 | L33: Prop | M33: Delivered | N33: 24.7.2025 | S33: 109
C34: PVC (Hensel) Box | F34: 154 | J34: Installed | K34: 8.8.2025 | L34: Prop | M34: Delivered | N34: 24.7.2025 | S34: 109
B35: Netfox | C35: Cat 6 Jack - Netfox-30 Nos. | E35: RJ-45 | J35: Installed - working | K35: 8.8.2025 | L35: Prop | M35: Delivered | N35: 24.7.2025 | S35: 109
A36: Wifi | B36: TP Link | C36: Access Point Indoor EAP 610 - TP Link | D36: 22475C2001182 | E36: EAP 610 Indoor | F36: 11500 | J36: Installed - working | K36: 8.8.2025 | L36: Prop | M36: Delivered | N36: 24.7.2025 | S36: 109
B37: TP Link | C37: Wi Fi Range Extender (Re205) - TP Link | D37: 2248815002496 | E37: RE205 | F37: 5200

Sheet Prakash
B1: Client Name | C1: Mr. Prakash | F1: Overall site status | J1: Count | K1: % | M1: Material status | N1: Count | O1: % | Q1: Visti No. | R1: IR No. | S1: Date
B2: Site | C2: Ganapathy | F2: Yet to start | M2: Awaiting order request | Q2: 1 | R2: IR No.211 | S2: 26.6.25 | T2: 1st site visit | U2: Asok
B3: Location | F3: Position marked - I | M3: To order material | Q3: 2 | R3: IR No.14 | S3: 9.9.25 | T3: Discussion with client and electrician reg security system | U3: Asok
B4: GPS Coordinates | F4: Piping done - C | M4: Ordered
B5: Architect | F5: Wiring done - C | M5: Recd (To test/config)
B6: Site Supervisor | F6: Wiring - Checked Ok - I | M6: Configured - ready for install
B7: Electrician | F7: Wiring rework reqd - C | M7: Delivered
B8: Electrical Contractor | F8: Provision not provided - C | M8: Provision only - Matl Not reqd
B9: Billing contact | F9: Position to be changed - C | M9: Failed - Picked up from site
B10: Carpenter | F10: Installed - working | M10: Failed - Need to service
B11: Civil Supervisor | F11: Installed - To activate - I | M11: Sent for service
B12: G-Drive Link | F12: Installed - Not working - IC | M12: Replaced/Serviced
B13: Mail id | F13: Door Ready - C | M13: Returned - Not reqd
B14: Site Engineer | F14: Door Not Ready - I
B16: Brand | C16: Product | D16: Serial No. | E16: Model No | F16: Sale Price | G16: Installation charge | H16: Location | I16: Drawing Ref No. | J16: Site status | K16: <--Date | L16: Prop/Addl | M16: Material | N16: <-- Date | O16: Client | P16: Inka | Q16: Comments | R16: SR Nos (If multiple - add all) | S16: DC
A17: Camera | B17: Prama Hikvision | C17: 4 MP Bullet IP Camera Colour | E17: PT-NC140D3-L(D) | F17: 4750 | G17: 8500 | J17: Position marked - I | L17: Prop
B18: Prama Hikvision | C18: 4 MP Bullet IP Camera Colour | E18: PT-NC140D3-L(D) | F18: 4750 | J18: Position marked - I | L18: Prop
B19: Prama Hikvision | C19: 4 MP Bullet IP Camera Colour | E19: PT-NC140D3-L(D) | F19: 4750 | J19: Position marked - I | L19: Prop
B20: Prama Hikvision | C20: 4 MP Bullet IP Camera Colour | E20: PT-NC140D3-L(D) | F20: 4750 | J20: Position marked - I | L20: Prop
B21: Prama Hikvision | C21: 4 MP Bullet IP Camera Colour | E21: PT-NC140D3-L(D) | F21: 4750 | J21: Position marked - I | L21: Prop
B22: Prama Hikvision | C22: 4 MP Bullet IP Camera Colour | E22: PT-NC140D3-L(D) | F22: 4750 | J22: Position marked - I | L22: Prop
B23: Prama Hikvision | C23: 4 MP Bullet IP Camera Colour | E23: PT-NC140D3-L(D) | F23: 4750 | J23: Position marked - I | L23: Prop
B24: Prama Hikvision | C24: 4 MP Bullet IP Camera Colour | E24: PT-NC140D3-L(D) | F24: 4750 | J24: Position marked - I | L24: Prop
B25: Hikvision | C25: 8 Channel NVR (2 Sata) - | E25: DS-7608NI-K2 | F25: 9750 | J25: Position marked - I | L25: Prop
B26: TP Link | C26: 8 Port POE Switch (Gigabit) 2 Uplink SFP | E26: TL-SG2210P | F26: 8400 | J26: Position marked - I | L26: Prop
B27: Toshiba | C27: 4 TB Hard Disk - Toshiba | E27: AVHDDS300 | F27: 8160 | J27: Position marked - I | L27: Prop
C28: Camera Accessories | F28: 2500 | J28: Position marked - I | L28: Prop
A30: Security system | B30: Hikvision | C30: Hikvision - Control Panel AX Pro | E30: DS-PWA64 - AX Pro | F30: 32000 | G30: 19500 | J30: Position marked - I | L30: Prop
B31: Hikvision | C31: Hikvision - Wireless Zone Receiver/Expander (Hybrid Pro) | E31: DS-PM1-RT-HWB | F31: 8240 | J31: Position marked - I | L31: Prop
B32: Hikvision | C32: Hikvision - Wireless Zone Receiver/Expander (Hybrid Pro) | E32: DS-PM1-RT-HWB | F32: 8240 | J32: Position marked - I | L32: Prop
B33: Hikvision | C33: Hikvision - Wireless Zone Receiver/Expander (Hybrid Pro) | E33: DS-PM1-RT-HWB | F33: 8240 | J33: Position marked - I | L33: Prop
B34: Hikvision | C34: Wireless Magnetic Door Sensor - Hikvision | E34: DS-PD1-MC-WWS | F34: 2950 | J34: Position marked - I | L34: Prop
B35: Hikvision | C35: Wireless Magnetic Door Sensor - Hikvision | E35: DS-PD1-MC-WWS | F35: 2950 | J35: Position marked - I | L35: Prop
B36: Hikvision | C36: Wireless Magnetic Door Sensor - Hikvision | E36: DS-PD1-MC-WWS | F36: 2950 | J36: Position marked - I | L36: Prop
B37: Hikvision | C37: Wireless Magnetic Door Sensor - Hikvision | E37: DS-PD1-MC-WWS | F37: 2950 | J37: Position marked - I | L37: Prop
B38: Hikvision | C38: Wireless Magnetic Door Sensor - Hikvision | E38: DS-PD1-MC-WWS | F38: 2950 | J38: Position marked - I | L38: Prop
B39: Hikvision | C39: Wireless Magnetic Door Sensor - Hikvision | E39: DS-PD1-MC-WWS | F39: 2950 | J39: Position marked - I | L39: Prop
B40: Hikvision | C40: Wireless Magnetic Door Sensor - Hikvision | E40: DS-PD1-MC-WWS | F40: 2950 | J40: Position marked - I | L40: Prop
B41: Hikvision | C41: Wireless Magnetic Door Sensor - Hikvision | E41: DS-PD1-MC-WWS | F41: 2950 | J41: Position marked - I | L41: Prop
B42: Hikvision | C42: Wireless Magnetic Door Sensor - Hikvision | E42: DS-PD1-MC-WWS | F42: 2950 | J42: Position marked - I | L42: Prop
... B65: Hikvision | C65: Wireless Outdoor Siren - Hikvision | E65: DS-PS1-E-WB | F65: 5100 | J65: Position marked - I | L65: Prop
C66: Battery Backup | E66: 12V-7amp | F66: 2240 | J66: Position marked - I | L66: Prop

Sheet Prem Kumaran
B1: Client Name | C1: Mr. Premkumaran | E1: 9894733399 | F1: Overall site status | J1: Count | K1: % | M1: Material status | N1: Count | O1: % | Q1: Visti No. | R1: IR No. | S1: Date
B2: Site | C2: Peelamedu | F2: Yet to start | M2: Awaiting order request | Q2: 1 | R2: IR No.1352 | S2: 30.5.2025 | T2: 1st site visit | U2: Asok
B3: Location | F3: Position marked - I | M3: To order material
B4: GPS Coordinates | F4: Piping done - C | M4: Ordered
B5: Architect | F5: Wiring done - C | M5: Recd (To test/config)
B6: Site Supervisor | F6: Wiring - Checked Ok - I | M6: Configured - ready for install
B7: Electrician | F7: Wiring rework reqd - C | M7: Delivered
B8: Electrical Contractor | F8: Provision not provided - C | M8: Provision only - Matl Not reqd
B9: Billing contact | F9: Position to be changed - C | M9: Failed - Picked up from site
B10: Carpenter | F10: Installed - working | M10: Failed - Need to service
B11: Civil Supervisor | C11: Mr. Lokanath | E11: 9047861479 | F11: Installed - To activate - I | M11: Sent for service
B12: G-Drive Link | F12: Installed - Not working - IC | M12: Replaced/Serviced
B13: Mail id | F13: Door Ready - C | M13: Returned - Not reqd
B14: Site Engineer | F14: Door Not Ready - I
B16: Brand | C16: Product | D16: Serial No. | E16: Model No | F16: Sale Price | G16: Installation charge | H16: Location | I16: Drawing Ref No. | J16: Site status | K16: <--Date | L16: Prop/Addl | M16: Material | N16: <-- Date | O16: Client | P16: Inka | Q16: Comments | R16: SR Nos (If multiple - add all) | S16: DC
A17: Camera | B17: Prama | C17: 4 Mp Bullet IP Camera Colour/InbuiltMic | E17: PT-NC140D3LIU(D2) | F17: 4750 | G17: 7920 | H17: GF | I17: A01C | J17: Yet to start | L17: Prop
B18: Prama | C18: 4 Mp Bullet IP Camera Colour/InbuiltMic | E18: PT-NC140D3LIU(D2) | F18: 4750 | H18: GF | I18: A02C | J18: Yet to start | L18: Prop
B19: Prama | C19: 4 Mp Bullet IP Camera Colour/InbuiltMic | E19: PT-NC140D3LIU(D2) | F19: 4750 | H19: GF | I19: A03C | J19: Yet to start | L19: Prop
B20: Prama | C20: 4 Mp Bullet IP Camera Colour/InbuiltMic | E20: PT-NC140D3LIU(D2) | F20: 4750 | H20: GF | I20: A04C | J20: Yet to start | L20: Prop
B21: Prama | C21: 4 Mp Bullet IP Camera Colour/InbuiltMic | E21: PT-NC140D3LIU(D2) | F21: 4750 | H21: GF | I21: A05C | J21: Yet to start | L21: Prop
B22: Prama | C22: 4 Mp Bullet IP Camera Colour/InbuiltMic | E22: PT-NC140D3LIU(D2) | F22: 4750 | H22: GF | I22: A06C | J22: Yet to start | L22: Prop
B23: Prama | C23: 4 Mp Bullet IP Camera Colour/InbuiltMic | E23: PT-NC140D3LIU(D2) | F23: 4750 | H23: FF | I23: A12C | J23: Yet to start | L23: Prop
B24: Prama | C24: 4 Mp Bullet IP Camera Colour/InbuiltMic | E24: PT-NC140D3LIU(D2) | F24: 4750 | H24: SF | I24: A15C | J24: Yet to start | L24: Prop
B25: Prama | C25: 4 Mp Bullet IP Camera Colour/InbuiltMic | E25: PT-NC140D3LIU(D2) | F25: 4750 | J25: Yet to start | L25: Prop
B26: Prama | C26: 4 Mp Bullet IP Camera Colour/InbuiltMic | E26: PT-NC140D3LIU(D2) | F26: 4750 | J26: Yet to start | L26: Prop
B27: Hikvision | C27: 16 channel NVR (K4) - Hikvision | E27: DS-7716NI-K4 | F27: 15600 | J27: Yet to start | L27: Prop
B28: TP link | C28: 8 Port POE Switch (Gigabit) 2 Uplink SFP - TP Link | E28: TL-SG2210P | F28: 8250 | J28: Yet to start | L28: Prop
B29: WBOX | C29: 2 TB Hard Disk - WD | E29: WDCWD022PURZ | F29: 5850 | J29: Yet to start | L29: Prop
A31: VDP | B31: Hikvision | C31: VDP Outdoor Camera - Hikvision | E31: DS-KD8003-IME1/Surface | F31: 11600 | G31: 3500 | H31: GF | I31: A11V | J31: Yet to start | L31: Prop
B32: Hikvision | C32: VDP Indoor Monitor - Hikvision | E32: DS-KH6320-WTE1 | F32: 10480 | H32: GF | I32: A10V | J32: Yet to start | L32: Prop
B33: Hikvision | C33: 4 Port POE Switch | E33: DS-3E0105P-E/M | F33: 3750 | H33: GF | J33: Yet to start | L33: Prop
A35: Wifi | B35: TP Link | C35: Access Point EAP245 - TP Link | E35: EAP245 | F35: 8850 | G35: 3915 | H35: GF | I35: A09AP | J35: Yet to start | L35: Prop
B36: TP Link | C36: Access Point EAP245 - TP Link | E36: EAP245 | F36: 8850 | H36: FF | I36: A13AP | J36: Yet to start | L36: Prop
B37: TP Link | C37: Access Point EAP245 - TP Link | E37: EAP245 | F37: 8850 | H37: FF | I37: A14AP | J37: Yet to start | L37: Prop
B38: TP Link | C38: Access Point EAP245 - TP Link | E38: EAP245 | F38: 8850 | H38: SF | I38: A16AP | J38: Yet to start | L38: Prop
A40: Automation | B40: Eglu | C40: In-Wall Switch (2S-DS) - Eg | E40: In wall 2S | F40: 7800 | G40: 6300 | J40: Yet to start | L40: Prop
B41: Eglu | C41: In-Wall Switch (2S-DS) - Eg | E41: In wall 2S | F41: 7800 | J41: Yet to start | L41: Prop
B42: Eglu | C42: In-Wall Switch 3S - Eg | E42: EGIW04R | F42: 9550 | J42: Yet to start | L42: Prop
B43: Eglu | C43: HUB PLUS -eGlu | E43: eglu | F43: 27500 | J43: Yet to start | L43: Prop

Sheet Codissia
B1: Client Name | C1: Codissia | D1: Mr. Krishnakumar | E1: 9994322036 | F1: Overall site status | J1: Count | K1: % | M1: Material status | N1: Count | O1: % | Q1: Visti No. | R1: IR No. | S1: Date
B2: Site | C2: Sulur | F2: Yet to start | M2: Awaiting order request | Q2: 1 | R2: IR No.1511 | S2: 8.3.2025 | T2: 1st site visit | U2: Asok
B3: Location | F3: Position marked - I | M3: To order material | Q3: 2 | R3: IR No.1354 | S3: 2.6.2025 | T3: Cable checking | U3: Asok
B4: GPS Coordinates | F4: Piping done - C | M4: Ordered | Q4: 3 | R4: IR No.1573 | S4: 7.6.2025 | T4: To remove existing cameras | U4: Kumaraguru
B5: Architect | F5: Wiring done - C | M5: Recd (To test/config)
B6: Site Supervisor | F6: Wiring - Checked Ok - I | M6: Configured - ready for install
B7: Electrician | C7: Mr.Chella | E7: 8825979969 | F7: Wiring rework reqd - C | M7: Delivered
B8: Electrical Contractor | F8: Provision not provided - C | M8: Provision only - Matl Not reqd
B9: Billing contact | F9: Position to be changed - C | M9: Failed - Picked up from site
B10: Carpenter | F10: Installed - working | M10: Failed - Need to service
B11: Civil Supervisor | F11: Installed - To activate - I | M11: Sent for service
B12: G-Drive Link | F12: Installed - Not working - IC | M12: Replaced/Serviced
B13: Mail id | F13: Door Ready - C | M13: Returned - Not reqd
B14: Site Engineer | F14: Door Not Ready - I
B16: Brand | C16: Product | D16: Serial No. | E16: Model No | F16: Sale Price | G16: Installation charge | H16: Location | I16: Drawing Ref No. | J16: Site status | K16: <--Date | L16: Prop/Addl | M16: Material | N16: <-- Date | O16: Client | P16: Inka | Q16: Comments | R16: SR Nos (If multiple - add all) | S16: DC
A17: Camera | B17: CP Plus | C17: 4 MP Bullet IP Camera - CP Plus | E17: CP-UNC-TA41L3C- | F17: 3300 | G17: 17980 | I17: A01C | J17: Installed - working | L17: Prop
B18: CP Plus | C18: 4 MP Bullet IP Camera - CP Plus | E18: CP-UNC-TA41L3C- | F18: 3300 | I18: A02C | J18: Installed - working | L18: Prop
B19: CP Plus | C19: 4 MP Bullet IP Camera - CP Plus | E19: CP-UNC-TA41L3C- | F19: 3300 | I19: A03C | J19: Installed - working | L19: Prop
B20: CP Plus | C20: 4 MP Bullet IP Camera - CP Plus | E20: CP-UNC-TA41L3C- | F20: 3300 | I20: A04C | J20: Installed - working | L20: Prop
B21: CP Plus | C21: 4 MP Bullet IP Camera - CP Plus | E21: CP-UNC-TA41L3C- | F21: 3300 | I21: A05C | J21: Installed - working | L21: Prop
B22: CP Plus | C22: 4 MP Bullet IP Camera - CP Plus | E22: CP-UNC-TA41L3C- | F22: 3300 | I22: A06C | J22: Installed - working | L22: Prop
B23: CP Plus | C23: 4 MP Bullet IP Camera - CP Plus | E23: CP-UNC-TA41L3C- | F23: 3300 | I23: A07C | J23: Installed - working | L23: Prop
B24: CP Plus | C24: 4 MP Bullet IP Camera - CP Plus | E24: CP-UNC-TA41L3C- | F24: 3300 | I24: A08C | J24: Installed - working | L24: Prop
B25: CP Plus | C25: 4 MP Bullet IP Camera - CP Plus | E25: CP-UNC-TA41L3C- | F25: 3300 | I25: A09C | J25: Installed - working | L25: Prop
B26: CP Plus | C26: 4 MP Bullet IP Camera - CP Plus | E26: CP-UNC-TA41L3C- | F26: 3300 | I26: A10C` | J26: Installed - working | L26: Prop
B27: CP Plus | C27: 4 MP Bullet IP Camera - CP Plus | E27: CP-UNC-TA41L3C- | F27: 3300 | J27: Installed - working | L27: Prop
B28: CP Plus | C28: 4 MP Bullet IP Camera - CP Plus | E28: CP-UNC-TA41L3C- | F28: 3300 | J28: Installed - working | L28: Prop
B29: CP Plus | C29: 4 MP Bullet IP Camera - CP Plus | E29: CP-UNC-TA41L3C- | F29: 3300 | J29: Installed - working | L29: Prop
B30: CP Plus | C30: 4 mp varifocal camera | E30: CP-UNC-TA41ZPL5-MD | F30: 6336 | J30: Installed - working | L30: Prop
B31: CP Plus | C31: 4 mp varifocal camera | E31: CP-UNC-TA41ZPL5-MD | F31: 6336 | L31: Prop
B32: CP Plus | C32: 4 mp varifocal camera | E32: CP-UNC-TA41ZPL5-MD | F32: 6336 | L32: Prop
B33: CP Plus | C33: 4 MP Dome IP Camera - CP Plus | E33: CP-UNC-DA41PL3C | F33: 3200 | J33: Installed - working | L33: Prop
B34: CP Plus | C34: 4 MP Dome IP Camera - CP Plus | E34: CP-UNC-DA41PL3C | F34: 3200 | J34: Installed - working | L34: Prop
B35: CP Plus | C35: 4 MP Dome IP Camera - CP Plus | E35: CP-UNC-DA41PL3C | F35: 3200 | J35: Installed - working | L35: Prop
B36: CP Plus | C36: 4 MP Dome IP Camera - CP Plus | E36: CP-UNC-DA41PL3C | F36: 3200 | J36: Installed - working | L36: Prop
B37: CP Plus | C37: 4 MP Dome IP Camera - CP Plus | E37: CP-UNC-DA41PL3C | F37: 3200 | J37: Installed - working | L37: Prop
B38: CP Plus | C38: 4 MP Dome IP Camera - CP Plus | E38: CP-UNC-DA41PL3C | F38: 3200 | J38: Installed - working | L38: Prop
B39: CP Plus | C39: 4 MP Dome IP Camera - CP Plus | E39: CP-UNC-DA41PL3C | F39: 3200 | J39: Installed - working | L39: Prop
B40: CP Plus | C40: 4 MP Dome IP Camera - CP Plus | E40: CP-UNC-DA41PL3C | F40: 3200 | J40: Installed - working | L40: Prop
B41: CP Plus | C41: 4 MP Dome IP Camera - CP Plus | E41: CP-UNC-DA41PL3C | F41: 3200 | J41: Installed - working | L41: Prop
B42: CP Plus | C42: 4 MP Dome IP Camera - CP Plus | E42: CP-UNC-DA41PL3C | F42: 3200 | J42: Installed - working | L42: Prop
B43: CP Plus | C43: 4 MP Dome IP Camera - CP Plus | E43: CP-UNC-DA41PL3C | F43: 3200 | J43: Installed - working | L43: Prop
B44: CP Plus | C44: 4 MP Dome IP Camera - CP Plus | E44: CP-UNC-DA41PL3C | F44: 3200 | J44: Installed - working | L44: Prop
... B47: CP Plus | C47: 4 MP Dome IP Camera - CP Plus | E47: CP-UNC-DA41PL3C | F47: 3200 | J47: Installed - working | L47: Prop
B48: CP Plus | C48: 4 MP Dome IP Camera - CP Plus | E48: CP-UNC-DA41PL3C | F48: 3200 | L48: Prop
B49: CP Plus | C49: 4 MP Dome IP Camera - CP Plus | E49: CP-UNC-DA41PL3C | F49: 3200 | L49: Prop
B50: CP Plus | C50: 4 MP Dome IP Camera - CP Plus | E50: CP-UNC-DA41PL3C | F50: 3200 | L50: Prop
B51: CP Plus | C51: 4 MP Dome IP Camera - CP Plus | E51: CP-UNC-DA41PL3C | F51: 3200 | L51: Prop
B52: CP Plus | C52: 4 MP Dome IP Camera - CP Plus | E52: CP-UNC-DA41PL3C | F52: 3200 | L52: Prop
B53: CP Plus | C53: 4 MP Dome IP Camera - CP Plus | E53: CP-UNC-DA41PL3C | F53: 3200 | L53: Prop
B54: CP Plus | C54: 4 MP Dome IP Camera - CP Plus | E54: CP-UNC-DA41PL3C | F54: 3200 | L54: Prop
B55: CP Plus | C55: 4 MP Dome IP Camera - CP Plus | E55: CP-UNC-DA41PL3C | F55: 3200 | L55: Prop
B56: CP Plus | C56: 4 MP Dome IP Camera - CP Plus | E56: CP-UNC-DA41PL3C | F56: 3200 | L56: Prop
B57: CP Plus | C57: 4 MP Dome IP Camera - CP Plus | E57: CP-UNC-DA41PL3C | F57: 3200 | L57: Prop
B58: CP Plus | C58: 4 MP Dome IP Camera - CP Plus | E58: CP-UNC-DA41PL3C | F58: 3200 | L58: Prop
B59: CP Plus | C59: 4 MP Dome IP Camera - CP Plus | E59: CP-UNC-DA41PL3C | F59: 3200 | L59: Prop
... B80: WBOX | C80: 8 TB Hard Disk - WD | E80: Nil | F80: 17980 | L80: Prop
A82: Wifi Access point | B82: TP Link | C82: Access Point Indoor EAP 610 - TP Link | E82: EAP 610 Indoor | F82: 9676 | L82: Prop
B83: TP Link | C83: Access Point Indoor EAP 610 - TP Link | E83: EAP 610 Indoor | F83: 9676 | L83: Prop
B84: TP Link | C84: Access Point Indoor EAP 610 - TP Link | E84: EAP 610 Indoor | F84: 9676 | L84: Prop
B85: TP Link | C85: Access Point Indoor EAP 610 - TP Link | E85: EAP 610 Indoor | F85: 9676 | L85: Prop
B86: TP Link | C86: 8 Port POE Switch (Gigabit) 2 Uplink SFP - TP Link | E86: TL-SG2210P | F86: 6372 | L86: Prop

Sheet Mahesh
B1: Client Name | C1: Mr. Mahesh | F1: Overall site status | J1: Count | K1: % | M1: Material status | N1: Count | O1: % | Q1: Visti No. | R1: IR No. | S1: Date
B2: Site | C2: NSN Palayam | F2: Yet to start | M2: Awaiting order request | Q2: 1 | R2: IR No.1515 | S2: 16.5.2025 | T2: Asok | U2: Sakthi
B3: Location | F3: Position marked - I | M3: To order material
B4: GPS Coordinates | F4: Piping done - C | M4: Ordered
B5: Architect | F5: Wiring done - C | M5: Recd (To test/config)
B6: Site Supervisor | F6: Wiring - Checked Ok - I | M6: Configured - ready for install
B7: Electrician | C7: Mr.Alwin | F7: Wiring rework reqd - C | M7: Delivered
B8: Electrical Contractor | F8: Provision not provided - C | M8: Provision only - Matl Not reqd
B9: Billing contact | F9: Position to be changed - C | M9: Failed - Picked up from site
B10: Carpenter | F10: Installed - working | M10: Failed - Need to service
B11: Civil Supervisor | F11: Installed - To activate - I | M11: Sent for service
B12: G-Drive Link | F12: Installed - Not working - IC | M12: Replaced/Serviced
B13: Mail id | F13: Door Ready - C | M13: Returned - Not reqd
B14: Site Engineer | F14: Door Not Ready - I
B16: Brand | C16: Product | D16: Serial No. | E16: Model No | F16: Sale Price | G16: Installation charge | H16: Location | I16: Drawing Ref No. | J16: Site status | K16: <--Date | L16: Prop/Addl | M16: Material | N16: <-- Date | O16: Client | P16: Inka | Q16: Comments | R16: SR Nos (If multiple - add all) | S16: DC
A17: Security Alarm System - Hikvision | B17: Hikvision | C17: Hikvision - Control Panel Wired Hybrid | E17: DS-PHA64-LP(B) | F17: 22150 | G17: 12500 | L17: Prop
B18: Hikvision | C18: Hikvision LCD Keypad | E18: LCD | F18: 6650 | L18: Prop
B19: Hikvision | C19: Hikvision IP Module | E19: IP Module | F19: 8450 | L19: Prop
B20: Hikvision | C20: Hikvision Door Sensor | E20: DS-PD1-MC-WWS(H) | F20: 450 | L20: Prop
B21: Hikvision | C21: Hikvision Door Sensor | E21: DS-PD1-MC-WWS(H) | F21: 450 | L21: Prop
B22: Hikvision | C22: Hikvision Door Sensor | E22: DS-PD1-MC-WWS(H) | F22: 450 | L22: Prop
B23: Hikvision | C23: Hikvision Door Sensor | E23: DS-PD1-MC-WWS(H) | F23: 450 | L23: Prop
B24: Hikvision | C24: Hikvision Door Sensor | E24: DS-PD1-MC-WWS(H) | F24: 450 | L24: Prop
B25: Hikvision | C25: Hikvision Door Sensor | E25: DS-PD1-MC-WWS(H) | F25: 450 | L25: Prop
B26: Hikvision | C26: Hikvision Door Sensor | E26: DS-PD1-MC-WWS(H) | F26: 450 | L26: Prop
C27: Glass Break Detector Wired (Digital) | E27: LC-105-DGB | F27: 3267 | L27: Prop
C28: Glass Break Detector Wired (Digital) | E28: LC-105-DGB | F28: 3267 | L28: Prop
C29: Glass Break Detector Wired (Digital) | E29: LC-105-DGB | F29: 3267 | L29: Prop
C30: Glass Break Detector Wired (Digital) | E30: LC-105-DGB | F30: 3267 | L30: Prop
C31: Glass Break Detector Wired (Digital) | E31: LC-105-DGB | F31: 3267 | L31: Prop
C32: Glass Break Detector Wired (Digital) | E32: LC-105-DGB | F32: 3267 | L32: Prop
C33: Glass Break Detector Wired (Digital) | E33: LC-105-DGB | F33: 3267 | L33: Prop
C34: Glass Break Detector Wired (Digital) | E34: LC-105-DGB | F34: 3267 | L34: Prop
C35: Power Supply | E35: Nil | F35: 1560 | L35: Prop
C36: Battery Backup | E36: 12V-7amp | F36: 1230 | L36: Prop
C37: Siren 15W | E37: SD15W | F37: 1100 | L37: Prop
A39: Video Door Phone System - Hikvision | B39: Hikvision | C39: VDP Outdoor Camera - Hikvision | E39: DS-KD8003-IME1/Surface | F39: 10600 | G39: 2413 | L39: Prop
B40: Hikvision | C40: VDP Outdoor Camera - Hikvision | E40: DS-KD8003-IME1/Surface | F40: 10600 | L40: Prop
B41: Hikvision | C41: VDP Indoor Monitor - Hikvision | E41: DS-KH6320-WTE1 | F41: 9780 | L41: Prop
C42: 4 Port POE Switch - Hikvision | E42: DS-3E0105P-E/M | F42: 3750 | L42: Prop
L43: Prop
A44: WIFI Access Point - TP Link | B44: TP Link | C44: Access Point EAP245 - TP Link | E44: EAP245 | F44: 8640 | G44: 2592 | L44: Prop
B45: TP Link | C45: Access Point EAP245 - TP Link | E45: EAP245 | F45: 8640 | L45: Prop
B46: TP Link | C46: Access Point EAP245 - TP Link | E46: EAP245 | F46: 8640 | L46: Prop

Sheet Priyadarshini
B1: Client Name | C1: Mrs. Priyadarshini | E1: 9842617176 | F1: Overall site status | J1: Count | K1: % | M1: Material status | N1: Count | O1: % | Q1: Visti No. | R1: IR No. | S1: Date
B2: Site | C2: Kalapatti | F2: Yet to start | M2: Awaiting order request | Q2: 1 | R2: IR No.1552 | S2: 23.4.2025 | U2: Sakthi
B3: Location | C3: https://www.google.com/maps/place/11%C2%B008'33.6%22N+77%C2%B002'25.9%22E/@11.1426611,77.0379524,17z/data=!3m1!4b1!4m4!3m3!8m2!3d11.1426611!4d77.0405273?hl=en&entry=ttu&g_ep=EgoyMDI1MDUwNy4wIKXMDSoASAFQAw%3D%3D | F3: Position marked - I | M3: To order material
B4: GPS Coordinates | F4: Piping done - C | M4: Ordered
B5: Architect | F5: Wiring done - C | M5: Recd (To test/config)
B6: Site Supervisor | F6: Wiring - Checked Ok - I | M6: Configured - ready for install
B7: Electrician | C7: Mr. Sultan | E7: 9487966241 | F7: Wiring rework reqd - C | M7: Delivered
B8: Electrical Contractor | F8: Provision not provided - C | M8: Provision only - Matl Not reqd
B9: Billing contact | F9: Position to be changed - C | M9: Failed - Picked up from site
B10: Carpenter | F10: Installed - working | M10: Failed - Need to service
B11: Civil Supervisor | F11: Installed - To activate - I | M11: Sent for service
B12: G-Drive Link | F12: Installed - Not working - IC | M12: Replaced/Serviced
B13: Mail id | F13: Door Ready - C | M13: Returned - Not reqd
B14: Site Engineer | F14: Door Not Ready - I
B16: Brand | C16: Product | D16: Serial No. | E16: Model No | F16: Sale Price | G16: Installation charge | H16: Location | I16: Drawing Ref No. | J16: Site status | K16: <--Date | L16: Prop/Addl | M16: Material | N16: <-- Date | O16: Client | P16: Inka | Q16: Comments | R16: SR Nos (If multiple - add all) | S16: DC

Sheet Mrs. Malarvizhi
B1: Client Name | C1: Mrs. Malarvizhi (New Lodge) | E1: 9487554943 | F1: Overall site status | J1: Count | K1: % | M1: Material status | N1: Count | O1: % | Q1: Visti No. | R1: IR No. | S1: Date
B2: Site | C2: Namakkal | D2: Mr. Udhaykumar | E2: 9940971333 | F2: Yet to start | M2: Awaiting order request
B3: Location | F3: Position marked - I | M3: To order material
B4: GPS Coordinates | F4: Piping done - C | M4: Ordered
B5: Architect | F5: Wiring done - C | M5: Recd (To test/config)
B6: Site Supervisor | F6: Wiring - Checked Ok - I | M6: Configured - ready for install
B7: Electrician | F7: Wiring rework reqd - C | M7: Delivered
B8: Electrical Contractor | F8: Provision not provided - C | M8: Provision only - Matl Not reqd
B9: Billing contact | F9: Position to be changed - C | M9: Failed - Picked up from site
B10: Carpenter | F10: Installed - working | M10: Failed - Need to service
B11: Civil Supervisor | F11: Installed - To activate - I | M11: Sent for service
B12: G-Drive Link | F12: Installed - Not working - IC | M12: Replaced/Serviced
B13: Mail id | F13: Door Ready - C | M13: Returned - Not reqd
B14: Site Engineer | F14: Door Not Ready - I
B16: Brand | C16: Product | D16: Serial No. | E16: Model No | F16: Sale Price | G16: Installation charge | H16: Location | I16: Drawing Ref No. | J16: Site status | K16: <--Date | L16: Prop/Addl | M16: Material | N16: <-- Date | O16: Client | P16: Inka | Q16: Comments | R16: SR Nos (If multiple - add all) | S16: DC
A17: Camera | B17: Prama Hikvision | C17: 4 MP Bullet IP Camera - Prama Hivision | E17: PT-NC140D3-IUF(D) | F17: 4750 | G17: 20000 | L17: Prop | M17: Delivered
B18: Prama Hikvision | C18: 4 MP Bullet IP Camera - Prama Hivision | E18: PT-NC140D3-IUF(D) | F18: 4750 | L18: Prop | M18: Delivered
B19: Prama Hikvision | C19: 4 MP Bullet IP Camera - Prama Hivision | E19: PT-NC140D3-IUF(D) | F19: 4750 | L19: Prop | M19: Delivered
B20: Prama Hikvision | C20: 4 MP Bullet IP Camera - Prama Hivision | E20: PT-NC140D3-IUF(D) | F20: 4750 | L20: Prop | M20: Delivered
B21: Prama Hikvision | C21: 4 MP Bullet IP Camera - Prama Hivision | E21: PT-NC140D3-IUF(D) | F21: 4750 | L21: Prop | M21: Delivered
B22: Prama Hikvision | C22: 4 MP Dome IP Camera Colour- Prama | E22: PT-NC143D3-LIU(D2) | F22: 4750 | L22: Prop | M22: Delivered
B23: Prama Hikvision | C23: 4 MP Dome IP Camera Colour- Prama | E23: PT-NC143D3-LIU(D2) | F23: 4750 | L23: Prop | M23: Delivered
B24: Prama Hikvision | C24: 4 MP Dome IP Camera Colour- Prama | E24: PT-NC143D3-LIU(D2) | F24: 4750 | L24: Prop | M24: Delivered
B25: Prama Hikvision | C25: 4 MP Dome IP Camera Colour- Prama | E25: PT-NC143D3-LIU(D2) | F25: 4750 | L25: Prop | M25: Delivered
B26: Prama Hikvision | C26: 4 MP Dome IP Camera Colour- Prama | E26: PT-NC143D3-LIU(D2) | F26: 4750 | L26: Prop | M26: Delivered
B27: Prama Hikvision | C27: 4 MP Dome IP Camera Colour- Prama | E27: PT-NC143D3-LIU(D2) | F27: 4750 | L27: Prop | M27: Delivered
B28: Prama Hikvision | C28: 4 MP Dome IP Camera Colour- Prama | E28: PT-NC143D3-LIU(D2) | F28: 4750 | L28: Prop | M28: Delivered
B29: Prama Hikvision | C29: 4 MP Dome IP Camera Colour- Prama | E29: PT-NC143D3-LIU(D2) | F29: 4750 | L29: Prop | M29: Delivered
... B37: TP Link | C37: 24 Port POE Switch (SG2428P) - TPlink | E37: SG2428P | F37: 24750 | L37: Prop | M37: Delivered
B38: Toshiba | C38: 8 TB Hard Disk | F38: 22500 | L38: Prop | M38: Delivered
C39: PVC (Hensel) Box | F39: 170 | L39: Prop | M39: Delivered
C40: PVC (Hensel) Box | F40: 170 | L40: Prop | M40: Delivered
C41: PVC (Hensel) Box | F41: 170 | L41: Prop | M41: Delivered
C42: PVC (Hensel) Box | F42: 170 | L42: Prop | M42: Delivered
C43: PVC (Hensel) Box | F43: 170 | L43: Prop | M43: Delivered
A45: Wifi | B45: TP Link | C45: Access Point EAP245 - TP Link | E45: EAP245 | F45: 9500 | G45: 8500 | L45: Prop | M45: Delivered
B46: TP Link | C46: Access Point EAP245 - TP Link | E46: EAP245 | F46: 9500 | L46: Prop | M46: Delivered
B47: TP Link | C47: Access Point EAP245 - TP Link | E47: EAP245 | F47: 9500 | L47: Prop | M47: Delivered
B48: TP Link | C48: Access Point EAP245 - TP Link | E48: EAP245 | F48: 9500 | L48: Prop | M48: Delivered
B49: TP Link | C49: Access Point EAP245 - TP Link | E49: EAP245 | F49: 9500 | L49: Prop | M49: Delivered
B50: TP Link | C50: Access Point EAP245 - TP Link | E50: EAP245 | F50: 9500 | L50: Prop | M50: Delivered
B51: TP Link | C51: Access Point EAP245 - TP Link | E51: EAP245 | F51: 9500 | L51: Prop | M51: Delivered
B52: TP Link | C52: Access Point EAP245 - TP Link | E52: EAP245 | F52: 9500 | L52: Prop | M52: Delivered
A54: AUDIO/ SYSTEMS | B54: Autozone | C54: Amplifier Beta3 BA160P | E54: BA160P | F54: 37892 | G54: 10000 | L54: Prop | M54: Delivered
B55: JBL | C55: Ceiling Speakers - JBL | E55: JBL 8124 | F55: 3610 | L55: Prop | M55: Delivered
B56: JBL | C56: Ceiling Speakers - JBL | E56: JBL 8124 | F56: 3610 | L56: Prop | M56: Delivered
B57: JBL | C57: Ceiling Speakers - JBL | E57: JBL 8124 | F57: 3610 | L57: Prop | M57: Delivered
B58: JBL | C58: Ceiling Speakers - JBL | E58: JBL 8124 | F58: 3610 | L58: Prop | M58: Delivered
B59: JBL | C59: Ceiling Speakers - JBL | E59: JBL 8124 | F59: 3610 | L59: Prop | M59: Delivered
B60: JBL | C60: Ceiling Speakers - JBL | E60: JBL 8124 | F60: 3610 | L60: Prop | M60: Delivered
B61: JBL | C61: Ceiling Speakers - JBL | E61: JBL 8124 | F61: 3610 | L61: Prop | M61: Delivered
B62: JBL | C62: Ceiling Speakers - JBL | E62: JBL 8124 | F62: 3610 | L62: Prop | M62: Delivered
A64: security system | B64: Ravel | C64: Ravel Fire Panel | E64: REFRE2558 | F64: 21560 | L64: Prop | M64: Delivered
B65: Ravel | C65: Ravel Smoke Detector | E65: REFRE3262SL | F65: 1350 | L65: Prop | M65: Delivered
B66: Ravel | C66: Ravel Smoke Detector | E66: REFRE3262SL | F66: 1350 | L66: Prop | M66: Delivered
B67: Ravel | C67: Ravel Smoke Detector | E67: REFRE3262SL | F67: 1350 | L67: Prop | M67: Delivered
B68: Ravel | C68: Ravel Smoke Detector | E68: REFRE3262SL | F68: 1350 | L68: Prop | M68: Delivered
B69: Ravel | C69: Ravel Smoke Detector | E69: REFRE3262SL | F69: 1350 | L69: Prop | M69: Delivered
B70: Ravel | C70: Ravel Smoke Detector | E70: REFRE3262SL | F70: 1350 | L70: Prop | M70: Delivered
B71: Ravel | C71: Ravel Smoke Detector | E71: REFRE3262SL | F71: 1350 | L71: Prop | M71: Delivered
B72: Ravel | C72: Ravel Smoke Detector | E72: REFRE3262SL | F72: 1350 | L72: Prop | M72: Delivered
B73: Ravel | C73: Smoke Response Indicator | E73: REFRERIP | F73: 250 | L73: Prop | M73: Delivered
B74: Ravel | C74: Smoke Response Indicator | E74: REFRERIP | F74: 250 | L74: Prop | M74: Delivered
B75: Ravel | C75: Smoke Response Indicator | E75: REFRERIP | F75: 250 | L75: Prop | M75: Delivered
B76: Ravel | C76: Smoke Response Indicator | E76: REFRERIP | F76: 250 | L76: Prop | M76: Delivered
... B80: Ravel | C80: Smoke Response Indicator | E80: REFRERIP | F80: 250 | L80: Prop | M80: Delivered
L81: Prop | M81: Delivered
L82: Prop | M82: Delivered
L83: Prop | M83: Delivered
L84: Prop | M84: Delivered
L85: Prop | M85: Delivered
L86: Prop | M86: Delivered
L87: Prop | M87: Delivered
L88: Prop | M88: Delivered
L89: Prop | M89: Delivered
L90: Prop | M90: Delivered

Sheet Palanichamy
B1: Client Name | C1: Mr. Palanichamy | E1: 98942 69494 | F1: Overall site status | J1: Count | K1: % | M1: Material status | N1: Count | O1: % | Q1: Visti No. | R1: IR No. | S1: Date
B2: Site | C2: Kalapatti | F2: Yet to start | M2: Awaiting order request | Q2: 1 | S2: 20.5.2025 | T2: Site visit | U2: Asok & Fabricator
B3: Location | F3: Position marked - I | M3: To order material | Q3: 2 | R3: IR No.1353 | S3: 2.6.2025 | T3: Site visit | U3: Asok
B4: GPS Coordinates | F4: Piping done - C | M4: Ordered | Q4: 3 | R4: IR No.1355 | S4: 3.6.2025 | T4: Installation | U4: Asok + Fabricator
B5: Architect | F5: Wiring done - C | M5: Recd (To test/config) | Q5: 4 | S5: 5.6.2025 | T5: Installation | U5: Asok + Fabricator
B6: Site Supervisor | F6: Wiring - Checked Ok - I | M6: Configured - ready for install | Q6: 5 | S6: 9.6.2025 | T6: Installation | U6: Asok
B7: Electrician | F7: Wiring rework reqd - C | M7: Delivered | Q7: 6 | S7: 10.6.2025 | T7: Installation | U7: Asok
B8: Electrical Contractor | F8: Provision not provided - C | M8: Provision only - Matl Not reqd | Q8: 7 | S8: 11.6.2025 | T8: Installation | U8: Asok
B9: Billing contact | F9: Position to be changed - C | M9: Failed - Picked up from site | Q9: 8 | S9: 21.6.2025 | T9: Program | U9: Asok
B10: Carpenter | F10: Installed - working | M10: Failed - Need to service | Q10: 9 | R10: IR No.214 | S10: 23.6.2025 | T10: Program | U10: Asok
B11: Civil Supervisor | F11: Installed - To activate - I | M11: Sent for service | Q11: 10 | R11: IR No.212 | S11: 26.6.2025 | T11: Program | U11: Asok
B12: G-Drive Link | F12: Installed - Not working - IC | M12: Replaced/Serviced | Q12: 11 | R12: IR No.1520 | S12: 8.7.2025 | T12: Service | U12: Asok
B13: Mail id | F13: Door Ready - C | M13: Returned - Not reqd | Q13: 12 | R13: IR No.1404 | S13: 12.7.2025 | T13: Service | U13: Asok
B14: Site Engineer | C14: Mr. Naveen | E14: 9655296503 | F14: Door Not Ready - I
B16: Brand | C16: Product | D16: Serial No. | E16: Model No | F16: Sale Price | G16: Installation charge | H16: Location | I16: Drawing Ref No. | J16: Site status | K16: <--Date | L16: Prop/Addl | M16: Material | N16: <-- Date | O16: Client | P16: Inka | Q16: Comments | R16: SR Nos (If multiple - add all) | S16: DC
A17: Gate Automation | B17: Autozone | C17: Swing Gate operator | E17: AZ - SW-107Kit | F17: 60385 | G17: 8500 | J17: Installed-working | K17: 3.6.2025 | L17: Prop | M17: Delivered | N17: 24.5.2025 | R17: IR No.1355 | S17: 43
C18: Sliding gate track ss drilled surface fixing | E18: AZTSS20A | F18: 6409 | L18: Prop
C19: ROATATING BEARING SS WHEEL WITH SPRING | E19: AZRWU60R20SS | F19: 4993 | L19: Prop
C20: ROATATING BEARING SS WHEEL WITH SPRING | E20: AZRWU60R20SS | F20: 4993 | L20: Prop
C21: Electrical materials | F21: 6500 | L21: Prop
C22: Fabrication materials | F22: 10250 | L22: Prop
C23: Fabrication labour | G23: 10300 | L23: Prop
C24: Electrician labour | G24: 4300 | L24: Prop
C25: MS ANGLE40X6 10FT | J25: Installed-working | K25: 23.6.2025 | L25: Prop | M25: Delivered | N25: 21.5.2025 | R25: IR No.214 | S25: 36
C26: MS ANGLE40X6 10FT | J26: Installed-working | K26: 23.6.2025 | L26: Prop | M26: Delivered | N26: 21.5.2025 | R26: IR No.214 | S26: 36
C27: MS ROD 10 FT | J27: Installed-working | K27: 23.6.2025 | L27: Prop | M27: Delivered | N27: 21.5.2025 | R27: IR No.214 | S27: 36
C28: MS ROD 10 FT | J28: Installed-working | K28: 23.6.2025 | L28: Prop | M28: Delivered | N28: 21.5.2025 | R28: IR No.214 | S28: 36
C29: 3.5 MM SLINDING WHEEL | J29: Installed-working | K29: 23.6.2025 | L29: Prop | M29: Delivered | N29: 21.5.2025 | R29: IR No.214 | S29: 36
C30: BI FOLDING DOUBLE BEARING SS HINGS(38MM) | J30: Installed-working | K30: 23.6.2025 | M30: Delivered | N30: 18.6.2025 | R30: IR No.214 | S30: 36
C31: BI FOLDING DOUBLE BEARING SS HINGS(38MM) | J31: Installed-working | K31: 23.6.2025 | M31: Delivered | N31: 18.6.2025 | R31: IR No.214 | S31: 69
C32: BI FOLDING DOUBLE BEARING SS HINGS(38MM) | J32: Installed-working | K32: 23.6.2025 | M32: Delivered | N32: 18.6.2025 | R32: IR No.214 | S32: 69
C33: BI FOLDING DOUBLE BEARING SS HINGS(38MM) | J33: Installed-working | K33: 23.6.2025 | M33: Delivered | N33: 18.6.2025 | R33: IR No.214 | S33: 69
C34: BI FOLDING DOUBLE BEARING SS HINGS(38MM) | J34: Installed-working | K34: 23.6.2025 | M34: Delivered | N34: 18.6.2025 | R34: IR No.214 | S34: 69
C35: S.S FITTING - 73072900 bearing rotating wheel 58 mm R20 | J35: Installed-working | K35: 23.6.2025 | M35: Delivered | N35: 18.6.2025 | R35: IR No.214 | S35: 69
C36: S.S FITTING - 73072900 bearing rotating wheel 58 mm R20 | J36: Installed-working | K36: 23.6.2025 | M36: Delivered | N36: 18.6.2025 | R36: IR No.214 | S36: 69
J37: Installed-working | K37: 23.6.2025 | R37: IR No.214

Sheet Mr. Manohar
B1: Client Name | C1: Mr. Manohar | D1: Mrs.Rithika Manohar | E1: 9842256656 | F1: Overall site status | J1: Count | K1: % | M1: Material status | N1: Count | O1: % | Q1: Visti No. | R1: IR No. | S1: Date
B2: Site | C2: Sulur | E2: 9865402211 | F2: Yet to start | M2: Awaiting order request | Q2: 1 | R2: IR No.1487 | S2: 6.5.2025 | T2: 1st site visit | U2: Kumaraguru
B3: Location | F3: Position marked - I | M3: To order material | Q3: 2 | R3: IR No.1413 | S3: 26.7.2025 | T3: site visit | U3: Sakthi
B4: GPS Coordinates | F4: Piping done - C | M4: Ordered | Q4: 3 | R4: IR No.237 | S4: 29.7.2025 | T4: Pipe checking | U4: Kumaraguru
B5: Architect | F5: Wiring done - C | M5: Recd (To test/config)
B6: Site Supervisor | C6: Mr. Prabhu | F6: Wiring - Checked Ok - I | M6: Configured - ready for install
B7: Electrician | C7: Mr. Murali | E7: 8870249650 | F7: Wiring rework reqd - C | M7: Delivered
B8: Electrical Contractor | F8: Provision not provided - C | M8: Provision only - Matl Not reqd
B9: Billing contact | F9: Position to be changed - C | M9: Failed - Picked up from site
B10: Carpenter | F10: Installed - working | M10: Failed - Need to service
B11: Civil Supervisor | F11: Installed - To activate - I | M11: Sent for service
B12: G-Drive Link | F12: Installed - Not working - IC | M12: Replaced/Serviced
B13: Mail id | F13: Door Ready - C | M13: Returned - Not reqd
B14: Site Engineer | F14: Door Not Ready - I
B16: Brand | C16: Product | D16: Serial No. | E16: Model No | F16: Sale Price | G16: Installation charge | H16: Location | I16: Drawing Ref No. | J16: Site status | K16: <--Date | L16: Prop/Addl | M16: Material | N16: <-- Date | O16: Client | P16: Inka | Q16: Comments | R16: SR Nos (If multiple - add all) | S16: DC
A17: Camera | B17: Prama | C17: 4 Mp Bullet IP Camera Colour/InbuiltMic - Prama | E17: PT-NC140D3LIU(D2) | F17: 4750 | G17: 9469 | H17: GF | I17: A01C | J17: Piping done - C | K17: 45813 | L17: Prop | M17: Awaiting order request | R17: 237
B18: Prama | C18: 4 Mp Bullet IP Camera Colour/InbuiltMic - Prama | E18: PT-NC140D3LIU(D2) | F18: 4750 | H18: GF | I18: A02C | J18: Piping done - C | K18: 45813 | L18: Prop | M18: Awaiting order request | R18: 237
B19: Prama | C19: 4 Mp Bullet IP Camera Colour/InbuiltMic - Prama | E19: PT-NC140D3LIU(D2) | F19: 4750 | H19: GF | I19: A03C | J19: Piping done - C | K19: 45813 | L19: Prop | M19: Awaiting order request | R19: 237
B20: Prama | C20: 4 Mp Bullet IP Camera Colour/InbuiltMic - Prama | E20: PT-NC140D3LIU(D2) | F20: 4750 | H20: GF | I20: A04C | J20: Piping done - C | K20: 45813 | L20: Prop | M20: Awaiting order request | R20: 237
B21: Prama | C21: 4 Mp Bullet IP Camera Colour/InbuiltMic - Prama | E21: PT-NC140D3LIU(D2) | F21: 4750 | H21: GF | I21: A05C | J21: Piping done - C | K21: 45813 | L21: Prop | M21: Awaiting order request | R21: 237
B22: Prama | C22: 4 Mp Bullet IP Camera Colour/InbuiltMic - Prama | E22: PT-NC140D3LIU(D2) | F22: 4750 | H22: GF | I22: A06C | J22: Piping done - C | K22: 45813 | L22: Prop | M22: Awaiting order request | R22: 237
B23: Prama | C23: 4 Mp Bullet IP Camera Colour/InbuiltMic - Prama | E23: PT-NC140D3LIU(D2) | F23: 4750 | H23: GF | I23: A07C | J23: Piping done - C | K23: 45813 | L23: Prop | M23: Awaiting order request | R23: 237
B24: Prama | C24: 4 Mp Bullet IP Camera Colour/InbuiltMic - Prama | E24: PT-NC140D3LIU(D2) | F24: 4750 | H24: GF | I24: A08C | J24: Piping done - C | K24: 45813 | L24: Prop | M24: Awaiting order request | R24: 237
B25: Prama | C25: 4 Mp Bullet IP Camera Colour/InbuiltMic - Prama | E25: PT-NC140D3LIU(D2) | F25: 4750 | H25: GF | I25: A09C | J25: Piping done - C | K25: 45813 | L25: Prop | M25: Awaiting order request | R25: 237
B26: Prama | C26: 4 Mp Bullet IP Camera Colour/InbuiltMic - Prama | E26: PT-NC140D3LIU(D2) | F26: 4750 | H26: FF | I26: A10C | J26: Piping done - C | K26: 45813 | L26: Prop | M26: Awaiting order request | R26: 237
B27: Prama | C27: 4 Mp Bullet IP Camera Colour/InbuiltMic - Prama | E27: PT-NC140D3LIU(D2) | F27: 4750 | H27: FF | I27: A12C | J27: Piping done - C | K27: 45813 | L27: Prop | M27: Awaiting order request | R27: 237
B28: Prama | C28: 4 Mp Bullet IP Camera Colour/InbuiltMic - Prama | E28: PT-NC140D3LIU(D2) | F28: 4750 | H28: FF-Optional | I28: A13C | J28: Piping done - C
B29: Prama | C29: 4 Mp Bullet IP Camera Colour/InbuiltMic - Prama | E29: PT-NC140D3LIU(D2) | F29: 4750 | H29: SF-Optional | I29: A11C | J29: Piping done - C
B30: Prama | C30: 4 Mp Bullet IP Camera Colour/InbuiltMic - Prama | E30: PT-NC140D3LIU(D2) | F30: 4750 | H30: SF-Optional | I30: A14C | J30: Piping done - C
B31: Hikvision | C31: 16 channel NVR (K2) - Hikvision | E31: DS-7616NI-K2 | F31: 14580 | J31: Piping done - C | K31: 45813 | L31: Prop | M31: Awaiting order request | R31: 237
B32: Toshiba | C32: 4 TB Hard Disk - Toshiba | E32: AVHDDS300 | F32: 8160 | J32: Piping done - C | K32: 45813 | L32: Prop | M32: Awaiting order request | R32: 237
B33: TP Link | C33: 8 Port POE Switch (Gigabit) 2 Uplink SFP - TP Link | E33: TL-SG2210P | F33: 8250 | J33: Piping done - C | K33: 45813 | L33: Prop | M33: Awaiting order request | R33: 237
B34: TP Link | C34: 8 Port POE Switch (Gigabit) 2 Uplink SFP - TP Link | E34: TL-SG2210P | F34: 8250 | J34: Piping done - C | K34: 45813 | L34: Prop | M34: Awaiting order request | R34: 237
C35: Camera Accessories | F35: 3200 | J35: Piping done - C | K35: 45813 | L35: Prop | M35: Awaiting order request | R35: 237
A37: Security system | B37: Hikvision | C37: Hikvision - Control Panel Hybrid | E37: DS-PHA64-LP(B) | F37: 29500 | G37: 10492 | J37: Piping done - C | K37: 45813 | L37: Prop | M37: Awaiting order request | R37: 237
B38: Hikvision | C38: Hikvision - GSM module | E38: DS-PM2-S | F38: 9773 | J38: Piping done - C | K38: 45813 | L38: Prop | M38: Awaiting order request | R38: 237
B39: Hikvision | C39: Hikvision IP Module | E39: IP Module | F39: 8450 | J39: Piping done - C | K39: 45813 | L39: Prop | M39: Awaiting order request | R39: 237
B40: Hikvision | C40: Hikvision - Wired LCD Keypad | E40: DS-PICI-LRT-HWB | F40: 7237 | J40: Piping done - C | K40: 45813 | L40: Prop | M40: Awaiting order request | R40: 237
B41: Hikvision | C41: Hikvision Door Sensor | E41: DS-PD1-MC-WWS(H) | F41: 450 | J41: Piping done - C | K41: 45813 | L41: Prop | M41: Awaiting order request | R41: 237
B42: Hikvision | C42: Hikvision Door Sensor | E42: DS-PD1-MC-WWS(H) | F42: 450 | J42: Piping done - C | K42: 45813 | L42: Prop | M42: Awaiting order request | R42: 237
B43: Hikvision | C43: Hikvision Door Sensor | E43: DS-PD1-MC-WWS(H) | F43: 450 | J43: Piping done - C | K43: 45813 | L43: Prop | M43: Awaiting order request | R43: 237
B44: Hikvision | C44: Hikvision Door Sensor | E44: DS-PD1-MC-WWS(H) | F44: 450 | J44: Piping done - C | K44: 45813 | L44: Prop | M44: Awaiting order request | R44: 237
B45: Hikvision | C45: Hikvision Door Sensor | E45: DS-PD1-MC-WWS(H) | F45: 450 | J45: Piping done - C | K45: 45813 | L45: Prop | M45: Awaiting order request | R45: 237
B46: Hikvision | C46: Hikvision Door Sensor | E46: DS-PD1-MC-WWS(H) | F46: 450 | J46: Piping done - C | K46: 45813 | L46: Prop | M46: Awaiting order request | R46: 237
C47: Glass Break Detector Wired (Digital) | E47: LC-105-DGB | F47: 3267 | J47: Piping done - C | K47: 45813 | L47: Prop | M47: Awaiting order request | R47: 237
C48: Glass Break Detector Wired (Digital) | E48: LC-105-DGB | F48: 3267 | J48: Piping done - C | K48: 45813 | L48: Prop | M48: Awaiting order request | R48: 237
C49: Glass Break Detector Wired (Digital) | E49: LC-105-DGB | F49: 3267 | J49: Piping done - C | K49: 45813 | L49: Prop | M49: Awaiting order request | R49: 237
C50: Glass Break Detector Wired (Digital) | E50: LC-105-DGB | F50: 3267 | J50: Piping done - C | K50: 45813 | L50: Prop | M50: Awaiting order request | R50: 237
C51: Glass Break Detector Wired (Digital) | E51: LC-105-DGB | F51: 3267 | J51: Piping done - C | K51: 45813 | L51: Prop | M51: Awaiting order request | R51: 237
C52: Glass Break Detector Wired (Digital) | E52: LC-105-DGB | F52: 3267 | J52: Piping done - C | K52: 45813 | L52: Prop | M52: Awaiting order request | R52: 237
C53: Glass Break Detector Wired (Digital) | E53: LC-105-DGB | F53: 3267 | J53: Piping done - C | K53: 45813 | L53: Prop | M53: Awaiting order request | R53: 237
C54: Glass Break Detector Wired (Digital) | E54: LC-105-DGB | F54: 3267 | J54: Piping done - C | K54: 45813 | L54: Prop | M54: Awaiting order request | R54: 237
C55: Glass Break Detector Wired (Digital) | E55: LC-105-DGB | F55: 3267 | J55: Piping done - C | K55: 45813 | L55: Prop | M55: Awaiting order request | R55: 237
C56: Glass Break Detector Wired (Digital) | E56: LC-105-DGB | F56: 3267 | J56: Piping done - C | K56: 45813 | L56: Prop | M56: Awaiting order request | R56: 237
C57: Glass Break Detector Wired (Digital) | E57: LC-105-DGB | F57: 3267 | J57: Piping done - C | K57: 45813 | L57: Prop | M57: Awaiting order request | R57: 237
C58: Wired 8 Zone Expander | E58: M-IN/OUT | F58: 6640 | J58: Piping done - C | K58: 45813 | L58: Prop | M58: Awaiting order request | R58: 237
B59: Hikvision | C59: Hikvision - Wired Siren | E59: DS 109 | F59: 2434 | J59: Piping done - C | K59: 45813 | L59: Prop | M59: Awaiting order request | R59: 237
C60: Battery Backup | E60: 12V-7amp | F60: 2240 | J60: Piping done - C | K60: 45813 | L60: Prop | M60: Awaiting order request | R60: 237
A62: Video Door Phone System - Hikvision | B62: Hikvision | C62: VDP Outdoor Camera - Hikvision | E62: DS-KD8003-IME1/Surface | F62: 11600 | G62: 3900 | H62: GF | I62: A20V | J62: Piping done - C
B63: Hikvision | C63: VDP Indoor Monitor - Hikvision | E63: DS-KH6320-WTE1 | F63: 10480 | J63: Piping done - C
A65: Wifi | B65: TP Link | C65: Access Point | E65: EAP245 | F65: 8850 | G65: 4350 | H65: SF | I65: A16A | J65: Piping done - C
B66: TP Link | C66: Access Point | E66: EAP245 | F66: 8850 | H66: FF | I66: A17A | J66: Piping done - C
B67: TP Link | C67: Access Point | E67: EAP245 | F67: 8850 | H67: FF | I67: A18A | J67: Piping done - C
B68: TP Link | C68: Access Point | E68: EAP245 | F68: 8850 | H68: GF | I68: A19A | J68: Piping done - C
C69: 8 Port POE Switch (Gigabit) 2 Uplink SFP - TP Lin | E69: TL-SG2210P | F69: 8100 | H69: GF | J69: Piping done - C

Sheet Erode Villa - Mrs. Vinothini
B1: Client Name | C1: Erode Villa - Mrs. Vinothini | F1: Overall site status | J1: Count | K1: % | M1: Material status | N1: Count | O1: % | Q1: Visti No. | R1: IR No. | S1: Date
B2: Site | C2: Erode | F2: Yet to start | M2: Awaiting order request | Q2: 1 | R2: IR No.1552 | S2: 23.4.2025 | U2: Sakthi
B3: Location | F3: Position marked - I | M3: To order material
B4: GPS Coordinates | F4: Piping done - C | M4: Ordered
B5: Architect | F5: Wiring done - C | M5: Recd (To test/config)
B6: Site Supervisor | F6: Wiring - Checked Ok - I | M6: Configured - ready for install
B7: Electrician | F7: Wiring rework reqd - C | M7: Delivered
B8: Electrical Contractor | F8: Provision not provided - C | M8: Provision only - Matl Not reqd
B9: Billing contact | F9: Position to be changed - C | M9: Failed - Picked up from site
B10: Carpenter | F10: Installed - working | M10: Failed - Need to service
B11: Civil Supervisor | F11: Installed - To activate - I | M11: Sent for service
B12: G-Drive Link | F12: Installed - Not working - IC | M12: Replaced/Serviced
B13: Mail id | F13: Door Ready - C | M13: Returned - Not reqd
B14: Site Engineer | F14: Door Not Ready - I
B16: Brand | C16: Product | D16: Serial No. | E16: Model No | F16: Sale Price | G16: Installation charge | H16: Location | I16: Drawing Ref No. | J16: Site status | K16: <--Date | L16: Prop/Addl | M16: Material | N16: <-- Date | O16: Client | P16: Inka | Q16: Comments | R16: SR Nos (If multiple - add all) | S16: DC

Sheet Gunasekar-Kalapatti
B1: Client Name | C1: Mr. Gunasekar | F1: Overall site status | J1: Count | K1: % | M1: Material status | N1: Count | O1: % | Q1: Visti No. | R1: IR No. | S1: Date
B2: Site | C2: Kalapatti | F2: Yet to start | M2: Awaiting order request | Q2: 1 | R2: IR No.1382 | S2: 9.10.2024 | T2: Pipe checking in MBR | U2: Sakthi
B3: Location | F3: Position marked - I | M3: To order material | Q3: 2 | R3: IR No.1388 | S3: 19.10.2024 | U3: Sakthi
B4: GPS Coordinates | F4: Piping done - C | M4: Ordered
B5: Architect | F5: Wiring done - C | M5: Recd (To test/config)
B6: Site Supervisor | F6: Wiring - Checked Ok - I | M6: Configured - ready for install
B7: Electrician | F7: Wiring rework reqd - C | M7: Delivered
B8: Electrical Contractor | F8: Provision not provided - C | M8: Provision only - Matl Not reqd
B9: Billing contact | F9: Position to be changed - C | M9: Failed - Picked up from site
B10: Carpenter | F10: Installed - working | M10: Failed - Need to service
B11: Civil Supervisor | F11: Installed - To activate - I | M11: Sent for service
B12: G-Drive Link | F12: Installed - Not working - IC | M12: Replaced/Serviced
B13: Mail id | F13: Door Ready - C | M13: Returned - Not reqd
B14: Site Engineer | F14: Door Not Ready - I
B16: Brand | C16: Product | D16: Serial No. | E16: Model No | F16: Sale Price | G16: Installation charge | H16: Location | I16: Drawing Ref No. | J16: Site status | K16: <--Date | L16: Prop/Addl | M16: Material | N16: <-- Date | O16: Client | P16: Inka | Q16: Comments | R16: SR Nos (If multiple - add all) | S16: DC
A17: camera | B17: Parma | C17: 4 Mp Bullet IP Camera Colour/InbuiltMic - Prama | E17: PT-NC140D3LIU(D2) | F17: 3440 | G17: 9450 | H17: FF | I17: A23C | L17: Prop | M17: Awaiting order request | O17: 3M Box fixing work
B18: Parma | C18: 4 Mp Bullet IP Camera Colour/InbuiltMic - Prama | E18: PT-NC140D3LIU(D2) | F18: 3440 | H18: FF | I18: A24C | L18: Prop | M18: Awaiting order request | O18: 3M Box fixing work
B19: Parma | C19: 4 Mp Bullet IP Camera Colour/InbuiltMic - Prama | E19: PT-NC140D3LIU(D2) | F19: 3440 | H19: GF | I19: A09C | L19: Prop | M19: Awaiting order request | O19: 3M Box fixing work | R19: IR No.1388
B20: Parma | C20: 4 Mp Bullet IP Camera Colour/InbuiltMic - Prama | E20: PT-NC140D3LIU(D2) | F20: 3440 | H20: GF | I20: A08C | L20: Prop | M20: Awaiting order request | O20: 3M Box fixing work | R20: IR No.1388
B21: Parma | C21: 4 Mp Bullet IP Camera Colour/InbuiltMic - Prama | E21: PT-NC140D3LIU(D2) | F21: 3440 | H21: GF | I21: A07C | L21: Prop | M21: Awaiting order request | O21: 3M Box fixing work | R21: IR No.1388
B22: Parma | C22: 4 Mp Bullet IP Camera Colour/InbuiltMic - Prama | E22: PT-NC140D3LIU(D2) | F22: 3440 | H22: GF | I22: A06C | L22: Prop | M22: Awaiting order request | O22: 3M Box fixing work | R22: IR No.1388
B23: Parma | C23: 4 Mp Bullet IP Camera Colour/InbuiltMic - Prama | E23: PT-NC140D3LIU(D2) | F23: 3440 | H23: GF | I23: A05C | L23: Prop | M23: Awaiting order request | O23: 3M Box fixing work | R23: IR No.1388
B24: Parma | C24: 4 Mp Bullet IP Camera Colour/InbuiltMic - Prama | E24: PT-NC140D3LIU(D2) | F24: 3440 | H24: GF | I24: A04C | L24: Prop | M24: Awaiting order request | O24: 3M Box fixing work | R24: IR No.1388
B25: Parma | C25: 4 Mp Bullet IP Camera Colour/InbuiltMic - Prama | E25: PT-NC140D3LIU(D2) | F25: 3440 | H25: GF | I25: A03C | L25: Prop | M25: Awaiting order request | O25: 3M Box fixing work | R25: IR No.1388
B26: Parma | C26: 4 Mp Bullet IP Camera Colour/InbuiltMic - Prama | E26: PT-NC140D3LIU(D2) | F26: 3440 | H26: GF | I26: A02C | L26: Prop | M26: Awaiting order request | O26: 3M Box fixing work | R26: IR No.1388
B27: Parma | C27: 4 Mp Bullet IP Camera Colour/InbuiltMic - Prama | E27: PT-NC140D3LIU(D2) | F27: 3440 | H27: GF | I27: A01C | L27: Prop | M27: Awaiting order request | O27: 3M Box fixing work
B28: Parma | C28: 4 Mp Bullet IP Camera Colour/InbuiltMic - Prama | E28: PT-NC140D3LIU(D2) | I28: A11C | M28: Awaiting order request | O28: 3M Box fixing work
B29: Parma | C29: 4 Mp Bullet IP Camera Colour/InbuiltMic - Prama | E29: PT-NC140D3LIU(D2) | I29: A10C | M29: Awaiting order request | O29: 3M Box fixing work
B30: Hikvision | C30: 16 channel NVR (K2) | E30: DS-7616NI-K2 | F30: 11780 | L30: Prop | M30: Awaiting order request
B31: TP Link | C31: 16 Port POE Gigabit Switch (TL-SG1218MPE) | E31: TL-SG1218MPE | F31: 16520 | L31: Prop | M31: Awaiting order request
B32: Toshiba | C32: 4 TB Hard Disk | E32: AVHDDS300 | F32: 8160 | L32: Prop | M32: Awaiting order request
A34: Video Door Phone System - Hikvision | B34: Hikvision | C34: VDP Outdoor Camera | E34: DS-KD8003-IME1/Surface | F34: 10600 | G34: 5450 | H34: GF | I34: A15V | L34: Prop | M34: Awaiting order request | R34: IR No.1388
B35: Hikvision | C35: VDP Outdoor Camera | E35: DS-KD8003-IME1/Surface | F35: 10600 | H35: GF | I35: A16V | L35: Prop | M35: Awaiting order request | R35: IR No.1388
B36: Hikvision | C36: VDP Indoor Monitor | E36: DS-KH6320-WTE1 | F36: 9480 | H36: GF | I36: A14V | L36: Prop | M36: Awaiting order request | R36: IR No.1388
B37: Hikvision | C37: VDP Indoor Monitor | E37: DS-KH6320-WTE1 | F37: 9480 | H37: FF | I37: A22V | L37: Prop | M37: Awaiting order request
A39: WIFI Access Point - TP Link | B39: TP Link | C39: Access Point EAP245 | E39: EAP245 | F39: 8240 | G39: 9450 | H39: FF | I39: A21A | L39: Prop | M39: Awaiting order request
B40: TP Link | C40: Access Point EAP245 | E40: EAP245 | F40: 8240 | H40: SF | I40: A25A | L40: Prop | M40: Awaiting order request
B41: TP Link | C41: Access Point EAP245 | E41: EAP245 | F41: 8240 | H41: FF | I41: A20A | L41: Prop | M41: Awaiting order request
B42: TP Link | C42: Access Point EAP245 | E42: EAP245 | F42: 8240 | H42: FF | I42: A19A | L42: Prop | M42: Awaiting order request
B43: TP Link | C43: Access Point EAP245 | E43: EAP245 | F43: 8240 | H43: FF | I43: A18A | L43: Prop | M43: Awaiting order request
B44: TP Link | C44: Access Point EAP245 | E44: EAP245 | F44: 8240 | H44: FF | I44: A17A | L44: Prop | M44: Awaiting order request
B45: TP Link | C45: Access Point EAP245 | E45: EAP245 | F45: 8240 | H45: GF | I45: A13A | L45: Prop | M45: Awaiting order request | R45: IR No.1388
B46: TP Link | C46: Access Point EAP245 | E46: EAP245 | F46: 8240 | H46: GF | I46: A12A | L46: Prop | M46: Awaiting order request | R46: IR No.1388
B47: TP Link | C47: Access Point EAP245 | E47: EAP245 | F47: 8240 | H47: GF | I47: A11A | L47: Prop | M47: Awaiting order request | R47: IR No.1388
B48: TP Link | C48: Access Point EAP245 | E48: EAP245 | F48: 8240 | H48: GF | I48: A10A | L48: Prop | M48: Awaiting order request | R48: IR No.1388
B49: TP Link | C49: 16 Port POE Gigabit Switch (TL-SG1218MPE) - TP Link | E49: TL-SG1218MPE | F49: 16650
A51: Security Alarm System | B51: DSC | C51: DSC - Control Panel | E51: HS2128CE | F51: 31782 | G51: 15650 | H51: GF | L51: Prop | M51: Awaiting order request | R51: IR No.1388
B52: DSC | C52: DSC - LCD Keypad Kit | E52: HS2LCDS | F52: 6300 | L52: Prop | M52: Awaiting order request | O52: 2M box need to fix
B53: DSC | C53: DSC - IP Module | E53: TL280E | F53: 9780 | L53: Prop | M53: Awaiting order request
B54: DSC | C54: Panic Switch DSC | F54: 2140 | L54: Prop | M54: Awaiting order request
B55: DSC | C55: Panic Switch DSC | F55: 2140 | L55: Prop | M55: Awaiting order request
B56: DSC | C56: Panic Switch DSC | F56: 2140 | L56: Prop | M56: Awaiting order request
B57: DSC | C57: Panic Switch DSC | F57: 2140 | L57: Prop | M57: Awaiting order request
B58: DSC | C58: Panic Switch DSC | F58: 2140 | L58: Prop | M58: Awaiting order request
B59: Securico | C59: Door Sensor (Mag) - Wired | E59: SEC-MSC | F59: 450 | H59: SF | I59: B31D | L59: Prop | M59: Awaiting order request
B60: Securico | C60: Door Sensor (Mag) - Wired | E60: SEC-MSC | F60: 450 | H60: SF | I60: B30D | L60: Prop | M60: Awaiting order request
B61: Securico | C61: Door Sensor (Mag) - Wired | E61: SEC-MSC | F61: 450 | H61: FF | I61: B20D | L61: Prop | M61: Awaiting order request
B62: Securico | C62: Door Sensor (Mag) - Wired | E62: SEC-MSC | F62: 450 | H62: FF | I62: B18D | L62: Prop | M62: Awaiting order request
B63: Securico | C63: Door Sensor (Mag) - Wired | E63: SEC-MSC | F63: 450 | H63: FF | I63: B19D | L63: Prop | M63: Awaiting order request
B64: Securico | C64: Door Sensor (Mag) - Wired | E64: SEC-MSC | F64: 450 | H64: FF | I64: B17D | L64: Prop | M64: Awaiting order request
B65: Securico | C65: Door Sensor (Mag) - Wired | E65: SEC-MSC | F65: 450 | H65: FF | I65: B16D | L65: Prop | M65: Awaiting order request
B66: Securico | C66: Door Sensor (Mag) - Wired | E66: SEC-MSC | F66: 450 | H66: GF | I66: B07D | L66: Prop | M66: Awaiting order request | R66: IR No.1388
B67: Securico | C67: Door Sensor (Mag) - Wired | E67: SEC-MSC | F67: 450 | H67: FF | I67: B15D | L67: Prop | M67: Awaiting order request
B68: Securico | C68: Door Sensor (Mag) - Wired | E68: SEC-MSC | F68: 450 | H68: GF | I68: B06D | L68: Prop | M68: Awaiting order request | R68: IR No.1388
B69: Securico | C69: Door Sensor (Mag) - Wired | E69: SEC-MSC | F69: 450 | H69: GF | I69: B04D | L69: Prop | M69: Awaiting order request | R69: IR No.1388
B70: Securico | C70: Door Sensor (Mag) - Wired | E70: SEC-MSC | F70: 450 | H70: GF | I70: B05D | L70: Prop | M70: Awaiting order request | R70: IR No.1388
B71: Securico | C71: Door Sensor (Mag) - Wired | E71: SEC-MSC | F71: 450 | H71: GF | I71: B03D | L71: Prop | M71: Awaiting order request | R71: IR No.1388
B72: Securico | C72: Door Sensor (Mag) - Wired | E72: SEC-MSC | F72: 450 | H72: GF | I72: B02D | L72: Prop | M72: Awaiting order request | R72: IR No.1388
B73: Securico | C73: Door Sensor (Mag) - Wired | E73: SEC-MSC | F73: 450 | H73: GF | I73: B01D | L73: Prop | M73: Awaiting order request | R73: IR No.1388
B74: DSC | C74: Glass Break Detector Wired (Digital) | E74: LC-105-DGB | F74: 3167 | H74: GF | I74: B37G | L74: Prop | M74: Awaiting order request | R74: IR No.1388
B75: DSC | C75: Glass Break Detector Wired (Digital) | E75: LC-105-DGB | F75: 3167 | H75: SF | I75: B36G | L75: Prop | M75: Awaiting order request
B76: DSC | C76: Glass Break Detector Wired (Digital) | E76: LC-105-DGB | F76: 3167 | H76: SF | I76: B34G | L76: Prop | M76: Awaiting order request
B77: DSC | C77: Glass Break Detector Wired (Digital) | E77: LC-105-DGB | F77: 3167 | H77: SF | I77: B35G | L77: Prop | M77: Awaiting order request
B78: DSC | C78: Glass Break Detector Wired (Digital) | E78: LC-105-DGB | F78: 3167 | H78: SF | I78: B33G | L78: Prop | M78: Awaiting order request
B79: DSC | C79: Glass Break Detector Wired (Digital) | E79: LC-105-DGB | F79: 3167 | H79: SF | I79: B32G | L79: Prop | M79: Awaiting order request
B80: DSC | C80: Glass Break Detector Wired (Digital) | E80: LC-105-DGB | F80: 3167 | H80: FF | I80: B28G | L80: Prop | M80: Awaiting order request
B81: DSC | C81: Glass Break Detector Wired (Digital) | E81: LC-105-DGB | F81: 3167 | H81: FF | I81: B29G | L81: Prop | M81: Awaiting order request
B82: DSC | C82: Glass Break Detector Wired (Digital) | E82: LC-105-DGB | F82: 3167 | H82: FF | I82: B27G | L82: Prop | M82: Awaiting order request
B83: DSC | C83: Glass Break Detector Wired (Digital) | E83: LC-105-DGB | F83: 3167 | H83: FF | I83: B26G | L83: Prop | M83: Awaiting order request
B84: DSC | C84: Glass Break Detector Wired (Digital) | E84: LC-105-DGB | F84: 3167 | H84: FF | I84: B25G | L84: Prop | M84: Awaiting order request
B85: DSC | C85: Glass Break Detector Wired (Digital) | E85: LC-105-DGB | F85: 3167 | H85: FF | I85: B24G | L85: Prop | M85: Awaiting order request
B86: DSC | C86: Glass Break Detector Wired (Digital) | E86: LC-105-DGB | F86: 3167 | H86: FF | I86: B23G | L86: Prop | M86: Awaiting order request
B87: DSC | C87: Glass Break Detector Wired (Digital) | E87: LC-105-DGB | F87: 3167 | H87: FF | I87: B22G | L87: Prop | M87: Awaiting order request
B88: DSC | C88: Glass Break Detector Wired (Digital) | E88: LC-105-DGB | F88: 3167 | H88: GF | I88: B14G | L88: Prop | M88: Awaiting order request | R88: IR No.1388
B89: DSC | C89: Glass Break Detector Wired (Digital) | E89: LC-105-DGB | F89: 3167 | H89: FF | I89: B21G | L89: Prop | M89: Awaiting order request
B90: DSC | C90: Glass Break Detector Wired (Digital) | E90: LC-105-DGB | F90: 3167 | H90: GF | I90: B13G | L90: Prop | M90: Awaiting order request | R90: IR No.1388
B91: DSC | C91: Glass Break Detector Wired (Digital) | E91: LC-105-DGB | F91: 3167 | H91: GF | I91: B11G | L91: Prop | M91: Awaiting order request | R91: IR No.1388
B92: DSC | C92: Glass Break Detector Wired (Digital) | E92: LC-105-DGB | F92: 3167 | H92: GF | I92: B12G | L92: Prop | M92: Awaiting order request | R92: IR No.1388
B93: DSC | C93: Glass Break Detector Wired (Digital) | E93: LC-105-DGB | F93: 3167 | H93: GF | I93: B10G | L93: Prop | M93: Awaiting order request | R93: IR No.1388
B94: DSC | C94: Glass Break Detector Wired (Digital) | E94: LC-105-DGB | F94: 3167 | H94: GF | I94: B08G | L94: Prop | M94: Awaiting order request | R94: IR No.1388
B95: DSC | C95: Glass Break Detector Wired (Digital) | E95: LC-105-DGB | F95: 3167 | H95: GF | I95: B09G | L95: Prop | M95: Awaiting order request | R95: IR No.1388
B96: DSC | C96: Glass Break Detector Wired (Digital) | E96: LC-105-DGB | F96: 3167 | H96: GF | L96: Prop | M96: Awaiting order request | R96: IR No.1388
B97: DSC | C97: Siren 15W | E97: SD15W | F97: 1400 | H97: GF | L97: Prop | M97: Awaiting order request | R97: IR No.1388
B98: DSC | C98: DSC - Power Supply (Transformer) | F98: 2400 | L98: Prop | M98: Awaiting order request
C99: Battery Backup | E99: 12V-7amp | F99: 1140 | L99: Prop | M99: Awaiting order request
A101: Automation | B101: KNX | C101: KNX Power Supply 640mA | E101: 24V | F101: 26900 | G101: 77350 | L101: Prop | M101: Awaiting order request
B102: KNX | C102: GWORLD KNX IP Interface | E102: IPG-0001 | F102: 32779 | L102: Prop | M102: Awaiting order request
B103: KNX | C103: GWORLD KNX 20 Channel Actuator | E103: ACT-0020 | F103: 43102 | L103: Prop | M103: Awaiting order request
B104: KNX | C104: GWORLD KNX 20 Channel Actuator | E104: ACT-0020 | F104: 43102 | L104: Prop | M104: Awaiting order request
B105: KNX | C105: GWORLD KNX 20 Channel Actuator | E105: ACT-0020 | F105: 43102 | L105: Prop | M105: Awaiting order request
...

Sheet Duraiswamy
B1: Client Name | C1: Mr.Duraiswamy | F1: Overall site status | J1: Count | K1: % | M1: Material status | N1: Count | O1: % | Q1: Visti No. | R1: IR No. | S1: Date
B2: Site | C2: Peelamedu | F2: Yet to start | M2: Awaiting order request | Q2: 1 | R2: IR No.1552 | S2: 23.4.2025 | U2: Sakthi
B3: Location | F3: Position marked - I | M3: To order material
B4: GPS Coordinates | F4: Piping done - C | M4: Ordered
B5: Architect | C5: Mr.Rithesh | E5: 9944399264 | F5: Wiring done - C | M5: Recd (To test/config)
B6: Site Supervisor | F6: Wiring - Checked Ok - I | M6: Configured - ready for install
B7: Electrician | F7: Wiring rework reqd - C | M7: Delivered
B8: Electrical Contractor | F8: Provision not provided - C | M8: Provision only - Matl Not reqd
B9: Billing contact | F9: Position to be changed - C | M9: Failed - Picked up from site
B10: Carpenter | F10: Installed - working | M10: Failed - Need to service
B11: Civil Supervisor | F11: Installed - To activate - I | M11: Sent for service
B12: G-Drive Link | F12: Installed - Not working - IC | M12: Replaced/Serviced
B13: Mail id | F13: Door Ready - C | M13: Returned - Not reqd
B14: Site Engineer | F14: Door Not Ready - I
B16: Brand | C16: Product | D16: Serial No. | E16: Model No | F16: Sale Price | G16: Installation charge | H16: Location | I16: Drawing Ref No. | J16: Site status | K16: <--Date | L16: Prop/Addl | M16: Material | N16: <-- Date | O16: Client | P16: Inka | Q16: Comments | R16: SR Nos (If multiple - add all) | S16: DC
A17: Camera | B17: Prama | C17: 4 Mp Bullet IP Camera Colour/InbuiltMic - Prama | E17: PT-NC140D3LIU(D2) | F17: 4750 | G17: 12450 | J17: Position marked - I | K17: 23.4.2025 | L17: Prop | M17: Awaiting order request | R17: 1552
B18: Prama | C18: 4 Mp Bullet IP Camera Colour/InbuiltMic - Prama | E18: PT-NC140D3LIU(D2) | F18: 4750 | J18: Position marked - I | K18: 23.4.2025 | L18: Prop | M18: Awaiting order request | R18: 1552
B19: Prama | C19: 4 Mp Bullet IP Camera Colour/InbuiltMic - Prama | E19: PT-NC140D3LIU(D2) | F19: 4750 | J19: Position marked - I | K19: 23.4.2025 | L19: Prop | M19: Awaiting order request | R19: 1552
B20: Prama | C20: 4 Mp Bullet IP Camera Colour/InbuiltMic - Prama | E20: PT-NC140D3LIU(D2) | F20: 4750 | J20: Position marked - I | K20: 23.4.2025 | L20: Prop | M20: Awaiting order request | R20: 1552
B21: Prama | C21: 4 Mp Bullet IP Camera Colour/InbuiltMic - Prama | E21: PT-NC140D3LIU(D2) | F21: 4750 | J21: Position marked - I | K21: 23.4.2025 | L21: Prop | M21: Awaiting order request | R21: 1552
B22: Prama | C22: 4 Mp Bullet IP Camera Colour/InbuiltMic - Prama | E22: PT-NC140D3LIU(D2) | F22: 4750 | J22: Position marked - I | K22: 23.4.2025 | L22: Prop | M22: Awaiting order request | R22: 1552
B23: Prama | C23: 4 Mp Bullet IP Camera Colour/InbuiltMic - Prama | E23: PT-NC140D3LIU(D2) | F23: 4750 | J23: Position marked - I | K23: 23.4.2025 | L23: Prop | M23: Awaiting order request | R23: 1552
B24: Prama | C24: 4 Mp Bullet IP Camera Colour/InbuiltMic - Prama | E24: PT-NC140D3LIU(D2) | F24: 4750 | J24: Position marked - I | K24: 23.4.2025 | L24: Prop | M24: Awaiting order request | R24: 1552
B25: Prama | C25: 4 Mp Bullet IP Camera Colour/InbuiltMic - Prama | E25: PT-NC140D3LIU(D2) | F25: 4750 | J25: Position marked - I | K25: 23.4.2025 | L25: Prop | M25: Awaiting order request | R25: 1552
B26: Hikvision | C26: 16 channel NVR (K4) - Hikvision | E26: DS-7716NI-K4 | F26: 15600 | J26: Position marked - I | K26: 23.4.2025 | L26: Prop | M26: Awaiting order request | R26: 1552
B27: TP Link | C27: 16 Port POE Switch - TP Link | E27: SL1218MP | F27: 16750 | J27: Position marked - I | K27: 23.4.2025 | L27: Prop | M27: Awaiting order request | R27: 1552
B28: Toshiba | C28: 4 TB Hard Disk - Toshiba | E28: AVHDDS300 | F28: 8160 | J28: Position marked - I | K28: 23.4.2025 | L28: Prop | M28: Awaiting order request | R28: 1552
C29: Camera Accessories | F29: 1700 | J29: Position marked - I | K29: 23.4.2025 | L29: Prop | M29: Awaiting order request | R29: 1552
A31: Security Alarm System - Tyco DSC | B31: DSC | C31: DSC - Control Panel | E31: HS2128CE | F31: 33782 | G31: 31000 | J31: Position marked - I | K31: 23.4.2025 | L31: Prop | M31: Awaiting order request | R31: 1552
B32: DSC | C32: DSC - LCD Keypad Kit | E32: HS2LCDS | F32: 6300 | J32: Position marked - I | K32: 23.4.2025 | L32: Prop | M32: Awaiting order request | R32: 1552
B33: DSC | C33: DSC - IP Module | E33: TL280E | F33: 9780 | J33: Position marked - I | K33: 23.4.2025 | L33: Prop | M33: Awaiting order request | R33: 1552
B34: DSC | C34: DSC - Wired 8 Zone Expander (Expansion Module) | E34: HSM2108 | F34: 4653 | J34: Position marked - I | K34: 23.4.2025 | L34: Prop | M34: Awaiting order request | R34: 1552
B35: DSC | C35: DSC - Wired 8 Zone Expander (Expansion Module) | E35: HSM2108 | F35: 4653 | J35: Position marked - I | K35: 23.4.2025 | L35: Prop | M35: Awaiting order request | R35: 1552
B36: Seurico | C36: Door Sensor (Mag) - Wired | E36: SEC-MSC | F36: 450 | J36: Position marked - I | K36: 23.4.2025 | L36: Prop | M36: Awaiting order request | Q36: Wicket gate door sensor cancelled | R36: 1552
B37: Seurico | C37: Door Sensor (Mag) - Wired | E37: SEC-MSC | F37: 450 | J37: Position marked - I | K37: 23.4.2025 | L37: Prop | M37: Awaiting order request | R37: 1552
B38: Seurico | C38: Door Sensor (Mag) - Wired | E38: SEC-MSC | F38: 450 | J38: Position marked - I | K38: 23.4.2025 | L38: Prop | M38: Awaiting order request | R38: 1552
B39: Seurico | C39: Door Sensor (Mag) - Wired | E39: SEC-MSC | F39: 450 | J39: Position marked - I | K39: 23.4.2025 | L39: Prop | M39: Awaiting order request | R39: 1552
B40: Seurico | C40: Door Sensor (Mag) - Wired | E40: SEC-MSC | F40: 450 | J40: Position marked - I | K40: 23.4.2025 | L40: Prop | M40: Awaiting order request | R40: 1552
B41: Seurico | C41: Door Sensor (Mag) - Wired | E41: SEC-MSC | F41: 450 | J41: Position marked - I | K41: 23.4.2025 | L41: Prop | M41: Awaiting order request | R41: 1552
B42: DSC | C42: Glass Break Detector Wired (Digital) | E42: LC-105-DGB | F42: 3267 | J42: Position marked - I | K42: 23.4.2025 | L42: Prop | M42: Awaiting order request | R42: 1552
B43: DSC | C43: Glass Break Detector Wired (Digital) | E43: LC-105-DGB | F43: 3267 | J43: Position marked - I | K43: 23.4.2025 | L43: Prop | M43: Awaiting order request | R43: 1552
B44: DSC | C44: Glass Break Detector Wired (Digital) | E44: LC-105-DGB | F44: 3267 | J44: Position marked - I | K44: 23.4.2025 | L44: Prop | M44: Awaiting order request | R44: 1552
B45: DSC | C45: Glass Break Detector Wired (Digital) | E45: LC-105-DGB | F45: 3267 | J45: Position marked - I | K45: 23.4.2025 | L45: Prop | M45: Awaiting order request | R45: 1552
B46: DSC | C46: Glass Break Detector Wired (Digital) | E46: LC-105-DGB | F46: 3267 | J46: Position marked - I | K46: 23.4.2025 | L46: Prop | M46: Awaiting order request | R46: 1552
B47: DSC | C47: Glass Break Detector Wired (Digital) | E47: LC-105-DGB | F47: 3267 | J47: Position marked - I | K47: 23.4.2025 | L47: Prop | M47: Awaiting order request | R47: 1552
B48: DSC | C48: Glass Break Detector Wired (Digital) | E48: LC-105-DGB | F48: 3267 | J48: Position marked - I | K48: 23.4.2025 | L48: Prop | M48: Awaiting order request | R48: 1552
... B84: DSC | C84: Glass Break Detector Wired (Digital) | E84: LC-105-DGB | F84: 3267 | J84: Position marked - I | K84: 23.4.2025 | L84: Prop | M84: Awaiting order request | R84: 1552
C85: Siren 15W | E85: SD15W | F85: 1450 | J85: Position marked - I | K85: 23.4.2025 | L85: Prop | M85: Awaiting order request | R85: 1552
B86: DSC | C86: DSC - Power Supply (220V CE Transformer) | E86: 220-16.5V TRF | F86: 2808 | J86: Position marked - I | K86: 23.4.2025 | L86: Prop | M86: Awaiting order request | R86: 1552
C87: Battery Backup | E87: 12V-7amp | F87: 1240 | J87: Position marked - I | K87: 23.4.2025 | L87: Prop | M87: Awaiting order request | R87: 1552
J88: Position marked - I | K88: 23.4.2025 | L88: Prop | M88: Awaiting order request | R88: 1552

Sheet Vijayaram Balasundaram
B1: Client Name | C1: Mr.Vijayaram Balasundaram | E1: 9952471219 | F1: Overall site status | J1: Count | K1: % | M1: Material status | N1: Count | O1: % | Q1: Visti No. | R1: IR No. | S1: Date
B2: Site | C2: Peelamedu | F2: Yet to start | M2: Awaiting order request | Q2: 1 | S2: 24.3.2025 | T2: 1st site visit | U2: Sakthi
B3: Location | C3: https://www.google.com/maps/place/11%C2%B000'52.2%22N+77%C2%B000'15.3%22E/@11.3810035,76.5757,9.45z/data=!4m4!3m3!8m2!3d11.0144879!4d77.0042351?hl=en&entry=ttu&g_ep=EgoyMDI1MDMxOS4yIKXMDSoASAFQAw%3D%3D | F3: Position marked - I | M3: To order material | Q3: 2
B4: GPS Coordinates | F4: Piping done - C | M4: Ordered
B5: Architect | C5: Mr.Rithesh | E5: 9944399264 | F5: Wiring done - C | M5: Recd (To test/config)
B6: Site Supervisor | F6: Wiring - Checked Ok - I | M6: Configured - ready for install
B7: Electrician | F7: Wiring rework reqd - C | M7: Delivered
B8: Electrical Contractor | F8: Provision not provided - C | M8: Provision only - Matl Not reqd
B9: Billing contact | F9: Position to be changed - C | M9: Failed - Picked up from site
B10: Carpenter | F10: Installed - working | M10: Failed - Need to service
B11: Civil Supervisor | F11: Installed - To activate - I | M11: Sent for service
B12: G-Drive Link | F12: Installed - Not working - IC | M12: Replaced/Serviced
B13: Mail id | F13: Door Ready - C | M13: Returned - Not reqd
B14: Site Engineer | F14: Door Not Ready - I
B16: Brand | C16: Product | D16: Serial No. | E16: Model No | F16: Sale Price | G16: Installation charge | H16: Location | I16: Drawing Ref No. | J16: Site status | K16: <--Date | L16: Prop/Addl | M16: Material | N16: <-- Date | O16: Client | P16: Inka | Q16: Comments | R16: SR Nos (If multiple - add all) | S16: DC
A17: Camera | B17: Prama | C17: 4 Mp Bullet IP Camera Colour/InbuiltMic - Prama | E17: PT-NC140D3LIU(D2) | F17: 4840 | G17: 11500 | J17: Installed - working | L17: Prop
B18: Prama | C18: 4 Mp Bullet IP Camera Colour/InbuiltMic - Prama | E18: PT-NC140D3LIU(D2) | F18: 4840 | J18: Installed - working | L18: Prop
B19: Prama | C19: 4 Mp Bullet IP Camera Colour/InbuiltMic - Prama | E19: PT-NC140D3LIU(D2) | F19: 4840 | J19: Installed - working | L19: Prop
B20: Prama | C20: 4 Mp Bullet IP Camera Colour/InbuiltMic - Prama | E20: PT-NC140D3LIU(D2) | F20: 4840 | J20: Installed - working | L20: Prop
B21: Prama | C21: 4 Mp Bullet IP Camera Colour/InbuiltMic - Prama | E21: PT-NC140D3LIU(D2) | F21: 4840 | J21: Installed - working | L21: Prop
B22: Prama | C22: 4 Mp Bullet IP Camera Colour/InbuiltMic - Prama | E22: PT-NC140D3LIU(D2) | F22: 4840 | J22: Installed - working | L22: Prop
B23: Prama | C23: 4 Mp Bullet IP Camera Colour/InbuiltMic - Prama | E23: PT-NC140D3LIU(D2) | F23: 4840 | J23: Installed - working | L23: Prop
B24: Prama | C24: 4 Mp Bullet IP Camera Colour/InbuiltMic - Prama | E24: PT-NC140D3LIU(D2) | F24: 4840 | J24: Installed - working | L24: Prop
B25: Prama | C25: 4 Mp Bullet IP Camera Colour/InbuiltMic - Prama | E25: PT-NC140D3LIU(D2) | F25: 4840 | J25: Installed - working | L25: Prop
B26: Prama | C26: 4 Mp Bullet IP Camera Colour/InbuiltMic - Prama | E26: PT-NC140D3LIU(D2) | F26: 4840 | J26: Installed - working | L26: Prop
B27: Prama | C27: 4 Mp Bullet IP Camera Colour/InbuiltMic - Prama | E27: PT-NC140D3LIU(D2) | F27: 4840 | J27: Installed - working | L27: Prop
B28: Prama | C28: 4 Mp Bullet IP Camera Colour/InbuiltMic - Prama | E28: PT-NC140D3LIU(D2) | F28: 4840 | J28: Installed - working | L28: Prop
B29: Prama | C29: 4 Mp Bullet IP Camera Colour/InbuiltMic - Prama | E29: PT-NC140D3LIU(D2) | F29: 4840 | J29: Installed - working
B30: Prama Hivision | C30: 16 Channel NVR (K2) - Prama Hikvision | E30: PT-NRAS2A16-K2 | F30: 14500 | J30: Installed - working | L30: Prop
B31: TP Link | C31: 24 Port POE Switch (SG2428P) - TPlink | D31: 22515H6000435 | E31: SG2428P | F31: 27450 | J31: Installed - working | L31: Prop
B32: Toshiba | C32: 8 TB Hard Disk - Toshiba | E32: nil | F32: 17980 | J32: Installed - working | L32: Prop
B33: Netfox | C33: Cat 6 Jack - Netfox-30 Nos. | E33: RJ-45 | F33: 25 | J33: Installed - working | M33: Delivered | N33: 1.8.2025 | S33: 116
A35: Security Alarm System - DSC TYCO | B35: DSC-Tyco | C35: DSC - Control Panel 64 Zone | E35: HS2064PCBCE | F35: 34460 | J35: Installed - working | L35: Prop
B36: DSC-Tyco | C36: DSC - LCD Keypad Kit | E36: HS2LCDS | F36: 6300 | J36: Installed - working | L36: Prop
B37: DSC-Tyco | C37: DSC - Power Supply (220V CE Transformer) | E37: 220-16.5V TRF | F37: 2808 | J37: Installed - working | L37: Prop
B38: Securico | C38: Door Sensor (Mag) - Wired | E38: SEC-MSC | F38: 450 | J38: Installed - working | L38: Prop
B39: Securico | C39: Door Sensor (Mag) - Wired | E39: SEC-MSC | F39: 450 | J39: Installed - working | L39: Prop
B40: Securico | C40: Door Sensor (Mag) - Wired | E40: SEC-MSC | F40: 450 | J40: Installed - working | L40: Prop
B41: Securico | C41: Door Sensor (Mag) - Wired | E41: SEC-MSC | F41: 450 | J41: Installed - working | L41: Prop
B42: Securico | C42: Door Sensor (Mag) - Wired | E42: SEC-MSC | F42: 450 | J42: Installed - working | L42: Prop
B43: Securico | C43: Door Sensor (Mag) - Wired | E43: SEC-MSC | F43: 450 | J43: Installed - working | L43: Prop
B44: Securico | C44: Door Sensor (Mag) - Wired | E44: SEC-MSC | F44: 450 | J44: Installed - working | L44: Prop
B45: Securico | C45: Door Sensor (Mag) - Wired | E45: SEC-MSC | F45: 450 | J45: Installed - working | L45: Prop
B46: Securico | C46: Door Sensor (Mag) - Wired | E46: SEC-MSC | F46: 450 | J46: Installed - working | L46: Prop
B47: Securico | C47: Door Sensor (Mag) - Wired | E47: SEC-MSC | F47: 450 | J47: Installed - working | L47: Prop
... B64: DSC-Tyco | C64: Glass Break Detector Wired (Vibration Sensor) | E64: AC101 | F64: 3440 | J64: Installed - working | L64: Prop
B65: DSC-Tyco | C65: Glass Break Detector Wired (Vibration Sensor) | E65: AC101 | F65: 3440 | L65: Prop
B66: DSC-Tyco | C66: Glass Break Detector Wired (Vibration Sensor) | E66: AC101 | F66: 3440 | L66: Prop
B67: DSC-Tyco | C67: Glass Break Detector Wired (Vibration Sensor) | E67: AC101 | F67: 3440 | L67: Prop
B68: DSC-Tyco | C68: Glass Break Detector Wired (Vibration Sensor) | E68: AC101 | F68: 3440 | L68: Prop
B69: DSC-Tyco | C69: Glass Break Detector Wired (Vibration Sensor) | E69: AC101 | F69: 3440 | L69: Prop
B70: DSC-Tyco | C70: Glass Break Detector Wired (Vibration Sensor) | E70: AC101 | F70: 3440 | L70: Prop
B71: DSC-Tyco | C71: Glass Break Detector Wired (Vibration Sensor) | E71: AC101 | F71: 3440 | L71: Prop
B72: DSC-Tyco | C72: Glass Break Detector Wired (Vibration Sensor) | E72: AC101 | F72: 3440 | L72: Prop
B73: DSC-Tyco | C73: DSC - IP Module | E73: TL280E | F73: 9780 | J73: Installed - working | L73: Prop
B74: DSC-Tyco | C74: DSC - Wired 8 Zone Expander (Expansion Module) | E74: HSM2108 | F74: 7653 | J74: Installed - working
B75: DSC-Tyco | C75: DSC - Wireless Receiver (Transceiver Module) | E75: HSM2HOST4 | F75: 9696 | J75: Installed - working
B76: DSC-Tyco | C76: DSC - Wireless Door Sensor (PG4945) | E76: PG4945 | F76: 2570 | J76: Installed - working
B77: DSC-Tyco | C77: DSC - Wireless Door Sensor (PG4945) | E77: PG4945 | F77: 2570 | J77: Installed - working
B78: DSC-Tyco | C78: DSC - Wireless Door Sensor (PG4945) | E78: PG4945 | F78: 2570 | J78: Installed - working
B79: DSC-Tyco | C79: DSC - Wireless Door Sensor (PG4945) | E79: PG4945 | F79: 2570 | J79: Installed - working
B80: DSC-Tyco | C80: DSC - Wireless Door Sensor (PG4945) | E80: PG4945 | F80: 2570 | J80: Installed - working
C81: Siren 15W | E81: SD15W | F81: 1400 | J81: Installed - working | L81: Prop
C82: Battery Backup | E82: 12V-7amp | F82: 1760 | J82: Installed - working | L82: Prop
L83: Prop
A84: Vedio Door Phone - Hikvision | B84: Hikvision | C84: VDP Outdoor Camera - Hikvision | E84: DS-KD8003-IME1/Surface | F84: 10600 | G84: 2080 | J84: Installed - working | L84: Prop
B85: Hikvision | C85: VDP Indoor Monitor - Hikvision | E85: DS-KH6320-WTE1 | F85: 9480 | J85: Installed - working | L85: Prop
A87: Wifi Access Point - TP Link | B87: TP Link | C87: Access Point EAP245 - TP Link | E87: EAP245 | F87: 8250 | G87: 3320 | J87: Installed - working | L87: Prop
B88: TP Link | C88: Access Point EAP245 - TP Link | E88: EAP245 | F88: 8250 | J88: Installed - working | L88: Prop
B89: TP Link | C89: Access Point EAP245 - TP Link | E89: EAP245 | F89: 8250 | J89: Installed - working | L89: Prop
B90: TP Link | C90: Access Point EAP245 - TP Link | E90: EAP245 | F90: 8250 | J90: Installed - working | L90: Prop
B91: TP Link | C91: 8 Port Switch (Gigabit) - TP Link | E91: TL-SG2008D | F91: 8450 | J91: Installed - working | L91: Prop
A93: Automation | B93: Eglu | C93: In-Wall Switch 3S - Eg | E93: EGIW04R | F93: 8550 | G93: 4155 | J93: Provision only - Matl Not reqd | L93: Prop
B94: Eglu | C94: In-Wall Switch 3S - Eg | E94: EGIW04R | F94: 8550 | J94: Provision only - Matl Not reqd | L94: Prop
B95: Eglu | C95: Automation Hub Plus - Eg | E95: EG-PLUS | F95: 24450 | J95: Provision only - Matl Not reqd | L95: Prop
C100: Camera Stand Adjustable- 1 to 2 Feet | E100: 30-60CM | F100: 950 | G100: 1500
C101: Power Card 3pin (Security System) | E101: Nil | F101: 150
C102: Glass Break Detector Wired (Vibration Sensor) | E102: AC101 | F102: 3440
C103: PVC (Hensel) Box | E103: NIL | F103: 154
C104: PVC (Hensel) Box | E104: NIL | F104: 154
C105: PVC (Hensel) Box | E105: NIL | F105: 154
C106: PVC (Hensel) Box | E106: NIL | F106: 154
C107: PVC (Hensel) Box | E107: NIL | F107: 154
C108: PVC (Hensel) Box | E108: NIL | F108: 154
C109: Door Sensor (Mag) - Wired squire -white | E109: SEC-MSC | F109: 450
C110: Door Sensor (Mag) - Wired squire -white | E110: SEC-MSC | F110: 450
C111: Door Sensor (Mag) - Wired squire -white | E111: SEC-MSC | F111: 450
C112: Cabinet Lock | E112: L-1 | F112: 250
... C118: Push Button | E118: Z-86D | F118: 100

Sheet Renjith
B1: Client Name | C1: Mr. Renjith | F1: Overall site status | J1: Count | K1: % | M1: Material status | N1: Count | O1: % | Q1: Visti No. | R1: IR No. | S1: Date
B2: Site | C2: Calicut | F2: Yet to start | M2: Awaiting order request | Q2: 1 | R2: IR No.1393 | S2: 4.11.2024 | T2: 1st site visit | U2: Sakthi
B3: Location | F3: Position marked - I | M3: To order material | Q3: 2 | R3: IR No.1397 | S3: 9.11.2024 | T3: Provision discussion | U3: Sakthi
B4: GPS Coordinates | F4: Piping done - C | M4: Ordered
B5: Architect | C5: Ar.Rajeev | E5: 9447008560 | F5: Wiring done - C | M5: Recd (To test/config)
B6: Site Supervisor | F6: Wiring - Checked Ok - I | M6: Configured - ready for install
B7: Electrician | C7: Mr. Yusaf | E7: 9995261777 | F7: Wiring rework reqd - C | M7: Delivered
B8: Electrical Contractor | F8: Provision not provided - C | M8: Provision only - Matl Not reqd
B9: Billing contact | F9: Position to be changed - C | M9: Failed - Picked up from site
B10: Carpenter | F10: Installed - working | M10: Failed - Need to service
B11: Civil Supervisor | F11: Installed - To activate - I | M11: Sent for service
B12: G-Drive Link | F12: Installed - Not working - IC | M12: Replaced/Serviced
B13: Mail id | F13: Door Ready - C | M13: Returned - Not reqd
B14: Site Engineer | F14: Door Not Ready - I
B16: Brand | C16: Product | D16: Serial No. | E16: Model No | F16: Sale Price | G16: Installation charge | H16: Location | I16: Drawing Ref No. | J16: Site status | K16: <--Date | L16: Prop/Addl | M16: Material | N16: <-- Date | O16: Client | P16: Inka | Q16: Comments | R16: SR Nos (If multiple - add all) | S16: DC
A17: Camera | B17: Hikvision | C17: 4 MP Bullet IP Camera ColorVu - (1047G2-L) | E17: DS-2CD1047G2-L | F17: 5440 | G17: 16500 | J17: Position marked - I | L17: Prop
C18: 4 MP Bullet IP Camera ColorVu - (1047G2-L) | E18: DS-2CD1047G2-L | F18: 5440 | J18: Position marked - I | L18: Prop
C19: 4 MP Bullet IP Camera ColorVu - (1047G2-L) | E19: DS-2CD1047G2-L | F19: 5440 | J19: Position marked - I | L19: Prop
C20: 4 MP Bullet IP Camera ColorVu - (1047G2-L) | E20: DS-2CD1047G2-L | F20: 5440 | J20: Position marked - I | L20: Prop
C21: 4 MP Bullet IP Camera ColorVu - (1047G2-L) | E21: DS-2CD1047G2-L | F21: 5440 | G21: 5440 | J21: Position marked - I | L21: Prop
C22: 4 MP Bullet IP Camera ColorVu - (1047G2-L) | E22: DS-2CD1047G2-L | F22: 5440 | J22: Position marked - I | L22: Prop
C23: 4 MP Bullet IP Camera ColorVu - (1047G2-L) | E23: DS-2CD1047G2-L | F23: 5440 | J23: Position marked - I | L23: Prop
C24: 4 MP Bullet IP Camera ColorVu - (1047G2-L) | E24: DS-2CD1047G2-L | F24: 5440 | J24: Position marked - I | L24: Prop
C25: 4 MP Bullet IP Camera ColorVu - (1047G2-L) | E25: DS-2CD1047G2-L | F25: 5440 | J25: Position marked - I | L25: Prop
C26: 4 MP Bullet IP Camera ColorVu - (1047G2-L) | E26: DS-2CD1047G2-L | F26: 5440 | J26: Position marked - I | L26: Prop
C27: 4 MP Bullet IP Camera ColorVu - (1047G2-L) | E27: DS-2CD1047G2-L | F27: 5440 | J27: Position marked - I | L27: Prop
C28: 4 MP Bullet IP Camera ColorVu - (1047G2-L) | E28: DS-2CD1047G2-L | F28: 5440 | J28: Position marked - I | L28: Prop
C29: 4 MP Bullet IP Camera ColorVu - (1047G2-L) | E29: DS-2CD1047G2-L | F29: 5440 | J29: Position marked - I | L29: Prop
C30: 16 channel NVR (K2) - Hikvision | E30: DS-7616NI-K2 | F30: 15480 | J30: Position marked - I | L30: Prop
B31: TP Link | C31: 16 Port POE Gigabit Switch (TL-SG1218MPE) - TP Link | E31: TL-SG1218MPE | F31: 16720 | J31: Position marked - I | L31: Prop
B32: Toshiba | C32: 4 TB Hard Disk - Toshiba | E32: AVHDDS300 | F32: 8160 | J32: Position marked - I | L32: Prop
A34: Video Door Phone System - Hikvision | B34: Hikvisiion | C34: VDP Outdoor Camera | E34: DS-KD8003-IME1/Surface | F34: 10600 | G34: 6500 | J34: Position marked - I | L34: Prop
C35: VDP Indoor Monitor | E35: DS-KH6320-WTE1 | F35: 9780 | J35: Position marked - I | L35: Prop
C36: VDP Indoor Monitor | E36: DS-KH6320-WTE1 | F36: 9780 | J36: Position marked - I | L36: Prop
C37: 4 Port POE Switch | E37: DS-3E0105P-E/M | F37: 3750 | J37: Position marked - I | L37: Prop
A39: WIFI Access Point - TP Link | B39: TP Link | C39: Access Point EAP245 - TP Link | E39: EAP245 | F39: 8640 | G39: 5900 | J39: Position marked - I | L39: Prop
C40: Access Point EAP245 - TP Link | E40: EAP245 | F40: 8640 | J40: Position marked - I | L40: Prop
C41: Access Point EAP245 - TP Link | E41: EAP245 | F41: 8640 | J41: Position marked - I | L41: Prop
C42: Access Point EAP245 - TP Link | E42: EAP245 | F42: 8640 | J42: Position marked - I | L42: Prop
C43: Cat 6 Cable - Netfoxv- 610 mts | E43: Gold N | F43: 18910 | J43: Position marked - I | L43: Prop
A45: Security Alarm System - Hikvision | B45: Hikvision | C45: Hikvision - Control Panel Wired Hybrid Inbuilt Power Supply, IP Module, 8 Zone Expander | E45: DS-PHA64-LP(B) | F45: 31650 | G45: 24900 | J45: Position marked - I | L45: Prop
B46: Hikvision | C46: Hikvision LCD Keypad | E46: LCD | F46: 7650 | J46: Position marked - I | L46: Prop
B47: Hikvision | C47: Hikvision IP Module | E47: IP Module | F47: 9450 | J47: Position marked - I | L47: Prop
B48: Securico | C48: Door Sensor (Mag) - Wired | E48: SEC-MSC | F48: 450 | J48: Position marked - I | L48: Prop
B49: Securico | C49: Door Sensor (Mag) - Wired | E49: SEC-MSC | F49: 450 | J49: Position marked - I | L49: Prop
B50: Securico | C50: Door Sensor (Mag) - Wired | E50: SEC-MSC | F50: 450 | J50: Position marked - I | L50: Prop
B51: Securico | C51: Door Sensor (Mag) - Wired | E51: SEC-MSC | F51: 450 | J51: Position marked - I | L51: Prop
B52: Securico | C52: Door Sensor (Mag) - Wired | E52: SEC-MSC | F52: 450 | J52: Position marked - I | L52: Prop
B53: Hikvision | C53: Hikvision - Wired Vibration Sensor | E53: DS-PDSK-P/PHDSVB1 | F53: 3240 | J53: Position marked - I | L53: Prop
B54: Hikvision | C54: Hikvision - Wired Vibration Sensor | E54: DS-PDSK-P/PHDSVB1 | F54: 3240 | J54: Position marked - I | L54: Prop
B55: Hikvision | C55: Hikvision - Wired Vibration Sensor | E55: DS-PDSK-P/PHDSVB1 | F55: 3240 | J55: Position marked - I | L55: Prop
B56: Hikvision | C56: Hikvision - Wired Vibration Sensor | E56: DS-PDSK-P/PHDSVB1 | F56: 3240 | J56: Position marked - I | L56: Prop
B57: Hikvision | C57: Hikvision - Wired Vibration Sensor | E57: DS-PDSK-P/PHDSVB1 | F57: 3240 | J57: Position marked - I | L57: Prop
... B67: DSC | C67: DSC - Power Supply (Transformer) | E67: NIL | F67: 2400 | J67: Position marked - I | L67: Prop
C68: Battery Backup | E68: 12V-7amp | F68: 1140 | J68: Position marked - I | L68: Prop
C69: 6 Core Shielded Cable - Manidhari - 630 mts 14/0060(38)/6Core Shielded Cable (0.25 Sqmm x 6 Core Shielded) (90M) Brand :- ”MANIDHARI” CABLES [ISI] (CE) FR | E69: Nil | F69: 34650 | J69: Position marked - I | L69: Prop
A71: Home Automation System - KNX | B71: KNX | C71: KNX Power Supply 640mA | E71: 24V | F71: 27900 | G71: 104000 | J71: Position marked - I | L71: Prop
C72: GWORLD KNX IP Interface | E72: IPG-0001 | F72: 36779 | J72: Position marked - I | L72: Prop
C73: GWORLD KNX 20 Channel Actuator | E73: ACT-0020 | F73: 49102 | J73: Position marked - I | L73: Prop
C74: GWORLD KNX 20 Channel Actuator | E74: ACT-0020 | F74: 49102 | J74: Position marked - I | L74: Prop
C75: GWORLD KNX 20 Channel Actuator | E75: ACT-0020 | F75: 49102 | J75: Position marked - I | L75: Prop
C76: GWORLD KNX 20 Channel Actuator | E76: ACT-0020 | F76: 49102 | J76: Position marked - I | L76: Prop
C77: GWORLD KNX 20 Channel Actuator | E77: ACT-0020 | F77: 49102 | J77: Position marked - I | L77: Prop
C78: GWORLD KNX Dali Gateway 2 Channel | E78: DLC-02 KN | F78: 62813 | J78: Position marked - I | L78: Prop
C79: Lumi 6 Button KNX Tactile Keypads | E79: LUMIKNX6T | F79: 15250 | J79: Position marked - I | L79: Prop
C80: Lumi 6 Button KNX Tactile Keypads | E80: LUMIKNX6T | F80: 15250 | J80: Position marked - I | L80: Prop
C81: Lumi 6 Button KNX Tactile Keypads | E81: LUMIKNX6T | F81: 15250 | J81: Position marked - I | L81: Prop
C82: Lumi 6 Button KNX Tactile Keypads | E82: LUMIKNX6T | F82: 15250 | J82: Position marked - I | L82: Prop
C83: Lumi 6 Button KNX Tactile Keypads | E83: LUMIKNX6T | F83: 15250 | J83: Position marked - I | L83: Prop
... C93: Lumi KNX Gateway | E93: Home Pro | F93: 87500 | J93: Position marked - I | L93: Prop
B94: Sensinova | C94: Basic Motion HF Microwave Sensor - Ceiling mount | E94: SN-MW700C | F94: 1978 | J94: Position marked - I | L94: Prop
B95: Sensinova | C95: Basic Motion HF Microwave Sensor - Ceiling mount | E95: SN-MW700C | F95: 1978 | J95: Position marked - I | L95: Prop
B96: Sensinova | C96: Basic Motion HF Microwave Sensor - Ceiling mount | E96: SN-MW700C | F96: 1978 | J96: Position marked - I | L96: Prop
B97: Sensinova | C97: Basic Motion HF Microwave Sensor - Ceiling mount | E97: SN-MW700C | F97: 1978 | J97: Position marked - I | L97: Prop
C98: KNX Cable - Kordz- 103 mts | E98: Nil | F98: 62830 | J98: Position marked - I | L98: Prop
A100: Home Theatre Audio | B100: Platin Audio | C100: Platin Audio 5.1.2 System | E100: Platin 5.1.2 | F100: 162500 | G100: 15000 | J100: Position marked - I | L100: Prop
C101: HDMI Cable - 3 Mtr | E101: NIL | F101: 450 | J101: Position marked - I | L101: Prop

Sheet Haaran Automation
B1: Client Name | C1: Haaran Automation | E1: 9566138496 | F1: Overall site status | J1: Count | K1: % | M1: Material status | N1: Count | O1: % | Q1: Visti No. | R1: IR No. | S1: Date
